Workbook

Sheet Analysis Summary
B3: Clackamas Town Center - Sales Analysis Summary
B5: Property Overview
B6: T-12 Period: | C6: ='Property Summary'!D2 -> 6/2024-5/2025 | E6: Placer Visits: | F6: ='Property Summary'!E2 -> 9376877 | H6: Trade Area Pop: | I6: ='Property Summary'!F2 -> 812175
B7: Inline Sales PSF: | C7: ='Property Summary'!I2 -> 615.0883 | E7: AHHI: | F7: ='Property Summary'!G2 -> 110808.28 | H7: Gross Rent PSF: | I7: ='Property Summary'!J2 -> 83.116846
B8: Total Occ Cost: | C8: ='Property Summary'!K2 -> 0.16065159 | E8: Set Avg Occ Cost: | F8: =AVERAGEIFS('Property Summary'!K$2:K$49,'Property Summary'!B$2:B$49,"Y",'Property Summary'!K$2:K$49,"<>") -> 0.14227871 | H8: Spread: | I8: ='Property Summary'!K2-AVERAGEIFS('Property Summary'!K$2:K$49,'Property Summary'!B$2:B$49,"Y",'Property Summary'!K$2:K$49,"<>") -> 0.018372882
B10: Methodology
B11: Comp set: 48 properties from the Select Asset Sales Comp. Inline tenants only (<10,000 SF). Sales PSF = total category sales / total category SQFT per property, averaged across set (excluding properties with $0 in category). All formulas reference the Tenant Data sheet. Toggle property inclusion on Property Summary col B.
B13: Total Inline Occupancy Cost - All Properties (Reporting Tenants Only)
B14: Property | C14: Sales PSF (ex Apple) | D14: Occ Cost | E14: Placer Visits | F14: AHHI | G14: Tenant Count
B15: Oklahoma City Collection | C15: =IF('Property Summary'!B32="Y",'Property Summary'!I32,"") -> 725.6863 | D15: =IF('Property Summary'!B32="Y",'Property Summary'!K32,"") -> 0.10212611 | E15: =IF('Property Summary'!B32="Y",'Property Summary'!E32,"") -> 6191968 | F15: =IF('Property Summary'!B32="Y",'Property Summary'!G32,"") -> 304463.27 | G15: =IF('Property Summary'!B32="Y",'Property Summary'!L32,"") -> 74
B16: Belmar | C16: =IF('Property Summary'!B6="Y",'Property Summary'!I6,"") -> 374.60868 | D16: =IF('Property Summary'!B6="Y",'Property Summary'!K6,"") -> 0.10331773 | E16: =IF('Property Summary'!B6="Y",'Property Summary'!E6,"") -> 7490755 | F16: =IF('Property Summary'!B6="Y",'Property Summary'!G6,"") -> 116194.71 | G16: =IF('Property Summary'!B6="Y",'Property Summary'!L6,"") -> 42
B17: LaCenterra at Cinco Ranch | C17: =IF('Property Summary'!B23="Y",'Property Summary'!I23,"") -> 706.70925 | D17: =IF('Property Summary'!B23="Y",'Property Summary'!K23,"") -> 0.10727303 | E17: =IF('Property Summary'!B23="Y",'Property Summary'!E23,"") -> 5076169 | F17: =IF('Property Summary'!B23="Y",'Property Summary'!G23,"") -> 144646.46 | G17: =IF('Property Summary'!B23="Y",'Property Summary'!L23,"") -> 86
B18: Bridge Street Towne Centre | C18: =IF('Property Summary'!B9="Y",'Property Summary'!I9,"") -> 606.2783 | D18: =IF('Property Summary'!B9="Y",'Property Summary'!K9,"") -> 0.1100116 | E18: =IF('Property Summary'!B9="Y",'Property Summary'!E9,"") -> 6217908 | F18: =IF('Property Summary'!B9="Y",'Property Summary'!G9,"") -> 109737.91 | G18: =IF('Property Summary'!B9="Y",'Property Summary'!L9,"") -> 70
B19: Mayfaire Town Center | C19: =IF('Property Summary'!B29="Y",'Property Summary'!I29,"") -> 484.02415 | D19: =IF('Property Summary'!B29="Y",'Property Summary'!K29,"") -> 0.11495173 | E19: =IF('Property Summary'!B29="Y",'Property Summary'!E29,"") -> 6047693 | F19: =IF('Property Summary'!B29="Y",'Property Summary'!G29,"") -> 116236.91 | G19: =IF('Property Summary'!B29="Y",'Property Summary'!L29,"") -> 73
B20: Mall at Wellington Green | C20: =IF('Property Summary'!B27="Y",'Property Summary'!I27,"") -> 496.34618 | D20: =IF('Property Summary'!B27="Y",'Property Summary'!K27,"") -> 0.11613297 | E20: =IF('Property Summary'!B27="Y",'Property Summary'!E27,"") -> 5009861 | F20: =IF('Property Summary'!B27="Y",'Property Summary'!G27,"") -> 100971.33 | G20: =IF('Property Summary'!B27="Y",'Property Summary'!L27,"") -> 83
B21: Mall at Partridge Creek | C21: =IF('Property Summary'!B25="Y",'Property Summary'!I25,"") -> 396.72978 | D21: =IF('Property Summary'!B25="Y",'Property Summary'!K25,"") -> 0.11859121 | E21: =IF('Property Summary'!B25="Y",'Property Summary'!E25,"") -> 4184715 | F21: =IF('Property Summary'!B25="Y",'Property Summary'!G25,"") -> 98824.38 | G21: =IF('Property Summary'!B25="Y",'Property Summary'!L25,"") -> 61
B22: Mesa Mall | C22: =IF('Property Summary'!B30="Y",'Property Summary'!I30,"") -> 384.09084 | D22: =IF('Property Summary'!B30="Y",'Property Summary'!K30,"") -> 0.11888943 | E22: =IF('Property Summary'!B30="Y",'Property Summary'!E30,"") -> 7396278 | F22: =IF('Property Summary'!B30="Y",'Property Summary'!G30,"") -> 86600.37 | G22: =IF('Property Summary'!B30="Y",'Property Summary'!L30,"") -> 68
B23: Hamilton Place Mall | C23: =IF('Property Summary'!B20="Y",'Property Summary'!I20,"") -> 489.11863 | D23: =IF('Property Summary'!B20="Y",'Property Summary'!K20,"") -> 0.12103796 | E23: =IF('Property Summary'!B20="Y",'Property Summary'!E20,"") -> 7021524 | F23: =IF('Property Summary'!B20="Y",'Property Summary'!G20,"") -> 99241.52 | G23: =IF('Property Summary'!B20="Y",'Property Summary'!L20,"") -> 99
B24: Willow Grove Park | C24: =IF('Property Summary'!B49="Y",'Property Summary'!I49,"") -> 557.27661 | D24: =IF('Property Summary'!B49="Y",'Property Summary'!K49,"") -> 0.12179287 | E24: =IF('Property Summary'!B49="Y",'Property Summary'!E49,"") -> 5160995 | F24: =IF('Property Summary'!B49="Y",'Property Summary'!G49,"") -> 105000 | G24: =IF('Property Summary'!B49="Y",'Property Summary'!L49,"") -> 37
B25: Scottsdale Quarter | C25: =IF('Property Summary'!B37="Y",'Property Summary'!I37,"") -> 1042.2429 | D25: =IF('Property Summary'!B37="Y",'Property Summary'!K37,"") -> 0.1220669 | E25: =IF('Property Summary'!B37="Y",'Property Summary'!E37,"") -> 4531037 | F25: =IF('Property Summary'!B37="Y",'Property Summary'!G37,"") -> 137148.56 | G25: =IF('Property Summary'!B37="Y",'Property Summary'!L37,"") -> 95
B26: West Towne Mall | C26: =IF('Property Summary'!B47="Y",'Property Summary'!I47,"") -> 404.91999 | D26: =IF('Property Summary'!B47="Y",'Property Summary'!K47,"") -> 0.12263295 | E26: =IF('Property Summary'!B47="Y",'Property Summary'!E47,"") -> 7476751 | F26: =IF('Property Summary'!B47="Y",'Property Summary'!G47,"") -> 113018.03 | G26: =IF('Property Summary'!B47="Y",'Property Summary'!L47,"") -> 76
B27: Brandon Exchange | C27: =IF('Property Summary'!B7="Y",'Property Summary'!I7,"") -> 655.83465 | D27: =IF('Property Summary'!B7="Y",'Property Summary'!K7,"") -> 0.12516513 | E27: =IF('Property Summary'!B7="Y",'Property Summary'!E7,"") -> 6850096 | F27: =IF('Property Summary'!B7="Y",'Property Summary'!G7,"") -> 93025.38 | G27: =IF('Property Summary'!B7="Y",'Property Summary'!L7,"") -> 101
B28: Pearland Town Center | C28: =IF('Property Summary'!B35="Y",'Property Summary'!I35,"") -> 383.83986 | D28: =IF('Property Summary'!B35="Y",'Property Summary'!K35,"") -> 0.12524162 | E28: =IF('Property Summary'!B35="Y",'Property Summary'!E35,"") -> 6077754 | F28: =IF('Property Summary'!B35="Y",'Property Summary'!G35,"") -> 126295.43 | G28: =IF('Property Summary'!B35="Y",'Property Summary'!L35,"") -> 91
B29: SouthPark Mall (OH) | C29: =IF('Property Summary'!B39="Y",'Property Summary'!I39,"") -> 399.91307 | D29: =IF('Property Summary'!B39="Y",'Property Summary'!K39,"") -> 0.12530479 | E29: =IF('Property Summary'!B39="Y",'Property Summary'!E39,"") -> 7531055 | F29: =IF('Property Summary'!B39="Y",'Property Summary'!G39,"") -> 88347.35 | G29: =IF('Property Summary'!B39="Y",'Property Summary'!L39,"") -> 95
B30: Crossgates Center | C30: =IF('Property Summary'!B16="Y",'Property Summary'!I16,"") -> 503.303 | D30: =IF('Property Summary'!B16="Y",'Property Summary'!K16,"") -> 0.12642244 | E30: =IF('Property Summary'!B16="Y",'Property Summary'!E16,"") -> 8839014 | F30: =IF('Property Summary'!B16="Y",'Property Summary'!G16,"") -> 100046.57 | G30: =IF('Property Summary'!B16="Y",'Property Summary'!L16,"") -> 75
B31: Oak Park Mall | C31: =IF('Property Summary'!B31="Y",'Property Summary'!I31,"") -> 561.77993 | D31: =IF('Property Summary'!B31="Y",'Property Summary'!K31,"") -> 0.12687737 | E31: =IF('Property Summary'!B31="Y",'Property Summary'!E31,"") -> 9415595 | F31: =IF('Property Summary'!B31="Y",'Property Summary'!G31,"") -> 111468.63 | G31: =IF('Property Summary'!B31="Y",'Property Summary'!L31,"") -> 107
B32: Liberty Center | C32: =IF('Property Summary'!B24="Y",'Property Summary'!I24,"") -> 430.2977 | D32: =IF('Property Summary'!B24="Y",'Property Summary'!K24,"") -> 0.12919602 | E32: =IF('Property Summary'!B24="Y",'Property Summary'!E24,"") -> 6380250 | F32: =IF('Property Summary'!B24="Y",'Property Summary'!G24,"") -> 107163.69 | G32: =IF('Property Summary'!B24="Y",'Property Summary'!L24,"") -> 71
B33: West County Center | C33: =IF('Property Summary'!B46="Y",'Property Summary'!I46,"") -> 683.68095 | D33: =IF('Property Summary'!B46="Y",'Property Summary'!K46,"") -> 0.13019321 | E33: =IF('Property Summary'!B46="Y",'Property Summary'!E46,"") -> 7072500 | F33: =IF('Property Summary'!B46="Y",'Property Summary'!G46,"") -> 120521 | G33: =IF('Property Summary'!B46="Y",'Property Summary'!L46,"") -> 95
B34: The Shops At Evergreen Walk | C34: =IF('Property Summary'!B42="Y",'Property Summary'!I42,"") -> 510.44745 | D34: =IF('Property Summary'!B42="Y",'Property Summary'!K42,"") -> 0.13142369 | E34: =IF('Property Summary'!B42="Y",'Property Summary'!E42,"") -> 3661226 | F34: =IF('Property Summary'!B42="Y",'Property Summary'!G42,"") -> 103025.54 | G34: =IF('Property Summary'!B42="Y",'Property Summary'!L42,"") -> 42
B35: Hanes Mall | C35: =IF('Property Summary'!B21="Y",'Property Summary'!I21,"") -> 405.40898 | D35: =IF('Property Summary'!B21="Y",'Property Summary'!K21,"") -> 0.13245697 | E35: =IF('Property Summary'!B21="Y",'Property Summary'!E21,"") -> 8597850 | F35: =IF('Property Summary'!B21="Y",'Property Summary'!G21,"") -> 86092.68 | G35: =IF('Property Summary'!B21="Y",'Property Summary'!L21,"") -> 108
B36: Annapolis Town Center | C36: =IF('Property Summary'!B4="Y",'Property Summary'!I4,"") -> 516.97672 | D36: =IF('Property Summary'!B4="Y",'Property Summary'!K4,"") -> 0.13606986 | E36: =IF('Property Summary'!B4="Y",'Property Summary'!E4,"") -> 5278675 | F36: =IF('Property Summary'!B4="Y",'Property Summary'!G4,"") -> 158600.14 | G36: =IF('Property Summary'!B4="Y",'Property Summary'!L4,"") -> 28
B37: Coastal Grand Mall | C37: =IF('Property Summary'!B12="Y",'Property Summary'!I12,"") -> 433.53269 | D37: =IF('Property Summary'!B12="Y",'Property Summary'!K12,"") -> 0.13689809 | E37: =IF('Property Summary'!B12="Y",'Property Summary'!E12,"") -> 5952111 | F37: =IF('Property Summary'!B12="Y",'Property Summary'!G12,"") -> 89321.41 | G37: =IF('Property Summary'!B12="Y",'Property Summary'!L12,"") -> 86
B38: Mall del Norte | C38: =IF('Property Summary'!B28="Y",'Property Summary'!I28,"") -> 468.53189 | D38: =IF('Property Summary'!B28="Y",'Property Summary'!K28,"") -> 0.13763678 | E38: =IF('Property Summary'!B28="Y",'Property Summary'!E28,"") -> 6444269 | F38: =IF('Property Summary'!B28="Y",'Property Summary'!G28,"") -> 83955 | G38: =IF('Property Summary'!B28="Y",'Property Summary'!L28,"") -> 70
B39: Fayette Mall | C39: =IF('Property Summary'!B18="Y",'Property Summary'!I18,"") -> 513.06433 | D39: =IF('Property Summary'!B18="Y",'Property Summary'!K18,"") -> 0.13856449 | E39: =IF('Property Summary'!B18="Y",'Property Summary'!E18,"") -> 7576017 | F39: =IF('Property Summary'!B18="Y",'Property Summary'!G18,"") -> 97053.18 | G39: =IF('Property Summary'!B18="Y",'Property Summary'!L18,"") -> 101
B40: Capital City Mall | C40: =IF('Property Summary'!B11="Y",'Property Summary'!I11,"") -> 467.54888 | D40: =IF('Property Summary'!B11="Y",'Property Summary'!K11,"") -> 0.14143738 | E40: =IF('Property Summary'!B11="Y",'Property Summary'!E11,"") -> 4655717 | F40: =IF('Property Summary'!B11="Y",'Property Summary'!G11,"") -> 99569 | G40: =IF('Property Summary'!B11="Y",'Property Summary'!L11,"") -> 71
B41: Providence Place | C41: =IF('Property Summary'!B36="Y",'Property Summary'!I36,"") -> 543.60095 | D41: =IF('Property Summary'!B36="Y",'Property Summary'!K36,"") -> 0.14178105 | E41: =IF('Property Summary'!B36="Y",'Property Summary'!E36,"") -> 6728617 | F41: =IF('Property Summary'!B36="Y",'Property Summary'!G36,"") -> 96480.19 | G41: =IF('Property Summary'!B36="Y",'Property Summary'!L36,"") -> 64
B42: Paddock Mall | C42: =IF('Property Summary'!B33="Y",'Property Summary'!I33,"") -> 542.2408 | D42: =IF('Property Summary'!B33="Y",'Property Summary'!K33,"") -> 0.14252952 | E42: =IF('Property Summary'!B33="Y",'Property Summary'!E33,"") -> 3312527 | F42: =IF('Property Summary'!B33="Y",'Property Summary'!G33,"") -> 82408 | G42: =IF('Property Summary'!B33="Y",'Property Summary'!L33,"") -> 59
B43: Southgate Mall | C43: =IF('Property Summary'!B40="Y",'Property Summary'!I40,"") -> 356.40139 | D43: =IF('Property Summary'!B40="Y",'Property Summary'!K40,"") -> 0.14360092 | E43: =IF('Property Summary'!B40="Y",'Property Summary'!E40,"") -> 5040890 | F43: =IF('Property Summary'!B40="Y",'Property Summary'!G40,"") -> 93119.05 | G43: =IF('Property Summary'!B40="Y",'Property Summary'!L40,"") -> 48
B44: CoolSprings Galleria | C44: =IF('Property Summary'!B13="Y",'Property Summary'!I13,"") -> 542.23444 | D44: =IF('Property Summary'!B13="Y",'Property Summary'!K13,"") -> 0.14441173 | E44: =IF('Property Summary'!B13="Y",'Property Summary'!E13,"") -> 5760072 | F44: =IF('Property Summary'!B13="Y",'Property Summary'!G13,"") -> 148339.87 | G44: =IF('Property Summary'!B13="Y",'Property Summary'!L13,"") -> 112
B45: Crabtree Valley Mall | C45: =IF('Property Summary'!B14="Y",'Property Summary'!I14,"") -> 794.4337 | D45: =IF('Property Summary'!B14="Y",'Property Summary'!K14,"") -> 0.1457247 | E45: =IF('Property Summary'!B14="Y",'Property Summary'!E14,"") -> 8462931 | F45: =IF('Property Summary'!B14="Y",'Property Summary'!G14,"") -> 122880.68 | G45: =IF('Property Summary'!B14="Y",'Property Summary'!L14,"") -> 90
B46: Kansas City Collection | C46: =IF('Property Summary'!B22="Y",'Property Summary'!I22,"") -> 562.47751 | D46: =IF('Property Summary'!B22="Y",'Property Summary'!K22,"") -> 0.14978846 | E46: =IF('Property Summary'!B22="Y",'Property Summary'!E22,"") -> 6544586 | F46: =IF('Property Summary'!B22="Y",'Property Summary'!G22,"") -> 138167.97 | G46: =IF('Property Summary'!B22="Y",'Property Summary'!L22,"") -> 88
B47: Destiny USA | C47: =IF('Property Summary'!B17="Y",'Property Summary'!I17,"") -> 422.36789 | D47: =IF('Property Summary'!B17="Y",'Property Summary'!K17,"") -> 0.15163519 | E47: =IF('Property Summary'!B17="Y",'Property Summary'!E17,"") -> 8448382 | F47: =IF('Property Summary'!B17="Y",'Property Summary'!G17,"") -> 85449.32 | G47: =IF('Property Summary'!B17="Y",'Property Summary'!L17,"") -> 139
B48: Bridgewater Commons | C48: =IF('Property Summary'!B10="Y",'Property Summary'!I10,"") -> 606.70036 | D48: =IF('Property Summary'!B10="Y",'Property Summary'!K10,"") -> 0.1564615 | E48: =IF('Property Summary'!B10="Y",'Property Summary'!E10,"") -> 5816055 | F48: =IF('Property Summary'!B10="Y",'Property Summary'!G10,"") -> 161034.37 | G48: =IF('Property Summary'!B10="Y",'Property Summary'!L10,"") -> 106
B49: Arden Fair Mall | C49: =IF('Property Summary'!B5="Y",'Property Summary'!I5,"") -> 690.82267 | D49: =IF('Property Summary'!B5="Y",'Property Summary'!K5,"") -> 0.1590532 | E49: =IF('Property Summary'!B5="Y",'Property Summary'!E5,"") -> 7097365 | F49: =IF('Property Summary'!B5="Y",'Property Summary'!G5,"") -> 105913.35 | G49: =IF('Property Summary'!B5="Y",'Property Summary'!L5,"") -> 78
B50: Clackamas Town Center | C50: =IF('Property Summary'!B2="Y",'Property Summary'!I2,"") -> 615.0883 | D50: =IF('Property Summary'!B2="Y",'Property Summary'!K2,"") -> 0.16065159 | E50: =IF('Property Summary'!B2="Y",'Property Summary'!E2,"") -> 9376877 | F50: =IF('Property Summary'!B2="Y",'Property Summary'!G2,"") -> 110808.28 | G50: =IF('Property Summary'!B2="Y",'Property Summary'!L2,"") -> 109 | H50: <-
B51: Walden Galleria | C51: =IF('Property Summary'!B45="Y",'Property Summary'!I45,"") -> 504.44049 | D51: =IF('Property Summary'!B45="Y",'Property Summary'!K45,"") -> 0.16148041 | E51: =IF('Property Summary'!B45="Y",'Property Summary'!E45,"") -> 8449098 | F51: =IF('Property Summary'!B45="Y",'Property Summary'!G45,"") -> 86005.81 | G51: =IF('Property Summary'!B45="Y",'Property Summary'!L45,"") -> 118
B52: Galleria at Tyler | C52: =IF('Property Summary'!B19="Y",'Property Summary'!I19,"") -> 778.06495 | D52: =IF('Property Summary'!B19="Y",'Property Summary'!K19,"") -> 0.16483324 | E52: =IF('Property Summary'!B19="Y",'Property Summary'!E19,"") -> 9034300 | F52: =IF('Property Summary'!B19="Y",'Property Summary'!G19,"") -> 114749.55 | G52: =IF('Property Summary'!B19="Y",'Property Summary'!L19,"") -> 118
B53: Cross Creek Mall | C53: =IF('Property Summary'!B15="Y",'Property Summary'!I15,"") -> 503.85373 | D53: =IF('Property Summary'!B15="Y",'Property Summary'!K15,"") -> 0.17104969 | E53: =IF('Property Summary'!B15="Y",'Property Summary'!E15,"") -> 6974859 | F53: =IF('Property Summary'!B15="Y",'Property Summary'!G15,"") -> 76450.46 | G53: =IF('Property Summary'!B15="Y",'Property Summary'!L15,"") -> 92
B54: Annapolis Mall | C54: =IF('Property Summary'!B3="Y",'Property Summary'!I3,"") -> 522.44917 | D54: =IF('Property Summary'!B3="Y",'Property Summary'!K3,"") -> 0.18015803 | E54: =IF('Property Summary'!B3="Y",'Property Summary'!E3,"") -> 7274990 | F54: =IF('Property Summary'!B3="Y",'Property Summary'!G3,"") -> 139445.69 | G54: =IF('Property Summary'!B3="Y",'Property Summary'!L3,"") -> 109
B55: Towson Town Center | C55: =IF('Property Summary'!B43="Y",'Property Summary'!I43,"") -> 541.7206 | D55: =IF('Property Summary'!B43="Y",'Property Summary'!K43,"") -> 0.1816442 | E55: =IF('Property Summary'!B43="Y",'Property Summary'!E43,"") -> 5089752 | F55: =IF('Property Summary'!B43="Y",'Property Summary'!G43,"") -> 100706.98 | G55: =IF('Property Summary'!B43="Y",'Property Summary'!L43,"") -> 75
B56: Palisades Center | C56: =IF('Property Summary'!B34="Y",'Property Summary'!I34,"") -> 467.97186 | D56: =IF('Property Summary'!B34="Y",'Property Summary'!K34,"") -> 0.18166508 | E56: =IF('Property Summary'!B34="Y",'Property Summary'!E34,"") -> 11774167 | F56: =IF('Property Summary'!B34="Y",'Property Summary'!G34,"") -> 98587.01 | G56: =IF('Property Summary'!B34="Y",'Property Summary'!L34,"") -> 117
B57: Mall at Prince Georges | C57: =IF('Property Summary'!B26="Y",'Property Summary'!I26,"") -> 531.76509 | D57: =IF('Property Summary'!B26="Y",'Property Summary'!K26,"") -> 0.18469715 | E57: =IF('Property Summary'!B26="Y",'Property Summary'!E26,"") -> 7640998 | F57: =IF('Property Summary'!B26="Y",'Property Summary'!G26,"") -> 127085 | G57: =IF('Property Summary'!B26="Y",'Property Summary'!L26,"") -> 79
B58: Westfarms Mall | C58: =IF('Property Summary'!B48="Y",'Property Summary'!I48,"") -> 715.85164 | D58: =IF('Property Summary'!B48="Y",'Property Summary'!K48,"") -> 0.20650364 | E58: =IF('Property Summary'!B48="Y",'Property Summary'!E48,"") -> 7186476 | F58: =IF('Property Summary'!B48="Y",'Property Summary'!G48,"") -> 106619.23 | G58: =IF('Property Summary'!B48="Y",'Property Summary'!L48,"") -> 126
B59: SoNo Collection | C59: =IF('Property Summary'!B38="Y",'Property Summary'!I38,"") -> 428.6808 | D59: =IF('Property Summary'!B38="Y",'Property Summary'!K38,"") -> 0.20655638 | E59: =IF('Property Summary'!B38="Y",'Property Summary'!E38,"") -> 2668507 | F59: =IF('Property Summary'!B38="Y",'Property Summary'!G38,"") -> 125000 | G59: =IF('Property Summary'!B38="Y",'Property Summary'!L38,"") -> 37
B60: Staten Island Mall | C60: =IF('Property Summary'!B41="Y",'Property Summary'!I41,"") -> 627.59743 | D60: =IF('Property Summary'!B41="Y",'Property Summary'!K41,"") -> 0.21804183 | E60: =IF('Property Summary'!B41="Y",'Property Summary'!E41,"") -> 10358762 | F60: =IF('Property Summary'!B41="Y",'Property Summary'!G41,"") -> 123204.9 | G60: =IF('Property Summary'!B41="Y",'Property Summary'!L41,"") -> 126
B61: Tysons Corner | C61: =IF('Property Summary'!B44="Y",'Property Summary'!I44,"") -> 974.18292 | D61: =IF('Property Summary'!B44="Y",'Property Summary'!K44,"") -> 0.2553982 | E61: =IF('Property Summary'!B44="Y",'Property Summary'!E44,"") -> 15515177 | F61: =IF('Property Summary'!B44="Y",'Property Summary'!G44,"") -> 173791.28 | G61: =IF('Property Summary'!B44="Y",'Property Summary'!L44,"") -> 180
B62: Briarwood Mall | C62: =IF('Property Summary'!B8="Y",'Property Summary'!I8,"") -> 36.056095 | D62: =IF('Property Summary'!B8="Y",'Property Summary'!K8,"") -> 0 | E62: =IF('Property Summary'!B8="Y",'Property Summary'!E8,"") -> 3417309 | F62: =IF('Property Summary'!B8="Y",'Property Summary'!G8,"") -> 112360.61 | G62: =IF('Property Summary'!B8="Y",'Property Summary'!L8,"") -> 67
B63: Set Average | C63: =AVERAGEIFS('Property Summary'!I$2:I$49,'Property Summary'!B$2:B$49,"Y",'Property Summary'!I$2:I$49,"<>") -> 539.81655 | D63: =AVERAGEIFS('Property Summary'!K$2:K$49,'Property Summary'!B$2:B$49,"Y",'Property Summary'!K$2:K$49,"<>") -> 0.14227871
B65: Clackamas Town Center vs Set Average (Sales PSF by Category)
B66: Category | C66: Clackamas PSF | D66: Set Avg PSF | E66: Variance | F66: % Diff
B67: Apparel | C67: =IFERROR(_CategoryCalc!B2,"") -> 413.19437 | D67: =IFERROR(AVERAGEIFS(_CategoryCalc!B$2:B$49,_CategoryCalc!AY$2:AY$49,"Y",_CategoryCalc!B$2:B$49,"<>"),"") -> 387.88826 | E67: =IFERROR(C67-D67,"") -> 25.306114 | F67: =IFERROR(E67/D67,"") -> 0.065240731
B68: Shoes | C68: =IFERROR(_CategoryCalc!C2,"") -> 719.05625 | D68: =IFERROR(AVERAGEIFS(_CategoryCalc!C$2:C$49,_CategoryCalc!AY$2:AY$49,"Y",_CategoryCalc!C$2:C$49,"<>"),"") -> 526.38637 | E68: =IFERROR(C68-D68,"") -> 192.66988 | F68: =IFERROR(E68/D68,"") -> 0.36602369
B69: Jewelry | C69: =IFERROR(_CategoryCalc!D2,"") -> 1075.6566 | D69: =IFERROR(AVERAGEIFS(_CategoryCalc!D$2:D$49,_CategoryCalc!AY$2:AY$49,"Y",_CategoryCalc!D$2:D$49,"<>"),"") -> 1037.5323 | E69: =IFERROR(C69-D69,"") -> 38.124317 | F69: =IFERROR(E69/D69,"") -> 0.036745187
B70: Health & Beauty | C70: =IFERROR(_CategoryCalc!E2,"") -> 1096.7614 | D70: =IFERROR(AVERAGEIFS(_CategoryCalc!E$2:E$49,_CategoryCalc!AY$2:AY$49,"Y",_CategoryCalc!E$2:E$49,"<>"),"") -> 845.55319 | E70: =IFERROR(C70-D70,"") -> 251.20819 | F70: =IFERROR(E70/D70,"") -> 0.29709331
B71: Food & Beverage | C71: =IFERROR(_CategoryCalc!F2,"") -> 893.99749 | D71: =IFERROR(AVERAGEIFS(_CategoryCalc!F$2:F$49,_CategoryCalc!AY$2:AY$49,"Y",_CategoryCalc!F$2:F$49,"<>"),"") -> 913.41798 | E71: =IFERROR(C71-D71,"") -> -19.42049 | F71: =IFERROR(E71/D71,"") -> -0.02126134
B72: Restaurant | C72: =IFERROR(_CategoryCalc!G2,"") -> 844.24471 | D72: =IFERROR(AVERAGEIFS(_CategoryCalc!G$2:G$49,_CategoryCalc!AY$2:AY$49,"Y",_CategoryCalc!G$2:G$49,"<>"),"") -> 777.00471 | E72: =IFERROR(C72-D72,"") -> 67.240002 | F72: =IFERROR(E72/D72,"") -> 0.086537444
B73: Hobby & Novelty | C73: =IFERROR(_CategoryCalc!H2,"") -> 458.75527 | D73: =IFERROR(AVERAGEIFS(_CategoryCalc!H$2:H$49,_CategoryCalc!AY$2:AY$49,"Y",_CategoryCalc!H$2:H$49,"<>"),"") -> 441.21772 | E73: =IFERROR(C73-D73,"") -> 17.537556 | F73: =IFERROR(E73/D73,"") -> 0.039748076
B74: Service | C74: =IFERROR(_CategoryCalc!I2,"") -> 398.207 | D74: =IFERROR(AVERAGEIFS(_CategoryCalc!I$2:I$49,_CategoryCalc!AY$2:AY$49,"Y",_CategoryCalc!I$2:I$49,"<>"),"") -> 470.30923 | E74: =IFERROR(C74-D74,"") -> -72.10223 | F74: =IFERROR(E74/D74,"") -> -0.15330813
B75: Tech | C75: =IFERROR(_CategoryCalc!J2,"") -> 513.13136 | D75: =IFERROR(AVERAGEIFS(_CategoryCalc!J$2:J$49,_CategoryCalc!AY$2:AY$49,"Y",_CategoryCalc!J$2:J$49,"<>"),"") -> 763.56959 | E75: =IFERROR(C75-D75,"") -> -250.43824 | F75: =IFERROR(E75/D75,"") -> -0.32798351
B76: Major | C76: =IFERROR(_CategoryCalc!K2,"") -> 511.38991 | D76: =IFERROR(AVERAGEIFS(_CategoryCalc!K$2:K$49,_CategoryCalc!AY$2:AY$49,"Y",_CategoryCalc!K$2:K$49,"<>"),"") -> 757.13814 | E76: =IFERROR(C76-D76,"") -> -245.74823 | F76: =IFERROR(E76/D76,"") -> -0.32457515
B77: Anchor | C77: =IFERROR(_CategoryCalc!L2,"") | D77: =IFERROR(AVERAGEIFS(_CategoryCalc!L$2:L$49,_CategoryCalc!AY$2:AY$49,"Y",_CategoryCalc!L$2:L$49,"<>"),"") | E77: =IFERROR(C77-D77,"") | F77: =IFERROR(E77/D77,"")
B78: Apple | C78: =IFERROR(_CategoryCalc!M2,"") | D78: =IFERROR(AVERAGEIFS(_CategoryCalc!M$2:M$49,_CategoryCalc!AY$2:AY$49,"Y",_CategoryCalc!M$2:M$49,"<>"),"") -> 5692.7099 | E78: =IFERROR(C78-D78,"") | F78: =IFERROR(E78/D78,"")
B80: SQFT Allocation - Clackamas Town Center vs Set Average
B81: Category | C81: Clackamas % | D81: Set Avg % | E81: Difference
B82: Apparel | C82: =IFERROR(_CategoryCalc!AL2/SUM(_CategoryCalc!AL$2:AW$2),"") -> 0.35270791 | D82: =IFERROR(SUMPRODUCT((_CategoryCalc!AY$2:AY$49="Y")*_CategoryCalc!AL$2:AL$49)/SUMPRODUCT((_CategoryCalc!AY$2:AY$49="Y")*_CategoryCalc!AZ$2:AZ$49),"") -> 0.42993583 | E82: =IFERROR(C82-D82,"") -> -0.077227921
B83: Shoes | C83: =IFERROR(_CategoryCalc!AM2/SUM(_CategoryCalc!AL$2:AW$2),"") -> 0.085182523 | D83: =IFERROR(SUMPRODUCT((_CategoryCalc!AY$2:AY$49="Y")*_CategoryCalc!AM$2:AM$49)/SUMPRODUCT((_CategoryCalc!AY$2:AY$49="Y")*_CategoryCalc!AZ$2:AZ$49),"") -> 0.11630914 | E83: =IFERROR(C83-D83,"") -> -0.031126619
B84: Jewelry | C84: =IFERROR(_CategoryCalc!AN2/SUM(_CategoryCalc!AL$2:AW$2),"") -> 0.041417436 | D84: =IFERROR(SUMPRODUCT((_CategoryCalc!AY$2:AY$49="Y")*_CategoryCalc!AN$2:AN$49)/SUMPRODUCT((_CategoryCalc!AY$2:AY$49="Y")*_CategoryCalc!AZ$2:AZ$49),"") -> 0.050665039 | E84: =IFERROR(C84-D84,"") -> -0.0092476031
B85: Health & Beauty | C85: =IFERROR(_CategoryCalc!AO2/SUM(_CategoryCalc!AL$2:AW$2),"") -> 0.04841985 | D85: =IFERROR(SUMPRODUCT((_CategoryCalc!AY$2:AY$49="Y")*_CategoryCalc!AO$2:AO$49)/SUMPRODUCT((_CategoryCalc!AY$2:AY$49="Y")*_CategoryCalc!AZ$2:AZ$49),"") -> 0.056206033 | E85: =IFERROR(C85-D85,"") -> -0.0077861827
B86: Food & Beverage | C86: =IFERROR(_CategoryCalc!AP2/SUM(_CategoryCalc!AL$2:AW$2),"") -> 0.088256215 | D86: =IFERROR(SUMPRODUCT((_CategoryCalc!AY$2:AY$49="Y")*_CategoryCalc!AP$2:AP$49)/SUMPRODUCT((_CategoryCalc!AY$2:AY$49="Y")*_CategoryCalc!AZ$2:AZ$49),"") -> 0.039755901 | E86: =IFERROR(C86-D86,"") -> 0.048500314
B87: Restaurant | C87: =IFERROR(_CategoryCalc!AQ2/SUM(_CategoryCalc!AL$2:AW$2),"") -> 0.15630862 | D87: =IFERROR(SUMPRODUCT((_CategoryCalc!AY$2:AY$49="Y")*_CategoryCalc!AQ$2:AQ$49)/SUMPRODUCT((_CategoryCalc!AY$2:AY$49="Y")*_CategoryCalc!AZ$2:AZ$49),"") -> 0.12938162 | E87: =IFERROR(C87-D87,"") -> 0.026926999
B88: Hobby & Novelty | C88: =IFERROR(_CategoryCalc!AR2/SUM(_CategoryCalc!AL$2:AW$2),"") -> 0.10902021 | D88: =IFERROR(SUMPRODUCT((_CategoryCalc!AY$2:AY$49="Y")*_CategoryCalc!AR$2:AR$49)/SUMPRODUCT((_CategoryCalc!AY$2:AY$49="Y")*_CategoryCalc!AZ$2:AZ$49),"") -> 0.072056106 | E88: =IFERROR(C88-D88,"") -> 0.036964109
B89: Service | C89: =IFERROR(_CategoryCalc!AS2/SUM(_CategoryCalc!AL$2:AW$2),"") -> 0.098435513 | D89: =IFERROR(SUMPRODUCT((_CategoryCalc!AY$2:AY$49="Y")*_CategoryCalc!AS$2:AS$49)/SUMPRODUCT((_CategoryCalc!AY$2:AY$49="Y")*_CategoryCalc!AZ$2:AZ$49),"") -> 0.068224453 | E89: =IFERROR(C89-D89,"") -> 0.03021106
B90: Tech | C90: =IFERROR(_CategoryCalc!AT2/SUM(_CategoryCalc!AL$2:AW$2),"") -> 0.0074630991 | D90: =IFERROR(SUMPRODUCT((_CategoryCalc!AY$2:AY$49="Y")*_CategoryCalc!AT$2:AT$49)/SUMPRODUCT((_CategoryCalc!AY$2:AY$49="Y")*_CategoryCalc!AZ$2:AZ$49),"") -> 0.0085140728 | E90: =IFERROR(C90-D90,"") -> -0.0010509737
B91: Major | C91: =IFERROR(_CategoryCalc!AU2/SUM(_CategoryCalc!AL$2:AW$2),"") -> 0.012788619 | D91: =IFERROR(SUMPRODUCT((_CategoryCalc!AY$2:AY$49="Y")*_CategoryCalc!AU$2:AU$49)/SUMPRODUCT((_CategoryCalc!AY$2:AY$49="Y")*_CategoryCalc!AZ$2:AZ$49),"") -> 0.016090054 | E91: =IFERROR(C91-D91,"") -> -0.0033014348
B92: Anchor | C92: =IFERROR(_CategoryCalc!AV2/SUM(_CategoryCalc!AL$2:AW$2),"") -> 0 | D92: =IFERROR(SUMPRODUCT((_CategoryCalc!AY$2:AY$49="Y")*_CategoryCalc!AV$2:AV$49)/SUMPRODUCT((_CategoryCalc!AY$2:AY$49="Y")*_CategoryCalc!AZ$2:AZ$49),"") -> 0 | E92: =IFERROR(C92-D92,"") -> 0
B93: Apple | C93: =IFERROR(_CategoryCalc!AW2/SUM(_CategoryCalc!AL$2:AW$2),"") -> 0 | D93: =IFERROR(SUMPRODUCT((_CategoryCalc!AY$2:AY$49="Y")*_CategoryCalc!AW$2:AW$49)/SUMPRODUCT((_CategoryCalc!AY$2:AY$49="Y")*_CategoryCalc!AZ$2:AZ$49),"") -> 0.012861747 | E93: =IFERROR(C93-D93,"") -> -0.012861747
B95: Occupancy Cost by Category - Clackamas Town Center vs Set Avg (Reporting Tenants Only)
B96: Category | C96: Clackamas | D96: Set Avg | E96: Spread
B97: Apparel | C97: =IFERROR(_CategoryCalc!N2,"") -> 0.15771644 | D97: =IFERROR(AVERAGEIFS(_CategoryCalc!N$2:N$49,_CategoryCalc!AY$2:AY$49,"Y",_CategoryCalc!N$2:N$49,"<>"),"") -> 0.14269995 | E97: =IFERROR(C97-D97,"") -> 0.015016494
B98: Shoes | C98: =IFERROR(_CategoryCalc!O2,"") -> 0.15520489 | D98: =IFERROR(AVERAGEIFS(_CategoryCalc!O$2:O$49,_CategoryCalc!AY$2:AY$49,"Y",_CategoryCalc!O$2:O$49,"<>"),"") -> 0.15078862 | E98: =IFERROR(C98-D98,"") -> 0.004416268
B99: Jewelry | C99: =IFERROR(_CategoryCalc!P2,"") -> 0.14207045 | D99: =IFERROR(AVERAGEIFS(_CategoryCalc!P$2:P$49,_CategoryCalc!AY$2:AY$49,"Y",_CategoryCalc!P$2:P$49,"<>"),"") -> 0.14229044 | E99: =IFERROR(C99-D99,"") -> -0.00021998477
B100: Health & Beauty | C100: =IFERROR(_CategoryCalc!Q2,"") -> 0.15048798 | D100: =IFERROR(AVERAGEIFS(_CategoryCalc!Q$2:Q$49,_CategoryCalc!AY$2:AY$49,"Y",_CategoryCalc!Q$2:Q$49,"<>"),"") -> 0.14088327 | E100: =IFERROR(C100-D100,"") -> 0.009604713
B101: Food & Beverage | C101: =IFERROR(_CategoryCalc!R2,"") -> 0.17702937 | D101: =IFERROR(AVERAGEIFS(_CategoryCalc!R$2:R$49,_CategoryCalc!AY$2:AY$49,"Y",_CategoryCalc!R$2:R$49,"<>"),"") -> 0.17221318 | E101: =IFERROR(C101-D101,"") -> 0.0048161873
B102: Restaurant | C102: =IFERROR(_CategoryCalc!S2,"") -> 0.096162978 | D102: =IFERROR(AVERAGEIFS(_CategoryCalc!S$2:S$49,_CategoryCalc!AY$2:AY$49,"Y",_CategoryCalc!S$2:S$49,"<>"),"") -> 0.10409788 | E102: =IFERROR(C102-D102,"") -> -0.0079349064
B103: Hobby & Novelty | C103: =IFERROR(_CategoryCalc!T2,"") -> 0.21511691 | D103: =IFERROR(AVERAGEIFS(_CategoryCalc!T$2:T$49,_CategoryCalc!AY$2:AY$49,"Y",_CategoryCalc!T$2:T$49,"<>"),"") -> 0.14402118 | E103: =IFERROR(C103-D103,"") -> 0.071095733
B104: Service | C104: =IFERROR(_CategoryCalc!U2,"") -> 0.19911007 | D104: =IFERROR(AVERAGEIFS(_CategoryCalc!U$2:U$49,_CategoryCalc!AY$2:AY$49,"Y",_CategoryCalc!U$2:U$49,"<>"),"") -> 0.17268864 | E104: =IFERROR(C104-D104,"") -> 0.026421426
B105: Tech | C105: =IFERROR(_CategoryCalc!V2,"") -> 0.3350604 | D105: =IFERROR(AVERAGEIFS(_CategoryCalc!V$2:V$49,_CategoryCalc!AY$2:AY$49,"Y",_CategoryCalc!V$2:V$49,"<>"),"") -> 0.3158966 | E105: =IFERROR(C105-D105,"") -> 0.019163806
B106: Major | C106: =IFERROR(_CategoryCalc!W2,"") -> 0.18962048 | D106: =IFERROR(AVERAGEIFS(_CategoryCalc!W$2:W$49,_CategoryCalc!AY$2:AY$49,"Y",_CategoryCalc!W$2:W$49,"<>"),"") -> 0.15018268 | E106: =IFERROR(C106-D106,"") -> 0.0394378
B107: Anchor | C107: =IFERROR(_CategoryCalc!X2,"") | D107: =IFERROR(AVERAGEIFS(_CategoryCalc!X$2:X$49,_CategoryCalc!AY$2:AY$49,"Y",_CategoryCalc!X$2:X$49,"<>"),"") | E107: =IFERROR(C107-D107,"")
B108: Apple | C108: =IFERROR(_CategoryCalc!Y2,"") | D108: =IFERROR(AVERAGEIFS(_CategoryCalc!Y$2:Y$49,_CategoryCalc!AY$2:AY$49,"Y",_CategoryCalc!Y$2:Y$49,"<>"),"") -> 0.059797483 | E108: =IFERROR(C108-D108,"")
...

Sheet Property Summary
A1: Property | B1: Include | C1: Property Type | D1: T-12 Period | E1: Placer Visits | F1: Trade Area Pop | G1: AHHI | H1: Inline Sales PSF | I1: Inline Sales PSF (ex Apple) | J1: Inline Rent PSF | K1: Inline Occ Cost % | L1: Inline Count
A2: Clackamas Town Center | B2: Y | C2: Enclosed Mall | D2: 6/2024-5/2025 | E2: 9376877 | F2: 812175 | G2: 110808.28 | H2: =IF(B2="Y",IFERROR(SUMIFS('Tenant Data'!$F$2:$F$4674,'Tenant Data'!$A$2:$A$4674,A2,'Tenant Data'!$F$2:$F$4674,">0",'Tenant Data'!$E$2:$E$4674,"<10000")/SUMIFS('Tenant Data'!$E$2:$E$4674,'Tenant Data'!$A$2:$A$4674,A2,'Tenant Data'!$F$2:$F$4674,">0",'Tenant Data'!$E$2:$E$4674,"<10000"),""),"") -> 615.0883 | I2: =IF(B2="Y",IFERROR(SUMIFS('Tenant Data'!$F$2:$F$4674,'Tenant Data'!$A$2:$A$4674,A2,'Tenant Data'!$D$2:$D$4674,"<>Apple",'Tenant Data'!$F$2:$F$4674,">0",'Tenant Data'!$E$2:$E$4674,"<10000")/SUMIFS('Tenant Data'!$E$2:$E$4674,'Tenant Data'!$A$2:$A$4674,A2,'Tenant Data'!$D$2:$D$4674,"<>Apple",'Tenant Data'!$F$2:$F$4674,">0",'Tenant Data'!$E$2:$E$4674,"<10000"),""),"") -> 615.0883 | J2: =IF(B2="Y",IFERROR(SUMPRODUCT(('Tenant Data'!$A$2:$A$4674=A2)*('Tenant Data'!$F$2:$F$4674>0)*('Tenant Data'!$E$2:$E$4674<10000)*'Tenant Data'!$I$2:$I$4674*'Tenant Data'!$E$2:$E$4674)/SUMPRODUCT(('Tenant Data'!$A$2:$A$4674=A2)*('Tenant Data'!$F$2:$F$4674>0)*('Tenant Data'!$E$2:$E$4674<10000)*'Tenant Data'!$E$2:$E$4674),""),"") -> 83.116846 | K2: =IF(B2="Y",IFERROR(SUMPRODUCT(('Tenant Data'!$A$2:$A$4674=A2)*('Tenant Data'!$F$2:$F$4674>0)*('Tenant Data'!$E$2:$E$4674<10000)*'Tenant Data'!$J$2:$J$4674*'Tenant Data'!$E$2:$E$4674)/SUMPRODUCT(('Tenant Data'!$A$2:$A$4674=A2)*('Tenant Data'!$F$2:$F$4674>0)*('Tenant Data'!$E$2:$E$4674<10000)*'Tenant Data'!$E$2:$E$4674),""),"") -> 0.16065159 | L2: =IF(B2="Y",COUNTIFS('Tenant Data'!$A$2:$A$4674,A2,'Tenant Data'!$E$2:$E$4674,"<10000"),"") -> 109
A3: Annapolis Mall | B3: Y | C3: Enclosed Mall | D3: 2/2022-1/2023 | E3: 7274990 | F3: 841572 | G3: 139445.69 | H3: =IF(B3="Y",IFERROR(SUMIFS('Tenant Data'!$F$2:$F$4674,'Tenant Data'!$A$2:$A$4674,A3,'Tenant Data'!$F$2:$F$4674,">0",'Tenant Data'!$E$2:$E$4674,"<10000")/SUMIFS('Tenant Data'!$E$2:$E$4674,'Tenant Data'!$A$2:$A$4674,A3,'Tenant Data'!$F$2:$F$4674,">0",'Tenant Data'!$E$2:$E$4674,"<10000"),""),"") -> 620.13578 | I3: =IF(B3="Y",IFERROR(SUMIFS('Tenant Data'!$F$2:$F$4674,'Tenant Data'!$A$2:$A$4674,A3,'Tenant Data'!$D$2:$D$4674,"<>Apple",'Tenant Data'!$F$2:$F$4674,">0",'Tenant Data'!$E$2:$E$4674,"<10000")/SUMIFS('Tenant Data'!$E$2:$E$4674,'Tenant Data'!$A$2:$A$4674,A3,'Tenant Data'!$D$2:$D$4674,"<>Apple",'Tenant Data'!$F$2:$F$4674,">0",'Tenant Data'!$E$2:$E$4674,"<10000"),""),"") -> 522.44917 | J3: =IF(B3="Y",IFERROR(SUMPRODUCT(('Tenant Data'!$A$2:$A$4674=A3)*('Tenant Data'!$F$2:$F$4674>0)*('Tenant Data'!$E$2:$E$4674<10000)*'Tenant Data'!$I$2:$I$4674*'Tenant Data'!$E$2:$E$4674)/SUMPRODUCT(('Tenant Data'!$A$2:$A$4674=A3)*('Tenant Data'!$F$2:$F$4674>0)*('Tenant Data'!$E$2:$E$4674<10000)*'Tenant Data'!$E$2:$E$4674),""),"") -> 78.405891 | K3: =IF(B3="Y",IFERROR(SUMPRODUCT(('Tenant Data'!$A$2:$A$4674=A3)*('Tenant Data'!$F$2:$F$4674>0)*('Tenant Data'!$E$2:$E$4674<10000)*'Tenant Data'!$J$2:$J$4674*'Tenant Data'!$E$2:$E$4674)/SUMPRODUCT(('Tenant Data'!$A$2:$A$4674=A3)*('Tenant Data'!$F$2:$F$4674>0)*('Tenant Data'!$E$2:$E$4674<10000)*'Tenant Data'!$E$2:$E$4674),""),"") -> 0.18015803 | L3: =IF(B3="Y",COUNTIFS('Tenant Data'!$A$2:$A$4674,A3,'Tenant Data'!$E$2:$E$4674,"<10000"),"") -> 109
A4: Annapolis Town Center | B4: Y | C4: Open Air | D4: 3/2023-2/2024 | E4: 5278675 | F4: 342233 | G4: 158600.14 | H4: =IF(B4="Y",IFERROR(SUMIFS('Tenant Data'!$F$2:$F$4674,'Tenant Data'!$A$2:$A$4674,A4,'Tenant Data'!$F$2:$F$4674,">0",'Tenant Data'!$E$2:$E$4674,"<10000")/SUMIFS('Tenant Data'!$E$2:$E$4674,'Tenant Data'!$A$2:$A$4674,A4,'Tenant Data'!$F$2:$F$4674,">0",'Tenant Data'!$E$2:$E$4674,"<10000"),""),"") -> 516.97672 | I4: =IF(B4="Y",IFERROR(SUMIFS('Tenant Data'!$F$2:$F$4674,'Tenant Data'!$A$2:$A$4674,A4,'Tenant Data'!$D$2:$D$4674,"<>Apple",'Tenant Data'!$F$2:$F$4674,">0",'Tenant Data'!$E$2:$E$4674,"<10000")/SUMIFS('Tenant Data'!$E$2:$E$4674,'Tenant Data'!$A$2:$A$4674,A4,'Tenant Data'!$D$2:$D$4674,"<>Apple",'Tenant Data'!$F$2:$F$4674,">0",'Tenant Data'!$E$2:$E$4674,"<10000"),""),"") -> 516.97672 | J4: =IF(B4="Y",IFERROR(SUMPRODUCT(('Tenant Data'!$A$2:$A$4674=A4)*('Tenant Data'!$F$2:$F$4674>0)*('Tenant Data'!$E$2:$E$4674<10000)*'Tenant Data'!$I$2:$I$4674*'Tenant Data'!$E$2:$E$4674)/SUMPRODUCT(('Tenant Data'!$A$2:$A$4674=A4)*('Tenant Data'!$F$2:$F$4674>0)*('Tenant Data'!$E$2:$E$4674<10000)*'Tenant Data'!$E$2:$E$4674),""),"") -> 48.304069 | K4: =IF(B4="Y",IFERROR(SUMPRODUCT(('Tenant Data'!$A$2:$A$4674=A4)*('Tenant Data'!$F$2:$F$4674>0)*('Tenant Data'!$E$2:$E$4674<10000)*'Tenant Data'!$J$2:$J$4674*'Tenant Data'!$E$2:$E$4674)/SUMPRODUCT(('Tenant Data'!$A$2:$A$4674=A4)*('Tenant Data'!$F$2:$F$4674>0)*('Tenant Data'!$E$2:$E$4674<10000)*'Tenant Data'!$E$2:$E$4674),""),"") -> 0.13606986 | L4: =IF(B4="Y",COUNTIFS('Tenant Data'!$A$2:$A$4674,A4,'Tenant Data'!$E$2:$E$4674,"<10000"),"") -> 28
A5: Arden Fair Mall | B5: Y | C5: Enclosed Mall | D5: 3/2023-2/2024 | E5: 7097365 | F5: 1081269 | G5: 105913.35 | H5: =IF(B5="Y",IFERROR(SUMIFS('Tenant Data'!$F$2:$F$4674,'Tenant Data'!$A$2:$A$4674,A5,'Tenant Data'!$F$2:$F$4674,">0",'Tenant Data'!$E$2:$E$4674,"<10000")/SUMIFS('Tenant Data'!$E$2:$E$4674,'Tenant Data'!$A$2:$A$4674,A5,'Tenant Data'!$F$2:$F$4674,">0",'Tenant Data'!$E$2:$E$4674,"<10000"),""),"") -> 841.96341 | I5: =IF(B5="Y",IFERROR(SUMIFS('Tenant Data'!$F$2:$F$4674,'Tenant Data'!$A$2:$A$4674,A5,'Tenant Data'!$D$2:$D$4674,"<>Apple",'Tenant Data'!$F$2:$F$4674,">0",'Tenant Data'!$E$2:$E$4674,"<10000")/SUMIFS('Tenant Data'!$E$2:$E$4674,'Tenant Data'!$A$2:$A$4674,A5,'Tenant Data'!$D$2:$D$4674,"<>Apple",'Tenant Data'!$F$2:$F$4674,">0",'Tenant Data'!$E$2:$E$4674,"<10000"),""),"") -> 690.82267 | J5: =IF(B5="Y",IFERROR(SUMPRODUCT(('Tenant Data'!$A$2:$A$4674=A5)*('Tenant Data'!$F$2:$F$4674>0)*('Tenant Data'!$E$2:$E$4674<10000)*'Tenant Data'!$I$2:$I$4674*'Tenant Data'!$E$2:$E$4674)/SUMPRODUCT(('Tenant Data'!$A$2:$A$4674=A5)*('Tenant Data'!$F$2:$F$4674>0)*('Tenant Data'!$E$2:$E$4674<10000)*'Tenant Data'!$E$2:$E$4674),""),"") -> 97.873362 | K5: =IF(B5="Y",IFERROR(SUMPRODUCT(('Tenant Data'!$A$2:$A$4674=A5)*('Tenant Data'!$F$2:$F$4674>0)*('Tenant Data'!$E$2:$E$4674<10000)*'Tenant Data'!$J$2:$J$4674*'Tenant Data'!$E$2:$E$4674)/SUMPRODUCT(('Tenant Data'!$A$2:$A$4674=A5)*('Tenant Data'!$F$2:$F$4674>0)*('Tenant Data'!$E$2:$E$4674<10000)*'Tenant Data'!$E$2:$E$4674),""),"") -> 0.1590532 | L5: =IF(B5="Y",COUNTIFS('Tenant Data'!$A$2:$A$4674,A5,'Tenant Data'!$E$2:$E$4674,"<10000"),"") -> 78
A6: Belmar | B6: Y | C6: Open Air | D6: 11/2019-10/2020 | E6: 7490755 | F6: 398730 | G6: 116194.71 | H6: =IF(B6="Y",IFERROR(SUMIFS('Tenant Data'!$F$2:$F$4674,'Tenant Data'!$A$2:$A$4674,A6,'Tenant Data'!$F$2:$F$4674,">0",'Tenant Data'!$E$2:$E$4674,"<10000")/SUMIFS('Tenant Data'!$E$2:$E$4674,'Tenant Data'!$A$2:$A$4674,A6,'Tenant Data'!$F$2:$F$4674,">0",'Tenant Data'!$E$2:$E$4674,"<10000"),""),"") -> 374.60868 | I6: =IF(B6="Y",IFERROR(SUMIFS('Tenant Data'!$F$2:$F$4674,'Tenant Data'!$A$2:$A$4674,A6,'Tenant Data'!$D$2:$D$4674,"<>Apple",'Tenant Data'!$F$2:$F$4674,">0",'Tenant Data'!$E$2:$E$4674,"<10000")/SUMIFS('Tenant Data'!$E$2:$E$4674,'Tenant Data'!$A$2:$A$4674,A6,'Tenant Data'!$D$2:$D$4674,"<>Apple",'Tenant Data'!$F$2:$F$4674,">0",'Tenant Data'!$E$2:$E$4674,"<10000"),""),"") -> 374.60868 | J6: =IF(B6="Y",IFERROR(SUMPRODUCT(('Tenant Data'!$A$2:$A$4674=A6)*('Tenant Data'!$F$2:$F$4674>0)*('Tenant Data'!$E$2:$E$4674<10000)*'Tenant Data'!$I$2:$I$4674*'Tenant Data'!$E$2:$E$4674)/SUMPRODUCT(('Tenant Data'!$A$2:$A$4674=A6)*('Tenant Data'!$F$2:$F$4674>0)*('Tenant Data'!$E$2:$E$4674<10000)*'Tenant Data'!$E$2:$E$4674),""),"") -> 35.03578 | K6: =IF(B6="Y",IFERROR(SUMPRODUCT(('Tenant Data'!$A$2:$A$4674=A6)*('Tenant Data'!$F$2:$F$4674>0)*('Tenant Data'!$E$2:$E$4674<10000)*'Tenant Data'!$J$2:$J$4674*'Tenant Data'!$E$2:$E$4674)/SUMPRODUCT(('Tenant Data'!$A$2:$A$4674=A6)*('Tenant Data'!$F$2:$F$4674>0)*('Tenant Data'!$E$2:$E$4674<10000)*'Tenant Data'!$E$2:$E$4674),""),"") -> 0.10331773 | L6: =IF(B6="Y",COUNTIFS('Tenant Data'!$A$2:$A$4674,A6,'Tenant Data'!$E$2:$E$4674,"<10000"),"") -> 42
A7: Brandon Exchange | B7: Y | C7: Enclosed Mall | D7: 7/2020-6/2021 | E7: 6850096 | F7: 698081 | G7: 93025.38 | H7: =IF(B7="Y",IFERROR(SUMIFS('Tenant Data'!$F$2:$F$4674,'Tenant Data'!$A$2:$A$4674,A7,'Tenant Data'!$F$2:$F$4674,">0",'Tenant Data'!$E$2:$E$4674,"<10000")/SUMIFS('Tenant Data'!$E$2:$E$4674,'Tenant Data'!$A$2:$A$4674,A7,'Tenant Data'!$F$2:$F$4674,">0",'Tenant Data'!$E$2:$E$4674,"<10000"),""),"") -> 807.12334 | I7: =IF(B7="Y",IFERROR(SUMIFS('Tenant Data'!$F$2:$F$4674,'Tenant Data'!$A$2:$A$4674,A7,'Tenant Data'!$D$2:$D$4674,"<>Apple",'Tenant Data'!$F$2:$F$4674,">0",'Tenant Data'!$E$2:$E$4674,"<10000")/SUMIFS('Tenant Data'!$E$2:$E$4674,'Tenant Data'!$A$2:$A$4674,A7,'Tenant Data'!$D$2:$D$4674,"<>Apple",'Tenant Data'!$F$2:$F$4674,">0",'Tenant Data'!$E$2:$E$4674,"<10000"),""),"") -> 655.83465 | J7: =IF(B7="Y",IFERROR(SUMPRODUCT(('Tenant Data'!$A$2:$A$4674=A7)*('Tenant Data'!$F$2:$F$4674>0)*('Tenant Data'!$E$2:$E$4674<10000)*'Tenant Data'!$I$2:$I$4674*'Tenant Data'!$E$2:$E$4674)/SUMPRODUCT(('Tenant Data'!$A$2:$A$4674=A7)*('Tenant Data'!$F$2:$F$4674>0)*('Tenant Data'!$E$2:$E$4674<10000)*'Tenant Data'!$E$2:$E$4674),""),"") -> 77.703159 | K7: =IF(B7="Y",IFERROR(SUMPRODUCT(('Tenant Data'!$A$2:$A$4674=A7)*('Tenant Data'!$F$2:$F$4674>0)*('Tenant Data'!$E$2:$E$4674<10000)*'Tenant Data'!$J$2:$J$4674*'Tenant Data'!$E$2:$E$4674)/SUMPRODUCT(('Tenant Data'!$A$2:$A$4674=A7)*('Tenant Data'!$F$2:$F$4674>0)*('Tenant Data'!$E$2:$E$4674<10000)*'Tenant Data'!$E$2:$E$4674),""),"") -> 0.12516513 | L7: =IF(B7="Y",COUNTIFS('Tenant Data'!$A$2:$A$4674,A7,'Tenant Data'!$E$2:$E$4674,"<10000"),"") -> 101
A8: Briarwood Mall | B8: Y | C8: Enclosed Mall | D8: 10/2021-9/2022 | E8: 3417309 | F8: 438493 | G8: 112360.61 | H8: =IF(B8="Y",IFERROR(SUMIFS('Tenant Data'!$F$2:$F$4674,'Tenant Data'!$A$2:$A$4674,A8,'Tenant Data'!$F$2:$F$4674,">0",'Tenant Data'!$E$2:$E$4674,"<10000")/SUMIFS('Tenant Data'!$E$2:$E$4674,'Tenant Data'!$A$2:$A$4674,A8,'Tenant Data'!$F$2:$F$4674,">0",'Tenant Data'!$E$2:$E$4674,"<10000"),""),"") -> 45.800694 | I8: =IF(B8="Y",IFERROR(SUMIFS('Tenant Data'!$F$2:$F$4674,'Tenant Data'!$A$2:$A$4674,A8,'Tenant Data'!$D$2:$D$4674,"<>Apple",'Tenant Data'!$F$2:$F$4674,">0",'Tenant Data'!$E$2:$E$4674,"<10000")/SUMIFS('Tenant Data'!$E$2:$E$4674,'Tenant Data'!$A$2:$A$4674,A8,'Tenant Data'!$D$2:$D$4674,"<>Apple",'Tenant Data'!$F$2:$F$4674,">0",'Tenant Data'!$E$2:$E$4674,"<10000"),""),"") -> 36.056095 | J8: =IF(B8="Y",IFERROR(SUMPRODUCT(('Tenant Data'!$A$2:$A$4674=A8)*('Tenant Data'!$F$2:$F$4674>0)*('Tenant Data'!$E$2:$E$4674<10000)*'Tenant Data'!$I$2:$I$4674*'Tenant Data'!$E$2:$E$4674)/SUMPRODUCT(('Tenant Data'!$A$2:$A$4674=A8)*('Tenant Data'!$F$2:$F$4674>0)*('Tenant Data'!$E$2:$E$4674<10000)*'Tenant Data'!$E$2:$E$4674),""),"") -> 0 | K8: =IF(B8="Y",IFERROR(SUMPRODUCT(('Tenant Data'!$A$2:$A$4674=A8)*('Tenant Data'!$F$2:$F$4674>0)*('Tenant Data'!$E$2:$E$4674<10000)*'Tenant Data'!$J$2:$J$4674*'Tenant Data'!$E$2:$E$4674)/SUMPRODUCT(('Tenant Data'!$A$2:$A$4674=A8)*('Tenant Data'!$F$2:$F$4674>0)*('Tenant Data'!$E$2:$E$4674<10000)*'Tenant Data'!$E$2:$E$4674),""),"") -> 0 | L8: =IF(B8="Y",COUNTIFS('Tenant Data'!$A$2:$A$4674,A8,'Tenant Data'!$E$2:$E$4674,"<10000"),"") -> 67
A9: Bridge Street Towne Centre | B9: Y | C9: Open Air | D9: 3/2022-2/2023 | E9: 6217908 | F9: 403025 | G9: 109737.91 | H9: =IF(B9="Y",IFERROR(SUMIFS('Tenant Data'!$F$2:$F$4674,'Tenant Data'!$A$2:$A$4674,A9,'Tenant Data'!$F$2:$F$4674,">0",'Tenant Data'!$E$2:$E$4674,"<10000")/SUMIFS('Tenant Data'!$E$2:$E$4674,'Tenant Data'!$A$2:$A$4674,A9,'Tenant Data'!$F$2:$F$4674,">0",'Tenant Data'!$E$2:$E$4674,"<10000"),""),"") -> 767.89327 | I9: =IF(B9="Y",IFERROR(SUMIFS('Tenant Data'!$F$2:$F$4674,'Tenant Data'!$A$2:$A$4674,A9,'Tenant Data'!$D$2:$D$4674,"<>Apple",'Tenant Data'!$F$2:$F$4674,">0",'Tenant Data'!$E$2:$E$4674,"<10000")/SUMIFS('Tenant Data'!$E$2:$E$4674,'Tenant Data'!$A$2:$A$4674,A9,'Tenant Data'!$D$2:$D$4674,"<>Apple",'Tenant Data'!$F$2:$F$4674,">0",'Tenant Data'!$E$2:$E$4674,"<10000"),""),"") -> 606.2783 | J9: =IF(B9="Y",IFERROR(SUMPRODUCT(('Tenant Data'!$A$2:$A$4674=A9)*('Tenant Data'!$F$2:$F$4674>0)*('Tenant Data'!$E$2:$E$4674<10000)*'Tenant Data'!$I$2:$I$4674*'Tenant Data'!$E$2:$E$4674)/SUMPRODUCT(('Tenant Data'!$A$2:$A$4674=A9)*('Tenant Data'!$F$2:$F$4674>0)*('Tenant Data'!$E$2:$E$4674<10000)*'Tenant Data'!$E$2:$E$4674),""),"") -> 52.902947 | K9: =IF(B9="Y",IFERROR(SUMPRODUCT(('Tenant Data'!$A$2:$A$4674=A9)*('Tenant Data'!$F$2:$F$4674>0)*('Tenant Data'!$E$2:$E$4674<10000)*'Tenant Data'!$J$2:$J$4674*'Tenant Data'!$E$2:$E$4674)/SUMPRODUCT(('Tenant Data'!$A$2:$A$4674=A9)*('Tenant Data'!$F$2:$F$4674>0)*('Tenant Data'!$E$2:$E$4674<10000)*'Tenant Data'!$E$2:$E$4674),""),"") -> 0.1100116 | L9: =IF(B9="Y",COUNTIFS('Tenant Data'!$A$2:$A$4674,A9,'Tenant Data'!$E$2:$E$4674,"<10000"),"") -> 70
A10: Bridgewater Commons | B10: Y | C10: Enclosed Mall | D10: 7/2021-6/2022 | E10: 5816055 | F10: 912121 | G10: 161034.37 | H10: =IF(B10="Y",IFERROR(SUMIFS('Tenant Data'!$F$2:$F$4674,'Tenant Data'!$A$2:$A$4674,A10,'Tenant Data'!$F$2:$F$4674,">0",'Tenant Data'!$E$2:$E$4674,"<10000")/SUMIFS('Tenant Data'!$E$2:$E$4674,'Tenant Data'!$A$2:$A$4674,A10,'Tenant Data'!$F$2:$F$4674,">0",'Tenant Data'!$E$2:$E$4674,"<10000"),""),"") -> 745.41106 | I10: =IF(B10="Y",IFERROR(SUMIFS('Tenant Data'!$F$2:$F$4674,'Tenant Data'!$A$2:$A$4674,A10,'Tenant Data'!$D$2:$D$4674,"<>Apple",'Tenant Data'!$F$2:$F$4674,">0",'Tenant Data'!$E$2:$E$4674,"<10000")/SUMIFS('Tenant Data'!$E$2:$E$4674,'Tenant Data'!$A$2:$A$4674,A10,'Tenant Data'!$D$2:$D$4674,"<>Apple",'Tenant Data'!$F$2:$F$4674,">0",'Tenant Data'!$E$2:$E$4674,"<10000"),""),"") -> 606.70036 | J10: =IF(B10="Y",IFERROR(SUMPRODUCT(('Tenant Data'!$A$2:$A$4674=A10)*('Tenant Data'!$F$2:$F$4674>0)*('Tenant Data'!$E$2:$E$4674<10000)*'Tenant Data'!$I$2:$I$4674*'Tenant Data'!$E$2:$E$4674)/SUMPRODUCT(('Tenant Data'!$A$2:$A$4674=A10)*('Tenant Data'!$F$2:$F$4674>0)*('Tenant Data'!$E$2:$E$4674<10000)*'Tenant Data'!$E$2:$E$4674),""),"") -> 84.846944 | K10: =IF(B10="Y",IFERROR(SUMPRODUCT(('Tenant Data'!$A$2:$A$4674=A10)*('Tenant Data'!$F$2:$F$4674>0)*('Tenant Data'!$E$2:$E$4674<10000)*'Tenant Data'!$J$2:$J$4674*'Tenant Data'!$E$2:$E$4674)/SUMPRODUCT(('Tenant Data'!$A$2:$A$4674=A10)*('Tenant Data'!$F$2:$F$4674>0)*('Tenant Data'!$E$2:$E$4674<10000)*'Tenant Data'!$E$2:$E$4674),""),"") -> 0.1564615 | L10: =IF(B10="Y",COUNTIFS('Tenant Data'!$A$2:$A$4674,A10,'Tenant Data'!$E$2:$E$4674,"<10000"),"") -> 106
A11: Capital City Mall | B11: Y | C11: Enclosed Mall | D11: 5/2024-6/2025 | E11: 4655717 | F11: 319614 | G11: 99569 | H11: =IF(B11="Y",IFERROR(SUMIFS('Tenant Data'!$F$2:$F$4674,'Tenant Data'!$A$2:$A$4674,A11,'Tenant Data'!$F$2:$F$4674,">0",'Tenant Data'!$E$2:$E$4674,"<10000")/SUMIFS('Tenant Data'!$E$2:$E$4674,'Tenant Data'!$A$2:$A$4674,A11,'Tenant Data'!$F$2:$F$4674,">0",'Tenant Data'!$E$2:$E$4674,"<10000"),""),"") -> 467.54888 | I11: =IF(B11="Y",IFERROR(SUMIFS('Tenant Data'!$F$2:$F$4674,'Tenant Data'!$A$2:$A$4674,A11,'Tenant Data'!$D$2:$D$4674,"<>Apple",'Tenant Data'!$F$2:$F$4674,">0",'Tenant Data'!$E$2:$E$4674,"<10000")/SUMIFS('Tenant Data'!$E$2:$E$4674,'Tenant Data'!$A$2:$A$4674,A11,'Tenant Data'!$D$2:$D$4674,"<>Apple",'Tenant Data'!$F$2:$F$4674,">0",'Tenant Data'!$E$2:$E$4674,"<10000"),""),"") -> 467.54888 | J11: =IF(B11="Y",IFERROR(SUMPRODUCT(('Tenant Data'!$A$2:$A$4674=A11)*('Tenant Data'!$F$2:$F$4674>0)*('Tenant Data'!$E$2:$E$4674<10000)*'Tenant Data'!$I$2:$I$4674*'Tenant Data'!$E$2:$E$4674)/SUMPRODUCT(('Tenant Data'!$A$2:$A$4674=A11)*('Tenant Data'!$F$2:$F$4674>0)*('Tenant Data'!$E$2:$E$4674<10000)*'Tenant Data'!$E$2:$E$4674),""),"") -> 61.929994 | K11: =IF(B11="Y",IFERROR(SUMPRODUCT(('Tenant Data'!$A$2:$A$4674=A11)*('Tenant Data'!$F$2:$F$4674>0)*('Tenant Data'!$E$2:$E$4674<10000)*'Tenant Data'!$J$2:$J$4674*'Tenant Data'!$E$2:$E$4674)/SUMPRODUCT(('Tenant Data'!$A$2:$A$4674=A11)*('Tenant Data'!$F$2:$F$4674>0)*('Tenant Data'!$E$2:$E$4674<10000)*'Tenant Data'!$E$2:$E$4674),""),"") -> 0.14143738 | L11: =IF(B11="Y",COUNTIFS('Tenant Data'!$A$2:$A$4674,A11,'Tenant Data'!$E$2:$E$4674,"<10000"),"") -> 71
A12: Coastal Grand Mall | B12: Y | C12: Enclosed Mall | D12: 12/2024-11/2025 | E12: 5952111 | F12: 224112 | G12: 89321.41 | H12: =IF(B12="Y",IFERROR(SUMIFS('Tenant Data'!$F$2:$F$4674,'Tenant Data'!$A$2:$A$4674,A12,'Tenant Data'!$F$2:$F$4674,">0",'Tenant Data'!$E$2:$E$4674,"<10000")/SUMIFS('Tenant Data'!$E$2:$E$4674,'Tenant Data'!$A$2:$A$4674,A12,'Tenant Data'!$F$2:$F$4674,">0",'Tenant Data'!$E$2:$E$4674,"<10000"),""),"") -> 433.53269 | I12: =IF(B12="Y",IFERROR(SUMIFS('Tenant Data'!$F$2:$F$4674,'Tenant Data'!$A$2:$A$4674,A12,'Tenant Data'!$D$2:$D$4674,"<>Apple",'Tenant Data'!$F$2:$F$4674,">0",'Tenant Data'!$E$2:$E$4674,"<10000")/SUMIFS('Tenant Data'!$E$2:$E$4674,'Tenant Data'!$A$2:$A$4674,A12,'Tenant Data'!$D$2:$D$4674,"<>Apple",'Tenant Data'!$F$2:$F$4674,">0",'Tenant Data'!$E$2:$E$4674,"<10000"),""),"") -> 433.53269 | J12: =IF(B12="Y",IFERROR(SUMPRODUCT(('Tenant Data'!$A$2:$A$4674=A12)*('Tenant Data'!$F$2:$F$4674>0)*('Tenant Data'!$E$2:$E$4674<10000)*'Tenant Data'!$I$2:$I$4674*'Tenant Data'!$E$2:$E$4674)/SUMPRODUCT(('Tenant Data'!$A$2:$A$4674=A12)*('Tenant Data'!$F$2:$F$4674>0)*('Tenant Data'!$E$2:$E$4674<10000)*'Tenant Data'!$E$2:$E$4674),""),"") -> 51.28943 | K12: =IF(B12="Y",IFERROR(SUMPRODUCT(('Tenant Data'!$A$2:$A$4674=A12)*('Tenant Data'!$F$2:$F$4674>0)*('Tenant Data'!$E$2:$E$4674<10000)*'Tenant Data'!$J$2:$J$4674*'Tenant Data'!$E$2:$E$4674)/SUMPRODUCT(('Tenant Data'!$A$2:$A$4674=A12)*('Tenant Data'!$F$2:$F$4674>0)*('Tenant Data'!$E$2:$E$4674<10000)*'Tenant Data'!$E$2:$E$4674),""),"") -> 0.13689809 | L12: =IF(B12="Y",COUNTIFS('Tenant Data'!$A$2:$A$4674,A12,'Tenant Data'!$E$2:$E$4674,"<10000"),"") -> 86
A13: CoolSprings Galleria | B13: Y | C13: Enclosed Mall | D13: 12/2024-11/2025 | E13: 5760072 | F13: 744158 | G13: 148339.87 | H13: =IF(B13="Y",IFERROR(SUMIFS('Tenant Data'!$F$2:$F$4674,'Tenant Data'!$A$2:$A$4674,A13,'Tenant Data'!$F$2:$F$4674,">0",'Tenant Data'!$E$2:$E$4674,"<10000")/SUMIFS('Tenant Data'!$E$2:$E$4674,'Tenant Data'!$A$2:$A$4674,A13,'Tenant Data'!$F$2:$F$4674,">0",'Tenant Data'!$E$2:$E$4674,"<10000"),""),"") -> 695.70041 | I13: =IF(B13="Y",IFERROR(SUMIFS('Tenant Data'!$F$2:$F$4674,'Tenant Data'!$A$2:$A$4674,A13,'Tenant Data'!$D$2:$D$4674,"<>Apple",'Tenant Data'!$F$2:$F$4674,">0",'Tenant Data'!$E$2:$E$4674,"<10000")/SUMIFS('Tenant Data'!$E$2:$E$4674,'Tenant Data'!$A$2:$A$4674,A13,'Tenant Data'!$D$2:$D$4674,"<>Apple",'Tenant Data'!$F$2:$F$4674,">0",'Tenant Data'!$E$2:$E$4674,"<10000"),""),"") -> 542.23444 | J13: =IF(B13="Y",IFERROR(SUMPRODUCT(('Tenant Data'!$A$2:$A$4674=A13)*('Tenant Data'!$F$2:$F$4674>0)*('Tenant Data'!$E$2:$E$4674<10000)*'Tenant Data'!$I$2:$I$4674*'Tenant Data'!$E$2:$E$4674)/SUMPRODUCT(('Tenant Data'!$A$2:$A$4674=A13)*('Tenant Data'!$F$2:$F$4674>0)*('Tenant Data'!$E$2:$E$4674<10000)*'Tenant Data'!$E$2:$E$4674),""),"") -> 65.304581 | K13: =IF(B13="Y",IFERROR(SUMPRODUCT(('Tenant Data'!$A$2:$A$4674=A13)*('Tenant Data'!$F$2:$F$4674>0)*('Tenant Data'!$E$2:$E$4674<10000)*'Tenant Data'!$J$2:$J$4674*'Tenant Data'!$E$2:$E$4674)/SUMPRODUCT(('Tenant Data'!$A$2:$A$4674=A13)*('Tenant Data'!$F$2:$F$4674>0)*('Tenant Data'!$E$2:$E$4674<10000)*'Tenant Data'!$E$2:$E$4674),""),"") -> 0.14441173 | L13: =IF(B13="Y",COUNTIFS('Tenant Data'!$A$2:$A$4674,A13,'Tenant Data'!$E$2:$E$4674,"<10000"),"") -> 112
... A49: Willow Grove Park | B49: Y | C49: Enclosed Mall | D49: 4/2024-3/2025 | E49: 5160995 | F49: 850000 | G49: 105000 | H49: =IF(B49="Y",IFERROR(SUMIFS('Tenant Data'!$F$2:$F$4674,'Tenant Data'!$A$2:$A$4674,A49,'Tenant Data'!$F$2:$F$4674,">0",'Tenant Data'!$E$2:$E$4674,"<10000")/SUMIFS('Tenant Data'!$E$2:$E$4674,'Tenant Data'!$A$2:$A$4674,A49,'Tenant Data'!$F$2:$F$4674,">0",'Tenant Data'!$E$2:$E$4674,"<10000"),""),"") -> 827.71397 | I49: =IF(B49="Y",IFERROR(SUMIFS('Tenant Data'!$F$2:$F$4674,'Tenant Data'!$A$2:$A$4674,A49,'Tenant Data'!$D$2:$D$4674,"<>Apple",'Tenant Data'!$F$2:$F$4674,">0",'Tenant Data'!$E$2:$E$4674,"<10000")/SUMIFS('Tenant Data'!$E$2:$E$4674,'Tenant Data'!$A$2:$A$4674,A49,'Tenant Data'!$D$2:$D$4674,"<>Apple",'Tenant Data'!$F$2:$F$4674,">0",'Tenant Data'!$E$2:$E$4674,"<10000"),""),"") -> 557.27661 | J49: =IF(B49="Y",IFERROR(SUMPRODUCT(('Tenant Data'!$A$2:$A$4674=A49)*('Tenant Data'!$F$2:$F$4674>0)*('Tenant Data'!$E$2:$E$4674<10000)*'Tenant Data'!$I$2:$I$4674*'Tenant Data'!$E$2:$E$4674)/SUMPRODUCT(('Tenant Data'!$A$2:$A$4674=A49)*('Tenant Data'!$F$2:$F$4674>0)*('Tenant Data'!$E$2:$E$4674<10000)*'Tenant Data'!$E$2:$E$4674),""),"") -> 65.432632 | K49: =IF(B49="Y",IFERROR(SUMPRODUCT(('Tenant Data'!$A$2:$A$4674=A49)*('Tenant Data'!$F$2:$F$4674>0)*('Tenant Data'!$E$2:$E$4674<10000)*'Tenant Data'!$J$2:$J$4674*'Tenant Data'!$E$2:$E$4674)/SUMPRODUCT(('Tenant Data'!$A$2:$A$4674=A49)*('Tenant Data'!$F$2:$F$4674>0)*('Tenant Data'!$E$2:$E$4674<10000)*'Tenant Data'!$E$2:$E$4674),""),"") -> 0.12179287 | L49: =IF(B49="Y",COUNTIFS('Tenant Data'!$A$2:$A$4674,A49,'Tenant Data'!$E$2:$E$4674,"<10000"),"") -> 37

Sheet Tenant Lookup
A1: Tenant Sales PSF Summary
A3: Select Tenant: | B3: Lovisa
A4: # of Locations: | B4: =COUNTIF(E8:E55,">0") -> 28
A6: Property Details
A7: Property | B7: Include | C7: Size (SF) | D7: T-12 Sales | E7: Sales PSF | F7: Rent PSF | G7: Occ Cost %
A8: Clackamas Town Center | B8: ='Property Summary'!B2 -> Y | C8: =IFERROR(SUMIFS('Tenant Data'!$E$2:$E$4674,'Tenant Data'!$A$2:$A$4674,A8,'Tenant Data'!$B$2:$B$4674,$B$3),"") -> 1325 | D8: =IFERROR(SUMIFS('Tenant Data'!$F$2:$F$4674,'Tenant Data'!$A$2:$A$4674,A8,'Tenant Data'!$B$2:$B$4674,$B$3),"") -> 685034 | E8: =IFERROR(IF(C8>0,D8/C8,""),"") -> 517.00679 | F8: =IFERROR(SUMIFS('Tenant Data'!$I$2:$I$4674,'Tenant Data'!$A$2:$A$4674,A8,'Tenant Data'!$B$2:$B$4674,$B$3),"") -> 78.1542 | G8: =IFERROR(SUMIFS('Tenant Data'!$J$2:$J$4674,'Tenant Data'!$A$2:$A$4674,A8,'Tenant Data'!$B$2:$B$4674,$B$3),"") -> 0.15116668
A9: Annapolis Mall | B9: ='Property Summary'!B3 -> Y | C9: =IFERROR(SUMIFS('Tenant Data'!$E$2:$E$4674,'Tenant Data'!$A$2:$A$4674,A9,'Tenant Data'!$B$2:$B$4674,$B$3),"") -> 1160 | D9: =IFERROR(SUMIFS('Tenant Data'!$F$2:$F$4674,'Tenant Data'!$A$2:$A$4674,A9,'Tenant Data'!$B$2:$B$4674,$B$3),"") -> 368697.45 | E9: =IFERROR(IF(C9>0,D9/C9,""),"") -> 317.84263 | F9: =IFERROR(SUMIFS('Tenant Data'!$I$2:$I$4674,'Tenant Data'!$A$2:$A$4674,A9,'Tenant Data'!$B$2:$B$4674,$B$3),"") -> 92.4 | G9: =IFERROR(SUMIFS('Tenant Data'!$J$2:$J$4674,'Tenant Data'!$A$2:$A$4674,A9,'Tenant Data'!$B$2:$B$4674,$B$3),"") -> 0.2907099
A10: Annapolis Town Center | B10: ='Property Summary'!B4 -> Y | C10: =IFERROR(SUMIFS('Tenant Data'!$E$2:$E$4674,'Tenant Data'!$A$2:$A$4674,A10,'Tenant Data'!$B$2:$B$4674,$B$3),"") -> 0 | D10: =IFERROR(SUMIFS('Tenant Data'!$F$2:$F$4674,'Tenant Data'!$A$2:$A$4674,A10,'Tenant Data'!$B$2:$B$4674,$B$3),"") -> 0 | E10: =IFERROR(IF(C10>0,D10/C10,""),"") | F10: =IFERROR(SUMIFS('Tenant Data'!$I$2:$I$4674,'Tenant Data'!$A$2:$A$4674,A10,'Tenant Data'!$B$2:$B$4674,$B$3),"") -> 0 | G10: =IFERROR(SUMIFS('Tenant Data'!$J$2:$J$4674,'Tenant Data'!$A$2:$A$4674,A10,'Tenant Data'!$B$2:$B$4674,$B$3),"") -> 0
A11: Arden Fair Mall | B11: ='Property Summary'!B5 -> Y | C11: =IFERROR(SUMIFS('Tenant Data'!$E$2:$E$4674,'Tenant Data'!$A$2:$A$4674,A11,'Tenant Data'!$B$2:$B$4674,$B$3),"") -> 0 | D11: =IFERROR(SUMIFS('Tenant Data'!$F$2:$F$4674,'Tenant Data'!$A$2:$A$4674,A11,'Tenant Data'!$B$2:$B$4674,$B$3),"") -> 0 | E11: =IFERROR(IF(C11>0,D11/C11,""),"") | F11: =IFERROR(SUMIFS('Tenant Data'!$I$2:$I$4674,'Tenant Data'!$A$2:$A$4674,A11,'Tenant Data'!$B$2:$B$4674,$B$3),"") -> 0 | G11: =IFERROR(SUMIFS('Tenant Data'!$J$2:$J$4674,'Tenant Data'!$A$2:$A$4674,A11,'Tenant Data'!$B$2:$B$4674,$B$3),"") -> 0
A12: Belmar | B12: ='Property Summary'!B6 -> Y | C12: =IFERROR(SUMIFS('Tenant Data'!$E$2:$E$4674,'Tenant Data'!$A$2:$A$4674,A12,'Tenant Data'!$B$2:$B$4674,$B$3),"") -> 0 | D12: =IFERROR(SUMIFS('Tenant Data'!$F$2:$F$4674,'Tenant Data'!$A$2:$A$4674,A12,'Tenant Data'!$B$2:$B$4674,$B$3),"") -> 0 | E12: =IFERROR(IF(C12>0,D12/C12,""),"") | F12: =IFERROR(SUMIFS('Tenant Data'!$I$2:$I$4674,'Tenant Data'!$A$2:$A$4674,A12,'Tenant Data'!$B$2:$B$4674,$B$3),"") -> 0 | G12: =IFERROR(SUMIFS('Tenant Data'!$J$2:$J$4674,'Tenant Data'!$A$2:$A$4674,A12,'Tenant Data'!$B$2:$B$4674,$B$3),"") -> 0
A13: Brandon Exchange | B13: ='Property Summary'!B7 -> Y | C13: =IFERROR(SUMIFS('Tenant Data'!$E$2:$E$4674,'Tenant Data'!$A$2:$A$4674,A13,'Tenant Data'!$B$2:$B$4674,$B$3),"") -> 0 | D13: =IFERROR(SUMIFS('Tenant Data'!$F$2:$F$4674,'Tenant Data'!$A$2:$A$4674,A13,'Tenant Data'!$B$2:$B$4674,$B$3),"") -> 0 | E13: =IFERROR(IF(C13>0,D13/C13,""),"") | F13: =IFERROR(SUMIFS('Tenant Data'!$I$2:$I$4674,'Tenant Data'!$A$2:$A$4674,A13,'Tenant Data'!$B$2:$B$4674,$B$3),"") -> 0 | G13: =IFERROR(SUMIFS('Tenant Data'!$J$2:$J$4674,'Tenant Data'!$A$2:$A$4674,A13,'Tenant Data'!$B$2:$B$4674,$B$3),"") -> 0
A14: Briarwood Mall | B14: ='Property Summary'!B8 -> Y | C14: =IFERROR(SUMIFS('Tenant Data'!$E$2:$E$4674,'Tenant Data'!$A$2:$A$4674,A14,'Tenant Data'!$B$2:$B$4674,$B$3),"") -> 841 | D14: =IFERROR(SUMIFS('Tenant Data'!$F$2:$F$4674,'Tenant Data'!$A$2:$A$4674,A14,'Tenant Data'!$B$2:$B$4674,$B$3),"") -> 17900 | E14: =IFERROR(IF(C14>0,D14/C14,""),"") -> 21.284185 | F14: =IFERROR(SUMIFS('Tenant Data'!$I$2:$I$4674,'Tenant Data'!$A$2:$A$4674,A14,'Tenant Data'!$B$2:$B$4674,$B$3),"") -> 0 | G14: =IFERROR(SUMIFS('Tenant Data'!$J$2:$J$4674,'Tenant Data'!$A$2:$A$4674,A14,'Tenant Data'!$B$2:$B$4674,$B$3),"") -> 0
A15: Bridge Street Towne Centre | B15: ='Property Summary'!B9 -> Y | C15: =IFERROR(SUMIFS('Tenant Data'!$E$2:$E$4674,'Tenant Data'!$A$2:$A$4674,A15,'Tenant Data'!$B$2:$B$4674,$B$3),"") -> 0 | D15: =IFERROR(SUMIFS('Tenant Data'!$F$2:$F$4674,'Tenant Data'!$A$2:$A$4674,A15,'Tenant Data'!$B$2:$B$4674,$B$3),"") -> 0 | E15: =IFERROR(IF(C15>0,D15/C15,""),"") | F15: =IFERROR(SUMIFS('Tenant Data'!$I$2:$I$4674,'Tenant Data'!$A$2:$A$4674,A15,'Tenant Data'!$B$2:$B$4674,$B$3),"") -> 0 | G15: =IFERROR(SUMIFS('Tenant Data'!$J$2:$J$4674,'Tenant Data'!$A$2:$A$4674,A15,'Tenant Data'!$B$2:$B$4674,$B$3),"") -> 0
A16: Bridgewater Commons | B16: ='Property Summary'!B10 -> Y | C16: =IFERROR(SUMIFS('Tenant Data'!$E$2:$E$4674,'Tenant Data'!$A$2:$A$4674,A16,'Tenant Data'!$B$2:$B$4674,$B$3),"") -> 806 | D16: =IFERROR(SUMIFS('Tenant Data'!$F$2:$F$4674,'Tenant Data'!$A$2:$A$4674,A16,'Tenant Data'!$B$2:$B$4674,$B$3),"") -> 669303 | E16: =IFERROR(IF(C16>0,D16/C16,""),"") -> 830.40074 | F16: =IFERROR(SUMIFS('Tenant Data'!$I$2:$I$4674,'Tenant Data'!$A$2:$A$4674,A16,'Tenant Data'!$B$2:$B$4674,$B$3),"") -> 116.19141 | G16: =IFERROR(SUMIFS('Tenant Data'!$J$2:$J$4674,'Tenant Data'!$A$2:$A$4674,A16,'Tenant Data'!$B$2:$B$4674,$B$3),"") -> 0.1399221
A17: Capital City Mall | B17: ='Property Summary'!B11 -> Y | C17: =IFERROR(SUMIFS('Tenant Data'!$E$2:$E$4674,'Tenant Data'!$A$2:$A$4674,A17,'Tenant Data'!$B$2:$B$4674,$B$3),"") -> 800 | D17: =IFERROR(SUMIFS('Tenant Data'!$F$2:$F$4674,'Tenant Data'!$A$2:$A$4674,A17,'Tenant Data'!$B$2:$B$4674,$B$3),"") -> 478642.84 | E17: =IFERROR(IF(C17>0,D17/C17,""),"") -> 598.30355 | F17: =IFERROR(SUMIFS('Tenant Data'!$I$2:$I$4674,'Tenant Data'!$A$2:$A$4674,A17,'Tenant Data'!$B$2:$B$4674,$B$3),"") -> 112.725 | G17: =IFERROR(SUMIFS('Tenant Data'!$J$2:$J$4674,'Tenant Data'!$A$2:$A$4674,A17,'Tenant Data'!$B$2:$B$4674,$B$3),"") -> 0.18840771
A18: Coastal Grand Mall | B18: ='Property Summary'!B12 -> Y | C18: =IFERROR(SUMIFS('Tenant Data'!$E$2:$E$4674,'Tenant Data'!$A$2:$A$4674,A18,'Tenant Data'!$B$2:$B$4674,$B$3),"") -> 1970 | D18: =IFERROR(SUMIFS('Tenant Data'!$F$2:$F$4674,'Tenant Data'!$A$2:$A$4674,A18,'Tenant Data'!$B$2:$B$4674,$B$3),"") -> 492166.72 | E18: =IFERROR(IF(C18>0,D18/C18,""),"") -> 249.83082 | F18: =IFERROR(SUMIFS('Tenant Data'!$I$2:$I$4674,'Tenant Data'!$A$2:$A$4674,A18,'Tenant Data'!$B$2:$B$4674,$B$3),"") -> 28.446703 | G18: =IFERROR(SUMIFS('Tenant Data'!$J$2:$J$4674,'Tenant Data'!$A$2:$A$4674,A18,'Tenant Data'!$B$2:$B$4674,$B$3),"") -> 0.11386387
A19: CoolSprings Galleria | B19: ='Property Summary'!B13 -> Y | C19: =IFERROR(SUMIFS('Tenant Data'!$E$2:$E$4674,'Tenant Data'!$A$2:$A$4674,A19,'Tenant Data'!$B$2:$B$4674,$B$3),"") -> 631 | D19: =IFERROR(SUMIFS('Tenant Data'!$F$2:$F$4674,'Tenant Data'!$A$2:$A$4674,A19,'Tenant Data'!$B$2:$B$4674,$B$3),"") -> 493135.42 | E19: =IFERROR(IF(C19>0,D19/C19,""),"") -> 781.51414 | F19: =IFERROR(SUMIFS('Tenant Data'!$I$2:$I$4674,'Tenant Data'!$A$2:$A$4674,A19,'Tenant Data'!$B$2:$B$4674,$B$3),"") -> 124.85835 | G19: =IFERROR(SUMIFS('Tenant Data'!$J$2:$J$4674,'Tenant Data'!$A$2:$A$4674,A19,'Tenant Data'!$B$2:$B$4674,$B$3),"") -> 0.15976467
... A55: Willow Grove Park | B55: ='Property Summary'!B49 -> Y | C55: =IFERROR(SUMIFS('Tenant Data'!$E$2:$E$4674,'Tenant Data'!$A$2:$A$4674,A55,'Tenant Data'!$B$2:$B$4674,$B$3),"") -> 738 | D55: =IFERROR(SUMIFS('Tenant Data'!$F$2:$F$4674,'Tenant Data'!$A$2:$A$4674,A55,'Tenant Data'!$B$2:$B$4674,$B$3),"") -> 539559 | E55: =IFERROR(IF(C55>0,D55/C55,""),"") -> 731.10976 | F55: =IFERROR(SUMIFS('Tenant Data'!$I$2:$I$4674,'Tenant Data'!$A$2:$A$4674,A55,'Tenant Data'!$B$2:$B$4674,$B$3),"") -> 136.57 | G55: =IFERROR(SUMIFS('Tenant Data'!$J$2:$J$4674,'Tenant Data'!$A$2:$A$4674,A55,'Tenant Data'!$B$2:$B$4674,$B$3),"") -> 0.1868
A56: Total / Weighted Avg | C56: =SUMPRODUCT((B8:B55="Y")*(C8:C55<>"")*C8:C55) -> 30138 | D56: =SUMPRODUCT((B8:B55="Y")*(D8:D55<>"")*D8:D55) -> 13793981 | E56: =IFERROR(D56/C56,"") -> 457.69397
A58: Sales PSF Ranking (Highest to Lowest)
A59: Rank | B59: Property | C59: Sales PSF
A60: 1 | B60: =IFERROR(INDEX($A$8:$A$55,MATCH(LARGE($E$8:$E$55,1),$E$8:$E$55,0)),"") -> Galleria at Tyler | C60: =IFERROR(LARGE($E$8:$E$55,1),"") -> 934.94586
A61: 2 | B61: =IFERROR(INDEX($A$8:$A$55,MATCH(LARGE($E$8:$E$55,2),$E$8:$E$55,0)),"") -> Fayette Mall | C61: =IFERROR(LARGE($E$8:$E$55,2),"") -> 914.33705
A62: 3 | B62: =IFERROR(INDEX($A$8:$A$55,MATCH(LARGE($E$8:$E$55,3),$E$8:$E$55,0)),"") -> Oak Park Mall | C62: =IFERROR(LARGE($E$8:$E$55,3),"") -> 842.28191
A63: 4 | B63: =IFERROR(INDEX($A$8:$A$55,MATCH(LARGE($E$8:$E$55,4),$E$8:$E$55,0)),"") -> Bridgewater Commons | C63: =IFERROR(LARGE($E$8:$E$55,4),"") -> 830.40074
A64: 5 | B64: =IFERROR(INDEX($A$8:$A$55,MATCH(LARGE($E$8:$E$55,5),$E$8:$E$55,0)),"") -> Hamilton Place Mall | C64: =IFERROR(LARGE($E$8:$E$55,5),"") -> 788.2124
A65: 6 | B65: =IFERROR(INDEX($A$8:$A$55,MATCH(LARGE($E$8:$E$55,6),$E$8:$E$55,0)),"") -> West Towne Mall | C65: =IFERROR(LARGE($E$8:$E$55,6),"") -> 781.69972
A66: 7 | B66: =IFERROR(INDEX($A$8:$A$55,MATCH(LARGE($E$8:$E$55,7),$E$8:$E$55,0)),"") -> CoolSprings Galleria | C66: =IFERROR(LARGE($E$8:$E$55,7),"") -> 781.51414
A67: 8 | B67: =IFERROR(INDEX($A$8:$A$55,MATCH(LARGE($E$8:$E$55,8),$E$8:$E$55,0)),"") -> Willow Grove Park | C67: =IFERROR(LARGE($E$8:$E$55,8),"") -> 731.10976
A68: 9 | B68: =IFERROR(INDEX($A$8:$A$55,MATCH(LARGE($E$8:$E$55,9),$E$8:$E$55,0)),"") -> Crabtree Valley Mall | C68: =IFERROR(LARGE($E$8:$E$55,9),"") -> 648.22177
A69: 10 | B69: =IFERROR(INDEX($A$8:$A$55,MATCH(LARGE($E$8:$E$55,10),$E$8:$E$55,0)),"") -> SouthPark Mall (OH) | C69: =IFERROR(LARGE($E$8:$E$55,10),"") -> 606.39334
A70: 11 | B70: =IFERROR(INDEX($A$8:$A$55,MATCH(LARGE($E$8:$E$55,11),$E$8:$E$55,0)),"") -> Capital City Mall | C70: =IFERROR(LARGE($E$8:$E$55,11),"") -> 598.30355
A71: 12 | B71: =IFERROR(INDEX($A$8:$A$55,MATCH(LARGE($E$8:$E$55,12),$E$8:$E$55,0)),"") -> Towson Town Center | C71: =IFERROR(LARGE($E$8:$E$55,12),"") -> 523.69713
A72: 13 | B72: =IFERROR(INDEX($A$8:$A$55,MATCH(LARGE($E$8:$E$55,13),$E$8:$E$55,0)),"") -> Providence Place | C72: =IFERROR(LARGE($E$8:$E$55,13),"") -> 519.6
A73: 14 | B73: =IFERROR(INDEX($A$8:$A$55,MATCH(LARGE($E$8:$E$55,14),$E$8:$E$55,0)),"") -> Clackamas Town Center | C73: =IFERROR(LARGE($E$8:$E$55,14),"") -> 517.00679
A74: 15 | B74: =IFERROR(INDEX($A$8:$A$55,MATCH(LARGE($E$8:$E$55,15),$E$8:$E$55,0)),"") -> Staten Island Mall | C74: =IFERROR(LARGE($E$8:$E$55,15),"") -> 507.52088
A75: 16 | B75: =IFERROR(INDEX($A$8:$A$55,MATCH(LARGE($E$8:$E$55,16),$E$8:$E$55,0)),"") -> West County Center | C75: =IFERROR(LARGE($E$8:$E$55,16),"") -> 477.68451
A76: 17 | B76: =IFERROR(INDEX($A$8:$A$55,MATCH(LARGE($E$8:$E$55,17),$E$8:$E$55,0)),"") -> Palisades Center | C76: =IFERROR(LARGE($E$8:$E$55,17),"") -> 467.76156
A77: 18 | B77: =IFERROR(INDEX($A$8:$A$55,MATCH(LARGE($E$8:$E$55,18),$E$8:$E$55,0)),"") -> SoNo Collection | C77: =IFERROR(LARGE($E$8:$E$55,18),"") -> 465.7367
A78: 19 | B78: =IFERROR(INDEX($A$8:$A$55,MATCH(LARGE($E$8:$E$55,19),$E$8:$E$55,0)),"") -> Crossgates Center | C78: =IFERROR(LARGE($E$8:$E$55,19),"") -> 463.83976
A79: 20 | B79: =IFERROR(INDEX($A$8:$A$55,MATCH(LARGE($E$8:$E$55,20),$E$8:$E$55,0)),"") -> Cross Creek Mall | C79: =IFERROR(LARGE($E$8:$E$55,20),"") -> 447.50862
A80: 21 | B80: =IFERROR(INDEX($A$8:$A$55,MATCH(LARGE($E$8:$E$55,21),$E$8:$E$55,0)),"") -> Tysons Corner | C80: =IFERROR(LARGE($E$8:$E$55,21),"") -> 437.98482
A81: 22 | B81: =IFERROR(INDEX($A$8:$A$55,MATCH(LARGE($E$8:$E$55,22),$E$8:$E$55,0)),"") -> Mall at Wellington Green | C81: =IFERROR(LARGE($E$8:$E$55,22),"") -> 419.35182
A82: 23 | B82: =IFERROR(INDEX($A$8:$A$55,MATCH(LARGE($E$8:$E$55,23),$E$8:$E$55,0)),"") -> Destiny USA | C82: =IFERROR(LARGE($E$8:$E$55,23),"") -> 371.5112
A83: 24 | B83: =IFERROR(INDEX($A$8:$A$55,MATCH(LARGE($E$8:$E$55,24),$E$8:$E$55,0)),"") -> Walden Galleria | C83: =IFERROR(LARGE($E$8:$E$55,24),"") -> 358.06068
A84: 25 | B84: =IFERROR(INDEX($A$8:$A$55,MATCH(LARGE($E$8:$E$55,25),$E$8:$E$55,0)),"") -> Mall at Partridge Creek | C84: =IFERROR(LARGE($E$8:$E$55,25),"") -> 341.08081
A85: 26 | B85: =IFERROR(INDEX($A$8:$A$55,MATCH(LARGE($E$8:$E$55,26),$E$8:$E$55,0)),"") -> Annapolis Mall | C85: =IFERROR(LARGE($E$8:$E$55,26),"") -> 317.84263
A86: 27 | B86: =IFERROR(INDEX($A$8:$A$55,MATCH(LARGE($E$8:$E$55,27),$E$8:$E$55,0)),"") -> Coastal Grand Mall | C86: =IFERROR(LARGE($E$8:$E$55,27),"") -> 249.83082
A87: 28 | B87: =IFERROR(INDEX($A$8:$A$55,MATCH(LARGE($E$8:$E$55,28),$E$8:$E$55,0)),"") -> Briarwood Mall | C87: =IFERROR(LARGE($E$8:$E$55,28),"") -> 21.284185
A88: 29 | B88: =IFERROR(INDEX($A$8:$A$55,MATCH(LARGE($E$8:$E$55,29),$E$8:$E$55,0)),"") -> Mall del Norte | C88: =IFERROR(LARGE($E$8:$E$55,29),"") -> 0
A89: 30 | B89: =IFERROR(INDEX($A$8:$A$55,MATCH(LARGE($E$8:$E$55,30),$E$8:$E$55,0)),"") -> Mall del Norte | C89: =IFERROR(LARGE($E$8:$E$55,30),"") -> 0
A90: 31 | B90: =IFERROR(INDEX($A$8:$A$55,MATCH(LARGE($E$8:$E$55,31),$E$8:$E$55,0)),"") | C90: =IFERROR(LARGE($E$8:$E$55,31),"")
A91: 32 | B91: =IFERROR(INDEX($A$8:$A$55,MATCH(LARGE($E$8:$E$55,32),$E$8:$E$55,0)),"") | C91: =IFERROR(LARGE($E$8:$E$55,32),"")
A92: 33 | B92: =IFERROR(INDEX($A$8:$A$55,MATCH(LARGE($E$8:$E$55,33),$E$8:$E$55,0)),"") | C92: =IFERROR(LARGE($E$8:$E$55,33),"")
A93: 34 | B93: =IFERROR(INDEX($A$8:$A$55,MATCH(LARGE($E$8:$E$55,34),$E$8:$E$55,0)),"") | C93: =IFERROR(LARGE($E$8:$E$55,34),"")
A94: 35 | B94: =IFERROR(INDEX($A$8:$A$55,MATCH(LARGE($E$8:$E$55,35),$E$8:$E$55,0)),"") | C94: =IFERROR(LARGE($E$8:$E$55,35),"")
A95: 36 | B95: =IFERROR(INDEX($A$8:$A$55,MATCH(LARGE($E$8:$E$55,36),$E$8:$E$55,0)),"") | C95: =IFERROR(LARGE($E$8:$E$55,36),"")
A96: 37 | B96: =IFERROR(INDEX($A$8:$A$55,MATCH(LARGE($E$8:$E$55,37),$E$8:$E$55,0)),"") | C96: =IFERROR(LARGE($E$8:$E$55,37),"")
A97: 38 | B97: =IFERROR(INDEX($A$8:$A$55,MATCH(LARGE($E$8:$E$55,38),$E$8:$E$55,0)),"") | C97: =IFERROR(LARGE($E$8:$E$55,38),"")
A98: 39 | B98: =IFERROR(INDEX($A$8:$A$55,MATCH(LARGE($E$8:$E$55,39),$E$8:$E$55,0)),"") | C98: =IFERROR(LARGE($E$8:$E$55,39),"")
A99: 40 | B99: =IFERROR(INDEX($A$8:$A$55,MATCH(LARGE($E$8:$E$55,40),$E$8:$E$55,0)),"") | C99: =IFERROR(LARGE($E$8:$E$55,40),"")
A100: 41 | B100: =IFERROR(INDEX($A$8:$A$55,MATCH(LARGE($E$8:$E$55,41),$E$8:$E$55,0)),"") | C100: =IFERROR(LARGE($E$8:$E$55,41),"")
A101: 42 | B101: =IFERROR(INDEX($A$8:$A$55,MATCH(LARGE($E$8:$E$55,42),$E$8:$E$55,0)),"") | C101: =IFERROR(LARGE($E$8:$E$55,42),"")
A102: 43 | B102: =IFERROR(INDEX($A$8:$A$55,MATCH(LARGE($E$8:$E$55,43),$E$8:$E$55,0)),"") | C102: =IFERROR(LARGE($E$8:$E$55,43),"")
A103: 44 | B103: =IFERROR(INDEX($A$8:$A$55,MATCH(LARGE($E$8:$E$55,44),$E$8:$E$55,0)),"") | C103: =IFERROR(LARGE($E$8:$E$55,44),"")
A104: 45 | B104: =IFERROR(INDEX($A$8:$A$55,MATCH(LARGE($E$8:$E$55,45),$E$8:$E$55,0)),"") | C104: =IFERROR(LARGE($E$8:$E$55,45),"")
A105: 46 | B105: =IFERROR(INDEX($A$8:$A$55,MATCH(LARGE($E$8:$E$55,46),$E$8:$E$55,0)),"") | C105: =IFERROR(LARGE($E$8:$E$55,46),"")
A106: 47 | B106: =IFERROR(INDEX($A$8:$A$55,MATCH(LARGE($E$8:$E$55,47),$E$8:$E$55,0)),"") | C106: =IFERROR(LARGE($E$8:$E$55,47),"")
A107: 48 | B107: =IFERROR(INDEX($A$8:$A$55,MATCH(LARGE($E$8:$E$55,48),$E$8:$E$55,0)),"") | C107: =IFERROR(LARGE($E$8:$E$55,48),"")

Sheet Category Lookup
A1: Category Sales PSF Summary
A3: Select Category: | B3: Apparel
A4: # Properties with this Category: | B4: =COUNTIF(C7:C54,">0") -> 48
A6: Property | B6: Include | C6: Tenants in Cat | D6: Total Cat SF | E6: Total Cat Sales | F6: Wtd Sales PSF
A7: Clackamas Town Center | B7: ='Property Summary'!B2 -> Y | C7: =COUNTIFS('Tenant Data'!$A$2:$A$4674,"Clackamas Town Center",'Tenant Data'!$D$2:$D$4674,$B$3,'Tenant Data'!$F$2:$F$4674,">0",'Tenant Data'!$E$2:$E$4674,"<10000") -> 25 | D7: =SUMIFS('Tenant Data'!$E$2:$E$4674,'Tenant Data'!$A$2:$A$4674,"Clackamas Town Center",'Tenant Data'!$D$2:$D$4674,$B$3,'Tenant Data'!$F$2:$F$4674,">0",'Tenant Data'!$E$2:$E$4674,"<10000") -> 95702 | E7: =SUMIFS('Tenant Data'!$F$2:$F$4674,'Tenant Data'!$A$2:$A$4674,"Clackamas Town Center",'Tenant Data'!$D$2:$D$4674,$B$3,'Tenant Data'!$E$2:$E$4674,"<10000") -> 39543528 | F7: =IFERROR(E7/D7,"") -> 413.19437
A8: Annapolis Mall | B8: ='Property Summary'!B3 -> Y | C8: =COUNTIFS('Tenant Data'!$A$2:$A$4674,"Annapolis Mall",'Tenant Data'!$D$2:$D$4674,$B$3,'Tenant Data'!$F$2:$F$4674,">0",'Tenant Data'!$E$2:$E$4674,"<10000") -> 36 | D8: =SUMIFS('Tenant Data'!$E$2:$E$4674,'Tenant Data'!$A$2:$A$4674,"Annapolis Mall",'Tenant Data'!$D$2:$D$4674,$B$3,'Tenant Data'!$F$2:$F$4674,">0",'Tenant Data'!$E$2:$E$4674,"<10000") -> 124472 | E8: =SUMIFS('Tenant Data'!$F$2:$F$4674,'Tenant Data'!$A$2:$A$4674,"Annapolis Mall",'Tenant Data'!$D$2:$D$4674,$B$3,'Tenant Data'!$E$2:$E$4674,"<10000") -> 40670815 | F8: =IFERROR(E8/D8,"") -> 326.7467
A9: Annapolis Town Center | B9: ='Property Summary'!B4 -> Y | C9: =COUNTIFS('Tenant Data'!$A$2:$A$4674,"Annapolis Town Center",'Tenant Data'!$D$2:$D$4674,$B$3,'Tenant Data'!$F$2:$F$4674,">0",'Tenant Data'!$E$2:$E$4674,"<10000") -> 2 | D9: =SUMIFS('Tenant Data'!$E$2:$E$4674,'Tenant Data'!$A$2:$A$4674,"Annapolis Town Center",'Tenant Data'!$D$2:$D$4674,$B$3,'Tenant Data'!$F$2:$F$4674,">0",'Tenant Data'!$E$2:$E$4674,"<10000") -> 7793 | E9: =SUMIFS('Tenant Data'!$F$2:$F$4674,'Tenant Data'!$A$2:$A$4674,"Annapolis Town Center",'Tenant Data'!$D$2:$D$4674,$B$3,'Tenant Data'!$E$2:$E$4674,"<10000") -> 3315511 | F9: =IFERROR(E9/D9,"") -> 425.44732
A10: Arden Fair Mall | B10: ='Property Summary'!B5 -> Y | C10: =COUNTIFS('Tenant Data'!$A$2:$A$4674,"Arden Fair Mall",'Tenant Data'!$D$2:$D$4674,$B$3,'Tenant Data'!$F$2:$F$4674,">0",'Tenant Data'!$E$2:$E$4674,"<10000") -> 32 | D10: =SUMIFS('Tenant Data'!$E$2:$E$4674,'Tenant Data'!$A$2:$A$4674,"Arden Fair Mall",'Tenant Data'!$D$2:$D$4674,$B$3,'Tenant Data'!$F$2:$F$4674,">0",'Tenant Data'!$E$2:$E$4674,"<10000") -> 112833 | E10: =SUMIFS('Tenant Data'!$F$2:$F$4674,'Tenant Data'!$A$2:$A$4674,"Arden Fair Mall",'Tenant Data'!$D$2:$D$4674,$B$3,'Tenant Data'!$E$2:$E$4674,"<10000") -> 58828912 | F10: =IFERROR(E10/D10,"") -> 521.38038
A11: Belmar | B11: ='Property Summary'!B6 -> Y | C11: =COUNTIFS('Tenant Data'!$A$2:$A$4674,"Belmar",'Tenant Data'!$D$2:$D$4674,$B$3,'Tenant Data'!$F$2:$F$4674,">0",'Tenant Data'!$E$2:$E$4674,"<10000") -> 5 | D11: =SUMIFS('Tenant Data'!$E$2:$E$4674,'Tenant Data'!$A$2:$A$4674,"Belmar",'Tenant Data'!$D$2:$D$4674,$B$3,'Tenant Data'!$F$2:$F$4674,">0",'Tenant Data'!$E$2:$E$4674,"<10000") -> 19325 | E11: =SUMIFS('Tenant Data'!$F$2:$F$4674,'Tenant Data'!$A$2:$A$4674,"Belmar",'Tenant Data'!$D$2:$D$4674,$B$3,'Tenant Data'!$E$2:$E$4674,"<10000") -> 3468669.8 | F11: =IFERROR(E11/D11,"") -> 179.49132
A12: Brandon Exchange | B12: ='Property Summary'!B7 -> Y | C12: =COUNTIFS('Tenant Data'!$A$2:$A$4674,"Brandon Exchange",'Tenant Data'!$D$2:$D$4674,$B$3,'Tenant Data'!$F$2:$F$4674,">0",'Tenant Data'!$E$2:$E$4674,"<10000") -> 32 | D12: =SUMIFS('Tenant Data'!$E$2:$E$4674,'Tenant Data'!$A$2:$A$4674,"Brandon Exchange",'Tenant Data'!$D$2:$D$4674,$B$3,'Tenant Data'!$F$2:$F$4674,">0",'Tenant Data'!$E$2:$E$4674,"<10000") -> 128917 | E12: =SUMIFS('Tenant Data'!$F$2:$F$4674,'Tenant Data'!$A$2:$A$4674,"Brandon Exchange",'Tenant Data'!$D$2:$D$4674,$B$3,'Tenant Data'!$E$2:$E$4674,"<10000") -> 52760542 | F12: =IFERROR(E12/D12,"") -> 409.25977
A13: Briarwood Mall | B13: ='Property Summary'!B8 -> Y | C13: =COUNTIFS('Tenant Data'!$A$2:$A$4674,"Briarwood Mall",'Tenant Data'!$D$2:$D$4674,$B$3,'Tenant Data'!$F$2:$F$4674,">0",'Tenant Data'!$E$2:$E$4674,"<10000") -> 25 | D13: =SUMIFS('Tenant Data'!$E$2:$E$4674,'Tenant Data'!$A$2:$A$4674,"Briarwood Mall",'Tenant Data'!$D$2:$D$4674,$B$3,'Tenant Data'!$F$2:$F$4674,">0",'Tenant Data'!$E$2:$E$4674,"<10000") -> 98694 | E13: =SUMIFS('Tenant Data'!$F$2:$F$4674,'Tenant Data'!$A$2:$A$4674,"Briarwood Mall",'Tenant Data'!$D$2:$D$4674,$B$3,'Tenant Data'!$E$2:$E$4674,"<10000") -> 2461300 | F13: =IFERROR(E13/D13,"") -> 24.938699
A14: Bridge Street Towne Centre | B14: ='Property Summary'!B9 -> Y | C14: =COUNTIFS('Tenant Data'!$A$2:$A$4674,"Bridge Street Towne Centre",'Tenant Data'!$D$2:$D$4674,$B$3,'Tenant Data'!$F$2:$F$4674,">0",'Tenant Data'!$E$2:$E$4674,"<10000") -> 16 | D14: =SUMIFS('Tenant Data'!$E$2:$E$4674,'Tenant Data'!$A$2:$A$4674,"Bridge Street Towne Centre",'Tenant Data'!$D$2:$D$4674,$B$3,'Tenant Data'!$F$2:$F$4674,">0",'Tenant Data'!$E$2:$E$4674,"<10000") -> 67517 | E14: =SUMIFS('Tenant Data'!$F$2:$F$4674,'Tenant Data'!$A$2:$A$4674,"Bridge Street Towne Centre",'Tenant Data'!$D$2:$D$4674,$B$3,'Tenant Data'!$E$2:$E$4674,"<10000") -> 28653133 | F14: =IFERROR(E14/D14,"") -> 424.38398
A15: Bridgewater Commons | B15: ='Property Summary'!B10 -> Y | C15: =COUNTIFS('Tenant Data'!$A$2:$A$4674,"Bridgewater Commons",'Tenant Data'!$D$2:$D$4674,$B$3,'Tenant Data'!$F$2:$F$4674,">0",'Tenant Data'!$E$2:$E$4674,"<10000") -> 39 | D15: =SUMIFS('Tenant Data'!$E$2:$E$4674,'Tenant Data'!$A$2:$A$4674,"Bridgewater Commons",'Tenant Data'!$D$2:$D$4674,$B$3,'Tenant Data'!$F$2:$F$4674,">0",'Tenant Data'!$E$2:$E$4674,"<10000") -> 129945 | E15: =SUMIFS('Tenant Data'!$F$2:$F$4674,'Tenant Data'!$A$2:$A$4674,"Bridgewater Commons",'Tenant Data'!$D$2:$D$4674,$B$3,'Tenant Data'!$E$2:$E$4674,"<10000") -> 59198033 | F15: =IFERROR(E15/D15,"") -> 455.56222
A16: Capital City Mall | B16: ='Property Summary'!B11 -> Y | C16: =COUNTIFS('Tenant Data'!$A$2:$A$4674,"Capital City Mall",'Tenant Data'!$D$2:$D$4674,$B$3,'Tenant Data'!$F$2:$F$4674,">0",'Tenant Data'!$E$2:$E$4674,"<10000") -> 16 | D16: =SUMIFS('Tenant Data'!$E$2:$E$4674,'Tenant Data'!$A$2:$A$4674,"Capital City Mall",'Tenant Data'!$D$2:$D$4674,$B$3,'Tenant Data'!$F$2:$F$4674,">0",'Tenant Data'!$E$2:$E$4674,"<10000") -> 61066 | E16: =SUMIFS('Tenant Data'!$F$2:$F$4674,'Tenant Data'!$A$2:$A$4674,"Capital City Mall",'Tenant Data'!$D$2:$D$4674,$B$3,'Tenant Data'!$E$2:$E$4674,"<10000") -> 21246686 | F16: =IFERROR(E16/D16,"") -> 347.92987
A17: Coastal Grand Mall | B17: ='Property Summary'!B12 -> Y | C17: =COUNTIFS('Tenant Data'!$A$2:$A$4674,"Coastal Grand Mall",'Tenant Data'!$D$2:$D$4674,$B$3,'Tenant Data'!$F$2:$F$4674,">0",'Tenant Data'!$E$2:$E$4674,"<10000") -> 22 | D17: =SUMIFS('Tenant Data'!$E$2:$E$4674,'Tenant Data'!$A$2:$A$4674,"Coastal Grand Mall",'Tenant Data'!$D$2:$D$4674,$B$3,'Tenant Data'!$F$2:$F$4674,">0",'Tenant Data'!$E$2:$E$4674,"<10000") -> 99474 | E17: =SUMIFS('Tenant Data'!$F$2:$F$4674,'Tenant Data'!$A$2:$A$4674,"Coastal Grand Mall",'Tenant Data'!$D$2:$D$4674,$B$3,'Tenant Data'!$E$2:$E$4674,"<10000") -> 30000421 | F17: =IFERROR(E17/D17,"") -> 301.59058
A18: CoolSprings Galleria | B18: ='Property Summary'!B13 -> Y | C18: =COUNTIFS('Tenant Data'!$A$2:$A$4674,"CoolSprings Galleria",'Tenant Data'!$D$2:$D$4674,$B$3,'Tenant Data'!$F$2:$F$4674,">0",'Tenant Data'!$E$2:$E$4674,"<10000") -> 33 | D18: =SUMIFS('Tenant Data'!$E$2:$E$4674,'Tenant Data'!$A$2:$A$4674,"CoolSprings Galleria",'Tenant Data'!$D$2:$D$4674,$B$3,'Tenant Data'!$F$2:$F$4674,">0",'Tenant Data'!$E$2:$E$4674,"<10000") -> 124374 | E18: =SUMIFS('Tenant Data'!$F$2:$F$4674,'Tenant Data'!$A$2:$A$4674,"CoolSprings Galleria",'Tenant Data'!$D$2:$D$4674,$B$3,'Tenant Data'!$E$2:$E$4674,"<10000") -> 47933250 | F18: =IFERROR(E18/D18,"") -> 385.39606
A19: Crabtree Valley Mall | B19: ='Property Summary'!B14 -> Y | C19: =COUNTIFS('Tenant Data'!$A$2:$A$4674,"Crabtree Valley Mall",'Tenant Data'!$D$2:$D$4674,$B$3,'Tenant Data'!$F$2:$F$4674,">0",'Tenant Data'!$E$2:$E$4674,"<10000") -> 32 | D19: =SUMIFS('Tenant Data'!$E$2:$E$4674,'Tenant Data'!$A$2:$A$4674,"Crabtree Valley Mall",'Tenant Data'!$D$2:$D$4674,$B$3,'Tenant Data'!$F$2:$F$4674,">0",'Tenant Data'!$E$2:$E$4674,"<10000") -> 122540 | E19: =SUMIFS('Tenant Data'!$F$2:$F$4674,'Tenant Data'!$A$2:$A$4674,"Crabtree Valley Mall",'Tenant Data'!$D$2:$D$4674,$B$3,'Tenant Data'!$E$2:$E$4674,"<10000") -> 65407476 | F19: =IFERROR(E19/D19,"") -> 533.76429
A20: Cross Creek Mall | B20: ='Property Summary'!B15 -> Y | C20: =COUNTIFS('Tenant Data'!$A$2:$A$4674,"Cross Creek Mall",'Tenant Data'!$D$2:$D$4674,$B$3,'Tenant Data'!$F$2:$F$4674,">0",'Tenant Data'!$E$2:$E$4674,"<10000") -> 24 | D20: =SUMIFS('Tenant Data'!$E$2:$E$4674,'Tenant Data'!$A$2:$A$4674,"Cross Creek Mall",'Tenant Data'!$D$2:$D$4674,$B$3,'Tenant Data'!$F$2:$F$4674,">0",'Tenant Data'!$E$2:$E$4674,"<10000") -> 102781 | E20: =SUMIFS('Tenant Data'!$F$2:$F$4674,'Tenant Data'!$A$2:$A$4674,"Cross Creek Mall",'Tenant Data'!$D$2:$D$4674,$B$3,'Tenant Data'!$E$2:$E$4674,"<10000") -> 33623800 | F20: =IFERROR(E20/D20,"") -> 327.14023
A21: Crossgates Center | B21: ='Property Summary'!B16 -> Y | C21: =COUNTIFS('Tenant Data'!$A$2:$A$4674,"Crossgates Center",'Tenant Data'!$D$2:$D$4674,$B$3,'Tenant Data'!$F$2:$F$4674,">0",'Tenant Data'!$E$2:$E$4674,"<10000") -> 27 | D21: =SUMIFS('Tenant Data'!$E$2:$E$4674,'Tenant Data'!$A$2:$A$4674,"Crossgates Center",'Tenant Data'!$D$2:$D$4674,$B$3,'Tenant Data'!$F$2:$F$4674,">0",'Tenant Data'!$E$2:$E$4674,"<10000") -> 126360 | E21: =SUMIFS('Tenant Data'!$F$2:$F$4674,'Tenant Data'!$A$2:$A$4674,"Crossgates Center",'Tenant Data'!$D$2:$D$4674,$B$3,'Tenant Data'!$E$2:$E$4674,"<10000") -> 52428213 | F21: =IFERROR(E21/D21,"") -> 414.91147
A22: Destiny USA | B22: ='Property Summary'!B17 -> Y | C22: =COUNTIFS('Tenant Data'!$A$2:$A$4674,"Destiny USA",'Tenant Data'!$D$2:$D$4674,$B$3,'Tenant Data'!$F$2:$F$4674,">0",'Tenant Data'!$E$2:$E$4674,"<10000") -> 41 | D22: =SUMIFS('Tenant Data'!$E$2:$E$4674,'Tenant Data'!$A$2:$A$4674,"Destiny USA",'Tenant Data'!$D$2:$D$4674,$B$3,'Tenant Data'!$F$2:$F$4674,">0",'Tenant Data'!$E$2:$E$4674,"<10000") -> 177924 | E22: =SUMIFS('Tenant Data'!$F$2:$F$4674,'Tenant Data'!$A$2:$A$4674,"Destiny USA",'Tenant Data'!$D$2:$D$4674,$B$3,'Tenant Data'!$E$2:$E$4674,"<10000") -> 59494876 | F22: =IFERROR(E22/D22,"") -> 334.38365
A23: Fayette Mall | B23: ='Property Summary'!B18 -> Y | C23: =COUNTIFS('Tenant Data'!$A$2:$A$4674,"Fayette Mall",'Tenant Data'!$D$2:$D$4674,$B$3,'Tenant Data'!$F$2:$F$4674,">0",'Tenant Data'!$E$2:$E$4674,"<10000") -> 35 | D23: =SUMIFS('Tenant Data'!$E$2:$E$4674,'Tenant Data'!$A$2:$A$4674,"Fayette Mall",'Tenant Data'!$D$2:$D$4674,$B$3,'Tenant Data'!$F$2:$F$4674,">0",'Tenant Data'!$E$2:$E$4674,"<10000") -> 147018 | E23: =SUMIFS('Tenant Data'!$F$2:$F$4674,'Tenant Data'!$A$2:$A$4674,"Fayette Mall",'Tenant Data'!$D$2:$D$4674,$B$3,'Tenant Data'!$E$2:$E$4674,"<10000") -> 59566882 | F23: =IFERROR(E23/D23,"") -> 405.16728
A24: Galleria at Tyler | B24: ='Property Summary'!B19 -> Y | C24: =COUNTIFS('Tenant Data'!$A$2:$A$4674,"Galleria at Tyler",'Tenant Data'!$D$2:$D$4674,$B$3,'Tenant Data'!$F$2:$F$4674,">0",'Tenant Data'!$E$2:$E$4674,"<10000") -> 29 | D24: =SUMIFS('Tenant Data'!$E$2:$E$4674,'Tenant Data'!$A$2:$A$4674,"Galleria at Tyler",'Tenant Data'!$D$2:$D$4674,$B$3,'Tenant Data'!$F$2:$F$4674,">0",'Tenant Data'!$E$2:$E$4674,"<10000") -> 102805 | E24: =SUMIFS('Tenant Data'!$F$2:$F$4674,'Tenant Data'!$A$2:$A$4674,"Galleria at Tyler",'Tenant Data'!$D$2:$D$4674,$B$3,'Tenant Data'!$E$2:$E$4674,"<10000") -> 32783728 | F24: =IFERROR(E24/D24,"") -> 318.89235
A25: Hamilton Place Mall | B25: ='Property Summary'!B20 -> Y | C25: =COUNTIFS('Tenant Data'!$A$2:$A$4674,"Hamilton Place Mall",'Tenant Data'!$D$2:$D$4674,$B$3,'Tenant Data'!$F$2:$F$4674,">0",'Tenant Data'!$E$2:$E$4674,"<10000") -> 27 | D25: =SUMIFS('Tenant Data'!$E$2:$E$4674,'Tenant Data'!$A$2:$A$4674,"Hamilton Place Mall",'Tenant Data'!$D$2:$D$4674,$B$3,'Tenant Data'!$F$2:$F$4674,">0",'Tenant Data'!$E$2:$E$4674,"<10000") -> 121920 | E25: =SUMIFS('Tenant Data'!$F$2:$F$4674,'Tenant Data'!$A$2:$A$4674,"Hamilton Place Mall",'Tenant Data'!$D$2:$D$4674,$B$3,'Tenant Data'!$E$2:$E$4674,"<10000") -> 44256196 | F25: =IFERROR(E25/D25,"") -> 362.99373
A26: Hanes Mall | B26: ='Property Summary'!B21 -> Y | C26: =COUNTIFS('Tenant Data'!$A$2:$A$4674,"Hanes Mall",'Tenant Data'!$D$2:$D$4674,$B$3,'Tenant Data'!$F$2:$F$4674,">0",'Tenant Data'!$E$2:$E$4674,"<10000") -> 26 | D26: =SUMIFS('Tenant Data'!$E$2:$E$4674,'Tenant Data'!$A$2:$A$4674,"Hanes Mall",'Tenant Data'!$D$2:$D$4674,$B$3,'Tenant Data'!$F$2:$F$4674,">0",'Tenant Data'!$E$2:$E$4674,"<10000") -> 114377 | E26: =SUMIFS('Tenant Data'!$F$2:$F$4674,'Tenant Data'!$A$2:$A$4674,"Hanes Mall",'Tenant Data'!$D$2:$D$4674,$B$3,'Tenant Data'!$E$2:$E$4674,"<10000") -> 34524103 | F26: =IFERROR(E26/D26,"") -> 301.8448
A27: Kansas City Collection | B27: ='Property Summary'!B22 -> Y | C27: =COUNTIFS('Tenant Data'!$A$2:$A$4674,"Kansas City Collection",'Tenant Data'!$D$2:$D$4674,$B$3,'Tenant Data'!$F$2:$F$4674,">0",'Tenant Data'!$E$2:$E$4674,"<10000") -> 23 | D27: =SUMIFS('Tenant Data'!$E$2:$E$4674,'Tenant Data'!$A$2:$A$4674,"Kansas City Collection",'Tenant Data'!$D$2:$D$4674,$B$3,'Tenant Data'!$F$2:$F$4674,">0",'Tenant Data'!$E$2:$E$4674,"<10000") -> 100797 | E27: =SUMIFS('Tenant Data'!$F$2:$F$4674,'Tenant Data'!$A$2:$A$4674,"Kansas City Collection",'Tenant Data'!$D$2:$D$4674,$B$3,'Tenant Data'!$E$2:$E$4674,"<10000") -> 51789898 | F27: =IFERROR(E27/D27,"") -> 513.80396
A28: LaCenterra at Cinco Ranch | B28: ='Property Summary'!B23 -> Y | C28: =COUNTIFS('Tenant Data'!$A$2:$A$4674,"LaCenterra at Cinco Ranch",'Tenant Data'!$D$2:$D$4674,$B$3,'Tenant Data'!$F$2:$F$4674,">0",'Tenant Data'!$E$2:$E$4674,"<10000") -> 12 | D28: =SUMIFS('Tenant Data'!$E$2:$E$4674,'Tenant Data'!$A$2:$A$4674,"LaCenterra at Cinco Ranch",'Tenant Data'!$D$2:$D$4674,$B$3,'Tenant Data'!$F$2:$F$4674,">0",'Tenant Data'!$E$2:$E$4674,"<10000") -> 44232 | E28: =SUMIFS('Tenant Data'!$F$2:$F$4674,'Tenant Data'!$A$2:$A$4674,"LaCenterra at Cinco Ranch",'Tenant Data'!$D$2:$D$4674,$B$3,'Tenant Data'!$E$2:$E$4674,"<10000") -> 23671807 | F28: =IFERROR(E28/D28,"") -> 535.17379
A29: Liberty Center | B29: ='Property Summary'!B24 -> Y | C29: =COUNTIFS('Tenant Data'!$A$2:$A$4674,"Liberty Center",'Tenant Data'!$D$2:$D$4674,$B$3,'Tenant Data'!$F$2:$F$4674,">0",'Tenant Data'!$E$2:$E$4674,"<10000") -> 22 | D29: =SUMIFS('Tenant Data'!$E$2:$E$4674,'Tenant Data'!$A$2:$A$4674,"Liberty Center",'Tenant Data'!$D$2:$D$4674,$B$3,'Tenant Data'!$F$2:$F$4674,">0",'Tenant Data'!$E$2:$E$4674,"<10000") -> 81489 | E29: =SUMIFS('Tenant Data'!$F$2:$F$4674,'Tenant Data'!$A$2:$A$4674,"Liberty Center",'Tenant Data'!$D$2:$D$4674,$B$3,'Tenant Data'!$E$2:$E$4674,"<10000") -> 19185407 | F29: =IFERROR(E29/D29,"") -> 235.43554
A30: Mall at Partridge Creek | B30: ='Property Summary'!B25 -> Y | C30: =COUNTIFS('Tenant Data'!$A$2:$A$4674,"Mall at Partridge Creek",'Tenant Data'!$D$2:$D$4674,$B$3,'Tenant Data'!$F$2:$F$4674,">0",'Tenant Data'!$E$2:$E$4674,"<10000") -> 26 | D30: =SUMIFS('Tenant Data'!$E$2:$E$4674,'Tenant Data'!$A$2:$A$4674,"Mall at Partridge Creek",'Tenant Data'!$D$2:$D$4674,$B$3,'Tenant Data'!$F$2:$F$4674,">0",'Tenant Data'!$E$2:$E$4674,"<10000") -> 105311 | E30: =SUMIFS('Tenant Data'!$F$2:$F$4674,'Tenant Data'!$A$2:$A$4674,"Mall at Partridge Creek",'Tenant Data'!$D$2:$D$4674,$B$3,'Tenant Data'!$E$2:$E$4674,"<10000") -> 29182549 | F30: =IFERROR(E30/D30,"") -> 277.10827
A31: Mall at Prince Georges | B31: ='Property Summary'!B26 -> Y | C31: =COUNTIFS('Tenant Data'!$A$2:$A$4674,"Mall at Prince Georges",'Tenant Data'!$D$2:$D$4674,$B$3,'Tenant Data'!$F$2:$F$4674,">0",'Tenant Data'!$E$2:$E$4674,"<10000") -> 11 | D31: =SUMIFS('Tenant Data'!$E$2:$E$4674,'Tenant Data'!$A$2:$A$4674,"Mall at Prince Georges",'Tenant Data'!$D$2:$D$4674,$B$3,'Tenant Data'!$F$2:$F$4674,">0",'Tenant Data'!$E$2:$E$4674,"<10000") -> 48003 | E31: =SUMIFS('Tenant Data'!$F$2:$F$4674,'Tenant Data'!$A$2:$A$4674,"Mall at Prince Georges",'Tenant Data'!$D$2:$D$4674,$B$3,'Tenant Data'!$E$2:$E$4674,"<10000") -> 14326859 | F31: =IFERROR(E31/D31,"") -> 298.45758
A32: Mall at Wellington Green | B32: ='Property Summary'!B27 -> Y | C32: =COUNTIFS('Tenant Data'!$A$2:$A$4674,"Mall at Wellington Green",'Tenant Data'!$D$2:$D$4674,$B$3,'Tenant Data'!$F$2:$F$4674,">0",'Tenant Data'!$E$2:$E$4674,"<10000") -> 22 | D32: =SUMIFS('Tenant Data'!$E$2:$E$4674,'Tenant Data'!$A$2:$A$4674,"Mall at Wellington Green",'Tenant Data'!$D$2:$D$4674,$B$3,'Tenant Data'!$F$2:$F$4674,">0",'Tenant Data'!$E$2:$E$4674,"<10000") -> 82974 | E32: =SUMIFS('Tenant Data'!$F$2:$F$4674,'Tenant Data'!$A$2:$A$4674,"Mall at Wellington Green",'Tenant Data'!$D$2:$D$4674,$B$3,'Tenant Data'!$E$2:$E$4674,"<10000") -> 21675097 | F32: =IFERROR(E32/D32,"") -> 261.22758
A33: Mall del Norte | B33: ='Property Summary'!B28 -> Y | C33: =COUNTIFS('Tenant Data'!$A$2:$A$4674,"Mall del Norte",'Tenant Data'!$D$2:$D$4674,$B$3,'Tenant Data'!$F$2:$F$4674,">0",'Tenant Data'!$E$2:$E$4674,"<10000") -> 13 | D33: =SUMIFS('Tenant Data'!$E$2:$E$4674,'Tenant Data'!$A$2:$A$4674,"Mall del Norte",'Tenant Data'!$D$2:$D$4674,$B$3,'Tenant Data'!$F$2:$F$4674,">0",'Tenant Data'!$E$2:$E$4674,"<10000") -> 58432 | E33: =SUMIFS('Tenant Data'!$F$2:$F$4674,'Tenant Data'!$A$2:$A$4674,"Mall del Norte",'Tenant Data'!$D$2:$D$4674,$B$3,'Tenant Data'!$E$2:$E$4674,"<10000") -> 15194502 | F33: =IFERROR(E33/D33,"") -> 260.03735
A34: Mayfaire Town Center | B34: ='Property Summary'!B29 -> Y | C34: =COUNTIFS('Tenant Data'!$A$2:$A$4674,"Mayfaire Town Center",'Tenant Data'!$D$2:$D$4674,$B$3,'Tenant Data'!$F$2:$F$4674,">0",'Tenant Data'!$E$2:$E$4674,"<10000") -> 32 | D34: =SUMIFS('Tenant Data'!$E$2:$E$4674,'Tenant Data'!$A$2:$A$4674,"Mayfaire Town Center",'Tenant Data'!$D$2:$D$4674,$B$3,'Tenant Data'!$F$2:$F$4674,">0",'Tenant Data'!$E$2:$E$4674,"<10000") -> 130823 | E34: =SUMIFS('Tenant Data'!$F$2:$F$4674,'Tenant Data'!$A$2:$A$4674,"Mayfaire Town Center",'Tenant Data'!$D$2:$D$4674,$B$3,'Tenant Data'!$E$2:$E$4674,"<10000") -> 50314594 | F34: =IFERROR(E34/D34,"") -> 384.60052
A35: Mesa Mall | B35: ='Property Summary'!B30 -> Y | C35: =COUNTIFS('Tenant Data'!$A$2:$A$4674,"Mesa Mall",'Tenant Data'!$D$2:$D$4674,$B$3,'Tenant Data'!$F$2:$F$4674,">0",'Tenant Data'!$E$2:$E$4674,"<10000") -> 16 | D35: =SUMIFS('Tenant Data'!$E$2:$E$4674,'Tenant Data'!$A$2:$A$4674,"Mesa Mall",'Tenant Data'!$D$2:$D$4674,$B$3,'Tenant Data'!$F$2:$F$4674,">0",'Tenant Data'!$E$2:$E$4674,"<10000") -> 58145 | E35: =SUMIFS('Tenant Data'!$F$2:$F$4674,'Tenant Data'!$A$2:$A$4674,"Mesa Mall",'Tenant Data'!$D$2:$D$4674,$B$3,'Tenant Data'!$E$2:$E$4674,"<10000") -> 20004026 | F35: =IFERROR(E35/D35,"") -> 344.03692
A36: Oak Park Mall | B36: ='Property Summary'!B31 -> Y | C36: =COUNTIFS('Tenant Data'!$A$2:$A$4674,"Oak Park Mall",'Tenant Data'!$D$2:$D$4674,$B$3,'Tenant Data'!$F$2:$F$4674,">0",'Tenant Data'!$E$2:$E$4674,"<10000") -> 31 | D36: =SUMIFS('Tenant Data'!$E$2:$E$4674,'Tenant Data'!$A$2:$A$4674,"Oak Park Mall",'Tenant Data'!$D$2:$D$4674,$B$3,'Tenant Data'!$F$2:$F$4674,">0",'Tenant Data'!$E$2:$E$4674,"<10000") -> 125309 | E36: =SUMIFS('Tenant Data'!$F$2:$F$4674,'Tenant Data'!$A$2:$A$4674,"Oak Park Mall",'Tenant Data'!$D$2:$D$4674,$B$3,'Tenant Data'!$E$2:$E$4674,"<10000") -> 51082794 | F36: =IFERROR(E36/D36,"") -> 407.65463
A37: Oklahoma City Collection | B37: ='Property Summary'!B32 -> Y | C37: =COUNTIFS('Tenant Data'!$A$2:$A$4674,"Oklahoma City Collection",'Tenant Data'!$D$2:$D$4674,$B$3,'Tenant Data'!$F$2:$F$4674,">0",'Tenant Data'!$E$2:$E$4674,"<10000") -> 14 | D37: =SUMIFS('Tenant Data'!$E$2:$E$4674,'Tenant Data'!$A$2:$A$4674,"Oklahoma City Collection",'Tenant Data'!$D$2:$D$4674,$B$3,'Tenant Data'!$F$2:$F$4674,">0",'Tenant Data'!$E$2:$E$4674,"<10000") -> 45509 | E37: =SUMIFS('Tenant Data'!$F$2:$F$4674,'Tenant Data'!$A$2:$A$4674,"Oklahoma City Collection",'Tenant Data'!$D$2:$D$4674,$B$3,'Tenant Data'!$E$2:$E$4674,"<10000") -> 38290230 | F37: =IFERROR(E37/D37,"") -> 841.37709
A38: Paddock Mall | B38: ='Property Summary'!B33 -> Y | C38: =COUNTIFS('Tenant Data'!$A$2:$A$4674,"Paddock Mall",'Tenant Data'!$D$2:$D$4674,$B$3,'Tenant Data'!$F$2:$F$4674,">0",'Tenant Data'!$E$2:$E$4674,"<10000") -> 13 | D38: =SUMIFS('Tenant Data'!$E$2:$E$4674,'Tenant Data'!$A$2:$A$4674,"Paddock Mall",'Tenant Data'!$D$2:$D$4674,$B$3,'Tenant Data'!$F$2:$F$4674,">0",'Tenant Data'!$E$2:$E$4674,"<10000") -> 46446 | E38: =SUMIFS('Tenant Data'!$F$2:$F$4674,'Tenant Data'!$A$2:$A$4674,"Paddock Mall",'Tenant Data'!$D$2:$D$4674,$B$3,'Tenant Data'!$E$2:$E$4674,"<10000") -> 17021465 | F38: =IFERROR(E38/D38,"") -> 366.47859
A39: Palisades Center | B39: ='Property Summary'!B34 -> Y | C39: =COUNTIFS('Tenant Data'!$A$2:$A$4674,"Palisades Center",'Tenant Data'!$D$2:$D$4674,$B$3,'Tenant Data'!$F$2:$F$4674,">0",'Tenant Data'!$E$2:$E$4674,"<10000") -> 20 | D39: =SUMIFS('Tenant Data'!$E$2:$E$4674,'Tenant Data'!$A$2:$A$4674,"Palisades Center",'Tenant Data'!$D$2:$D$4674,$B$3,'Tenant Data'!$F$2:$F$4674,">0",'Tenant Data'!$E$2:$E$4674,"<10000") -> 79990 | E39: =SUMIFS('Tenant Data'!$F$2:$F$4674,'Tenant Data'!$A$2:$A$4674,"Palisades Center",'Tenant Data'!$D$2:$D$4674,$B$3,'Tenant Data'!$E$2:$E$4674,"<10000") -> 27053169 | F39: =IFERROR(E39/D39,"") -> 338.20689
A40: Pearland Town Center | B40: ='Property Summary'!B35 -> Y | C40: =COUNTIFS('Tenant Data'!$A$2:$A$4674,"Pearland Town Center",'Tenant Data'!$D$2:$D$4674,$B$3,'Tenant Data'!$F$2:$F$4674,">0",'Tenant Data'!$E$2:$E$4674,"<10000") -> 14 | D40: =SUMIFS('Tenant Data'!$E$2:$E$4674,'Tenant Data'!$A$2:$A$4674,"Pearland Town Center",'Tenant Data'!$D$2:$D$4674,$B$3,'Tenant Data'!$F$2:$F$4674,">0",'Tenant Data'!$E$2:$E$4674,"<10000") -> 58655 | E40: =SUMIFS('Tenant Data'!$F$2:$F$4674,'Tenant Data'!$A$2:$A$4674,"Pearland Town Center",'Tenant Data'!$D$2:$D$4674,$B$3,'Tenant Data'!$E$2:$E$4674,"<10000") -> 15075756 | F40: =IFERROR(E40/D40,"") -> 257.02423
A41: Providence Place | B41: ='Property Summary'!B36 -> Y | C41: =COUNTIFS('Tenant Data'!$A$2:$A$4674,"Providence Place",'Tenant Data'!$D$2:$D$4674,$B$3,'Tenant Data'!$F$2:$F$4674,">0",'Tenant Data'!$E$2:$E$4674,"<10000") -> 22 | D41: =SUMIFS('Tenant Data'!$E$2:$E$4674,'Tenant Data'!$A$2:$A$4674,"Providence Place",'Tenant Data'!$D$2:$D$4674,$B$3,'Tenant Data'!$F$2:$F$4674,">0",'Tenant Data'!$E$2:$E$4674,"<10000") -> 111357 | E41: =SUMIFS('Tenant Data'!$F$2:$F$4674,'Tenant Data'!$A$2:$A$4674,"Providence Place",'Tenant Data'!$D$2:$D$4674,$B$3,'Tenant Data'!$E$2:$E$4674,"<10000") -> 38289804 | F41: =IFERROR(E41/D41,"") -> 343.8473
A42: Scottsdale Quarter | B42: ='Property Summary'!B37 -> Y | C42: =COUNTIFS('Tenant Data'!$A$2:$A$4674,"Scottsdale Quarter",'Tenant Data'!$D$2:$D$4674,$B$3,'Tenant Data'!$F$2:$F$4674,">0",'Tenant Data'!$E$2:$E$4674,"<10000") -> 24 | D42: =SUMIFS('Tenant Data'!$E$2:$E$4674,'Tenant Data'!$A$2:$A$4674,"Scottsdale Quarter",'Tenant Data'!$D$2:$D$4674,$B$3,'Tenant Data'!$F$2:$F$4674,">0",'Tenant Data'!$E$2:$E$4674,"<10000") -> 63533 | E42: =SUMIFS('Tenant Data'!$F$2:$F$4674,'Tenant Data'!$A$2:$A$4674,"Scottsdale Quarter",'Tenant Data'!$D$2:$D$4674,$B$3,'Tenant Data'!$E$2:$E$4674,"<10000") -> 53773904 | F42: =IFERROR(E42/D42,"") -> 846.39327
A43: SoNo Collection | B43: ='Property Summary'!B38 -> Y | C43: =COUNTIFS('Tenant Data'!$A$2:$A$4674,"SoNo Collection",'Tenant Data'!$D$2:$D$4674,$B$3,'Tenant Data'!$F$2:$F$4674,">0",'Tenant Data'!$E$2:$E$4674,"<10000") -> 19 | D43: =SUMIFS('Tenant Data'!$E$2:$E$4674,'Tenant Data'!$A$2:$A$4674,"SoNo Collection",'Tenant Data'!$D$2:$D$4674,$B$3,'Tenant Data'!$F$2:$F$4674,">0",'Tenant Data'!$E$2:$E$4674,"<10000") -> 81547 | E43: =SUMIFS('Tenant Data'!$F$2:$F$4674,'Tenant Data'!$A$2:$A$4674,"SoNo Collection",'Tenant Data'!$D$2:$D$4674,$B$3,'Tenant Data'!$E$2:$E$4674,"<10000") -> 24932503 | F43: =IFERROR(E43/D43,"") -> 305.74396
A44: SouthPark Mall (OH) | B44: ='Property Summary'!B39 -> Y | C44: =COUNTIFS('Tenant Data'!$A$2:$A$4674,"SouthPark Mall (OH)",'Tenant Data'!$D$2:$D$4674,$B$3,'Tenant Data'!$F$2:$F$4674,">0",'Tenant Data'!$E$2:$E$4674,"<10000") -> 31 | D44: =SUMIFS('Tenant Data'!$E$2:$E$4674,'Tenant Data'!$A$2:$A$4674,"SouthPark Mall (OH)",'Tenant Data'!$D$2:$D$4674,$B$3,'Tenant Data'!$F$2:$F$4674,">0",'Tenant Data'!$E$2:$E$4674,"<10000") -> 117294 | E44: =SUMIFS('Tenant Data'!$F$2:$F$4674,'Tenant Data'!$A$2:$A$4674,"SouthPark Mall (OH)",'Tenant Data'!$D$2:$D$4674,$B$3,'Tenant Data'!$E$2:$E$4674,"<10000") -> 37609641 | F44: =IFERROR(E44/D44,"") -> 320.6442
A45: Southgate Mall | B45: ='Property Summary'!B40 -> Y | C45: =COUNTIFS('Tenant Data'!$A$2:$A$4674,"Southgate Mall",'Tenant Data'!$D$2:$D$4674,$B$3,'Tenant Data'!$F$2:$F$4674,">0",'Tenant Data'!$E$2:$E$4674,"<10000") -> 14 | D45: =SUMIFS('Tenant Data'!$E$2:$E$4674,'Tenant Data'!$A$2:$A$4674,"Southgate Mall",'Tenant Data'!$D$2:$D$4674,$B$3,'Tenant Data'!$F$2:$F$4674,">0",'Tenant Data'!$E$2:$E$4674,"<10000") -> 58399 | E45: =SUMIFS('Tenant Data'!$F$2:$F$4674,'Tenant Data'!$A$2:$A$4674,"Southgate Mall",'Tenant Data'!$D$2:$D$4674,$B$3,'Tenant Data'!$E$2:$E$4674,"<10000") -> 20951931 | F45: =IFERROR(E45/D45,"") -> 358.77209
A46: Staten Island Mall | B46: ='Property Summary'!B41 -> Y | C46: =COUNTIFS('Tenant Data'!$A$2:$A$4674,"Staten Island Mall",'Tenant Data'!$D$2:$D$4674,$B$3,'Tenant Data'!$F$2:$F$4674,">0",'Tenant Data'!$E$2:$E$4674,"<10000") -> 25 | D46: =SUMIFS('Tenant Data'!$E$2:$E$4674,'Tenant Data'!$A$2:$A$4674,"Staten Island Mall",'Tenant Data'!$D$2:$D$4674,$B$3,'Tenant Data'!$F$2:$F$4674,">0",'Tenant Data'!$E$2:$E$4674,"<10000") -> 86550 | E46: =SUMIFS('Tenant Data'!$F$2:$F$4674,'Tenant Data'!$A$2:$A$4674,"Staten Island Mall",'Tenant Data'!$D$2:$D$4674,$B$3,'Tenant Data'!$E$2:$E$4674,"<10000") -> 27216833 | F46: =IFERROR(E46/D46,"") -> 314.4637
A47: The Shops At Evergreen Walk | B47: ='Property Summary'!B42 -> Y | C47: =COUNTIFS('Tenant Data'!$A$2:$A$4674,"The Shops At Evergreen Walk",'Tenant Data'!$D$2:$D$4674,$B$3,'Tenant Data'!$F$2:$F$4674,">0",'Tenant Data'!$E$2:$E$4674,"<10000") -> 9 | D47: =SUMIFS('Tenant Data'!$E$2:$E$4674,'Tenant Data'!$A$2:$A$4674,"The Shops At Evergreen Walk",'Tenant Data'!$D$2:$D$4674,$B$3,'Tenant Data'!$F$2:$F$4674,">0",'Tenant Data'!$E$2:$E$4674,"<10000") -> 33353 | E47: =SUMIFS('Tenant Data'!$F$2:$F$4674,'Tenant Data'!$A$2:$A$4674,"The Shops At Evergreen Walk",'Tenant Data'!$D$2:$D$4674,$B$3,'Tenant Data'!$E$2:$E$4674,"<10000") -> 9978810 | F47: =IFERROR(E47/D47,"") -> 299.18778
A48: Towson Town Center | B48: ='Property Summary'!B43 -> Y | C48: =COUNTIFS('Tenant Data'!$A$2:$A$4674,"Towson Town Center",'Tenant Data'!$D$2:$D$4674,$B$3,'Tenant Data'!$F$2:$F$4674,">0",'Tenant Data'!$E$2:$E$4674,"<10000") -> 25 | D48: =SUMIFS('Tenant Data'!$E$2:$E$4674,'Tenant Data'!$A$2:$A$4674,"Towson Town Center",'Tenant Data'!$D$2:$D$4674,$B$3,'Tenant Data'!$F$2:$F$4674,">0",'Tenant Data'!$E$2:$E$4674,"<10000") -> 98621 | E48: =SUMIFS('Tenant Data'!$F$2:$F$4674,'Tenant Data'!$A$2:$A$4674,"Towson Town Center",'Tenant Data'!$D$2:$D$4674,$B$3,'Tenant Data'!$E$2:$E$4674,"<10000") -> 37234785 | F48: =IFERROR(E48/D48,"") -> 377.55433
A49: Tysons Corner | B49: ='Property Summary'!B44 -> Y | C49: =COUNTIFS('Tenant Data'!$A$2:$A$4674,"Tysons Corner",'Tenant Data'!$D$2:$D$4674,$B$3,'Tenant Data'!$F$2:$F$4674,">0",'Tenant Data'!$E$2:$E$4674,"<10000") -> 51 | D49: =SUMIFS('Tenant Data'!$E$2:$E$4674,'Tenant Data'!$A$2:$A$4674,"Tysons Corner",'Tenant Data'!$D$2:$D$4674,$B$3,'Tenant Data'!$F$2:$F$4674,">0",'Tenant Data'!$E$2:$E$4674,"<10000") -> 189607 | E49: =SUMIFS('Tenant Data'!$F$2:$F$4674,'Tenant Data'!$A$2:$A$4674,"Tysons Corner",'Tenant Data'!$D$2:$D$4674,$B$3,'Tenant Data'!$E$2:$E$4674,"<10000") -> 1.2695764e+08 | F49: =IFERROR(E49/D49,"") -> 669.58306
A50: Walden Galleria | B50: ='Property Summary'!B45 -> Y | C50: =COUNTIFS('Tenant Data'!$A$2:$A$4674,"Walden Galleria",'Tenant Data'!$D$2:$D$4674,$B$3,'Tenant Data'!$F$2:$F$4674,">0",'Tenant Data'!$E$2:$E$4674,"<10000") -> 37 | D50: =SUMIFS('Tenant Data'!$E$2:$E$4674,'Tenant Data'!$A$2:$A$4674,"Walden Galleria",'Tenant Data'!$D$2:$D$4674,$B$3,'Tenant Data'!$F$2:$F$4674,">0",'Tenant Data'!$E$2:$E$4674,"<10000") -> 142375 | E50: =SUMIFS('Tenant Data'!$F$2:$F$4674,'Tenant Data'!$A$2:$A$4674,"Walden Galleria",'Tenant Data'!$D$2:$D$4674,$B$3,'Tenant Data'!$E$2:$E$4674,"<10000") -> 55281507 | F50: =IFERROR(E50/D50,"") -> 388.281
A51: West County Center | B51: ='Property Summary'!B46 -> Y | C51: =COUNTIFS('Tenant Data'!$A$2:$A$4674,"West County Center",'Tenant Data'!$D$2:$D$4674,$B$3,'Tenant Data'!$F$2:$F$4674,">0",'Tenant Data'!$E$2:$E$4674,"<10000") -> 31 | D51: =SUMIFS('Tenant Data'!$E$2:$E$4674,'Tenant Data'!$A$2:$A$4674,"West County Center",'Tenant Data'!$D$2:$D$4674,$B$3,'Tenant Data'!$F$2:$F$4674,">0",'Tenant Data'!$E$2:$E$4674,"<10000") -> 119097 | E51: =SUMIFS('Tenant Data'!$F$2:$F$4674,'Tenant Data'!$A$2:$A$4674,"West County Center",'Tenant Data'!$D$2:$D$4674,$B$3,'Tenant Data'!$E$2:$E$4674,"<10000") -> 65276160 | F51: =IFERROR(E51/D51,"") -> 548.0924
A52: West Towne Mall | B52: ='Property Summary'!B47 -> Y | C52: =COUNTIFS('Tenant Data'!$A$2:$A$4674,"West Towne Mall",'Tenant Data'!$D$2:$D$4674,$B$3,'Tenant Data'!$F$2:$F$4674,">0",'Tenant Data'!$E$2:$E$4674,"<10000") -> 22 | D52: =SUMIFS('Tenant Data'!$E$2:$E$4674,'Tenant Data'!$A$2:$A$4674,"West Towne Mall",'Tenant Data'!$D$2:$D$4674,$B$3,'Tenant Data'!$F$2:$F$4674,">0",'Tenant Data'!$E$2:$E$4674,"<10000") -> 95775 | E52: =SUMIFS('Tenant Data'!$F$2:$F$4674,'Tenant Data'!$A$2:$A$4674,"West Towne Mall",'Tenant Data'!$D$2:$D$4674,$B$3,'Tenant Data'!$E$2:$E$4674,"<10000") -> 25565599 | F52: =IFERROR(E52/D52,"") -> 266.93395
A53: Westfarms Mall | B53: ='Property Summary'!B48 -> Y | C53: =COUNTIFS('Tenant Data'!$A$2:$A$4674,"Westfarms Mall",'Tenant Data'!$D$2:$D$4674,$B$3,'Tenant Data'!$F$2:$F$4674,">0",'Tenant Data'!$E$2:$E$4674,"<10000") -> 39 | D53: =SUMIFS('Tenant Data'!$E$2:$E$4674,'Tenant Data'!$A$2:$A$4674,"Westfarms Mall",'Tenant Data'!$D$2:$D$4674,$B$3,'Tenant Data'!$F$2:$F$4674,">0",'Tenant Data'!$E$2:$E$4674,"<10000") -> 154722 | E53: =SUMIFS('Tenant Data'!$F$2:$F$4674,'Tenant Data'!$A$2:$A$4674,"Westfarms Mall",'Tenant Data'!$D$2:$D$4674,$B$3,'Tenant Data'!$E$2:$E$4674,"<10000") -> 98286453 | F53: =IFERROR(E53/D53,"") -> 635.24549
A54: Willow Grove Park | B54: ='Property Summary'!B49 -> Y | C54: =COUNTIFS('Tenant Data'!$A$2:$A$4674,"Willow Grove Park",'Tenant Data'!$D$2:$D$4674,$B$3,'Tenant Data'!$F$2:$F$4674,">0",'Tenant Data'!$E$2:$E$4674,"<10000") -> 16 | D54: =SUMIFS('Tenant Data'!$E$2:$E$4674,'Tenant Data'!$A$2:$A$4674,"Willow Grove Park",'Tenant Data'!$D$2:$D$4674,$B$3,'Tenant Data'!$F$2:$F$4674,">0",'Tenant Data'!$E$2:$E$4674,"<10000") -> 63784 | E54: =SUMIFS('Tenant Data'!$F$2:$F$4674,'Tenant Data'!$A$2:$A$4674,"Willow Grove Park",'Tenant Data'!$D$2:$D$4674,$B$3,'Tenant Data'!$E$2:$E$4674,"<10000") -> 26078216 | F54: =IFERROR(E54/D54,"") -> 408.852
A55: Set Average | D55: =SUMPRODUCT((B7:B54="Y")*(D7:D54<>"")*D7:D54) -> 4567966 | E55: =SUMPRODUCT((B7:B54="Y")*(E7:E54<>"")*E7:E54) -> 1.811468e+09 | F55: =IFERROR(E55/D55,"") -> 396.559
A57: Sales PSF Ranking (Highest to Lowest)
A58: Rank | B58: Property | C58: Wtd Sales PSF
A59: 1 | B59: =IFERROR(INDEX($A$7:$A$54,MATCH(LARGE($F$7:$F$54,1),$F$7:$F$54,0)),"") -> Scottsdale Quarter | C59: =IFERROR(LARGE($F$7:$F$54,1),"") -> 846.39327
A60: 2 | B60: =IFERROR(INDEX($A$7:$A$54,MATCH(LARGE($F$7:$F$54,2),$F$7:$F$54,0)),"") -> Oklahoma City Collection | C60: =IFERROR(LARGE($F$7:$F$54,2),"") -> 841.37709
A61: 3 | B61: =IFERROR(INDEX($A$7:$A$54,MATCH(LARGE($F$7:$F$54,3),$F$7:$F$54,0)),"") -> Tysons Corner | C61: =IFERROR(LARGE($F$7:$F$54,3),"") -> 669.58306
A62: 4 | B62: =IFERROR(INDEX($A$7:$A$54,MATCH(LARGE($F$7:$F$54,4),$F$7:$F$54,0)),"") -> Westfarms Mall | C62: =IFERROR(LARGE($F$7:$F$54,4),"") -> 635.24549
A63: 5 | B63: =IFERROR(INDEX($A$7:$A$54,MATCH(LARGE($F$7:$F$54,5),$F$7:$F$54,0)),"") -> West County Center | C63: =IFERROR(LARGE($F$7:$F$54,5),"") -> 548.0924
A64: 6 | B64: =IFERROR(INDEX($A$7:$A$54,MATCH(LARGE($F$7:$F$54,6),$F$7:$F$54,0)),"") -> LaCenterra at Cinco Ranch | C64: =IFERROR(LARGE($F$7:$F$54,6),"") -> 535.17379
A65: 7 | B65: =IFERROR(INDEX($A$7:$A$54,MATCH(LARGE($F$7:$F$54,7),$F$7:$F$54,0)),"") -> Crabtree Valley Mall | C65: =IFERROR(LARGE($F$7:$F$54,7),"") -> 533.76429
A66: 8 | B66: =IFERROR(INDEX($A$7:$A$54,MATCH(LARGE($F$7:$F$54,8),$F$7:$F$54,0)),"") -> Arden Fair Mall | C66: =IFERROR(LARGE($F$7:$F$54,8),"") -> 521.38038
A67: 9 | B67: =IFERROR(INDEX($A$7:$A$54,MATCH(LARGE($F$7:$F$54,9),$F$7:$F$54,0)),"") -> Kansas City Collection | C67: =IFERROR(LARGE($F$7:$F$54,9),"") -> 513.80396
A68: 10 | B68: =IFERROR(INDEX($A$7:$A$54,MATCH(LARGE($F$7:$F$54,10),$F$7:$F$54,0)),"") -> Bridgewater Commons | C68: =IFERROR(LARGE($F$7:$F$54,10),"") -> 455.56222
A69: 11 | B69: =IFERROR(INDEX($A$7:$A$54,MATCH(LARGE($F$7:$F$54,11),$F$7:$F$54,0)),"") -> Annapolis Town Center | C69: =IFERROR(LARGE($F$7:$F$54,11),"") -> 425.44732
A70: 12 | B70: =IFERROR(INDEX($A$7:$A$54,MATCH(LARGE($F$7:$F$54,12),$F$7:$F$54,0)),"") -> Bridge Street Towne Centre | C70: =IFERROR(LARGE($F$7:$F$54,12),"") -> 424.38398
A71: 13 | B71: =IFERROR(INDEX($A$7:$A$54,MATCH(LARGE($F$7:$F$54,13),$F$7:$F$54,0)),"") -> Crossgates Center | C71: =IFERROR(LARGE($F$7:$F$54,13),"") -> 414.91147
A72: 14 | B72: =IFERROR(INDEX($A$7:$A$54,MATCH(LARGE($F$7:$F$54,14),$F$7:$F$54,0)),"") -> Clackamas Town Center | C72: =IFERROR(LARGE($F$7:$F$54,14),"") -> 413.19437
A73: 15 | B73: =IFERROR(INDEX($A$7:$A$54,MATCH(LARGE($F$7:$F$54,15),$F$7:$F$54,0)),"") -> Brandon Exchange | C73: =IFERROR(LARGE($F$7:$F$54,15),"") -> 409.25977
A74: 16 | B74: =IFERROR(INDEX($A$7:$A$54,MATCH(LARGE($F$7:$F$54,16),$F$7:$F$54,0)),"") -> Willow Grove Park | C74: =IFERROR(LARGE($F$7:$F$54,16),"") -> 408.852
A75: 17 | B75: =IFERROR(INDEX($A$7:$A$54,MATCH(LARGE($F$7:$F$54,17),$F$7:$F$54,0)),"") -> Oak Park Mall | C75: =IFERROR(LARGE($F$7:$F$54,17),"") -> 407.65463
A76: 18 | B76: =IFERROR(INDEX($A$7:$A$54,MATCH(LARGE($F$7:$F$54,18),$F$7:$F$54,0)),"") -> Fayette Mall | C76: =IFERROR(LARGE($F$7:$F$54,18),"") -> 405.16728
A77: 19 | B77: =IFERROR(INDEX($A$7:$A$54,MATCH(LARGE($F$7:$F$54,19),$F$7:$F$54,0)),"") -> Walden Galleria | C77: =IFERROR(LARGE($F$7:$F$54,19),"") -> 388.281
A78: 20 | B78: =IFERROR(INDEX($A$7:$A$54,MATCH(LARGE($F$7:$F$54,20),$F$7:$F$54,0)),"") -> CoolSprings Galleria | C78: =IFERROR(LARGE($F$7:$F$54,20),"") -> 385.39606
A79: 21 | B79: =IFERROR(INDEX($A$7:$A$54,MATCH(LARGE($F$7:$F$54,21),$F$7:$F$54,0)),"") -> Mayfaire Town Center | C79: =IFERROR(LARGE($F$7:$F$54,21),"") -> 384.60052
A80: 22 | B80: =IFERROR(INDEX($A$7:$A$54,MATCH(LARGE($F$7:$F$54,22),$F$7:$F$54,0)),"") -> Towson Town Center | C80: =IFERROR(LARGE($F$7:$F$54,22),"") -> 377.55433
A81: 23 | B81: =IFERROR(INDEX($A$7:$A$54,MATCH(LARGE($F$7:$F$54,23),$F$7:$F$54,0)),"") -> Paddock Mall | C81: =IFERROR(LARGE($F$7:$F$54,23),"") -> 366.47859
A82: 24 | B82: =IFERROR(INDEX($A$7:$A$54,MATCH(LARGE($F$7:$F$54,24),$F$7:$F$54,0)),"") -> Hamilton Place Mall | C82: =IFERROR(LARGE($F$7:$F$54,24),"") -> 362.99373
A83: 25 | B83: =IFERROR(INDEX($A$7:$A$54,MATCH(LARGE($F$7:$F$54,25),$F$7:$F$54,0)),"") -> Southgate Mall | C83: =IFERROR(LARGE($F$7:$F$54,25),"") -> 358.77209
A84: 26 | B84: =IFERROR(INDEX($A$7:$A$54,MATCH(LARGE($F$7:$F$54,26),$F$7:$F$54,0)),"") -> Capital City Mall | C84: =IFERROR(LARGE($F$7:$F$54,26),"") -> 347.92987
A85: 27 | B85: =IFERROR(INDEX($A$7:$A$54,MATCH(LARGE($F$7:$F$54,27),$F$7:$F$54,0)),"") -> Mesa Mall | C85: =IFERROR(LARGE($F$7:$F$54,27),"") -> 344.03692
A86: 28 | B86: =IFERROR(INDEX($A$7:$A$54,MATCH(LARGE($F$7:$F$54,28),$F$7:$F$54,0)),"") -> Providence Place | C86: =IFERROR(LARGE($F$7:$F$54,28),"") -> 343.8473
A87: 29 | B87: =IFERROR(INDEX($A$7:$A$54,MATCH(LARGE($F$7:$F$54,29),$F$7:$F$54,0)),"") -> Palisades Center | C87: =IFERROR(LARGE($F$7:$F$54,29),"") -> 338.20689
A88: 30 | B88: =IFERROR(INDEX($A$7:$A$54,MATCH(LARGE($F$7:$F$54,30),$F$7:$F$54,0)),"") -> Destiny USA | C88: =IFERROR(LARGE($F$7:$F$54,30),"") -> 334.38365
A89: 31 | B89: =IFERROR(INDEX($A$7:$A$54,MATCH(LARGE($F$7:$F$54,31),$F$7:$F$54,0)),"") -> Cross Creek Mall | C89: =IFERROR(LARGE($F$7:$F$54,31),"") -> 327.14023
A90: 32 | B90: =IFERROR(INDEX($A$7:$A$54,MATCH(LARGE($F$7:$F$54,32),$F$7:$F$54,0)),"") -> Annapolis Mall | C90: =IFERROR(LARGE($F$7:$F$54,32),"") -> 326.7467
A91: 33 | B91: =IFERROR(INDEX($A$7:$A$54,MATCH(LARGE($F$7:$F$54,33),$F$7:$F$54,0)),"") -> SouthPark Mall (OH) | C91: =IFERROR(LARGE($F$7:$F$54,33),"") -> 320.6442
A92: 34 | B92: =IFERROR(INDEX($A$7:$A$54,MATCH(LARGE($F$7:$F$54,34),$F$7:$F$54,0)),"") -> Galleria at Tyler | C92: =IFERROR(LARGE($F$7:$F$54,34),"") -> 318.89235
A93: 35 | B93: =IFERROR(INDEX($A$7:$A$54,MATCH(LARGE($F$7:$F$54,35),$F$7:$F$54,0)),"") -> Staten Island Mall | C93: =IFERROR(LARGE($F$7:$F$54,35),"") -> 314.4637
A94: 36 | B94: =IFERROR(INDEX($A$7:$A$54,MATCH(LARGE($F$7:$F$54,36),$F$7:$F$54,0)),"") -> SoNo Collection | C94: =IFERROR(LARGE($F$7:$F$54,36),"") -> 305.74396
A95: 37 | B95: =IFERROR(INDEX($A$7:$A$54,MATCH(LARGE($F$7:$F$54,37),$F$7:$F$54,0)),"") -> Hanes Mall | C95: =IFERROR(LARGE($F$7:$F$54,37),"") -> 301.8448
A96: 38 | B96: =IFERROR(INDEX($A$7:$A$54,MATCH(LARGE($F$7:$F$54,38),$F$7:$F$54,0)),"") -> Coastal Grand Mall | C96: =IFERROR(LARGE($F$7:$F$54,38),"") -> 301.59058
A97: 39 | B97: =IFERROR(INDEX($A$7:$A$54,MATCH(LARGE($F$7:$F$54,39),$F$7:$F$54,0)),"") -> The Shops At Evergreen Walk | C97: =IFERROR(LARGE($F$7:$F$54,39),"") -> 299.18778
A98: 40 | B98: =IFERROR(INDEX($A$7:$A$54,MATCH(LARGE($F$7:$F$54,40),$F$7:$F$54,0)),"") -> Mall at Prince Georges | C98: =IFERROR(LARGE($F$7:$F$54,40),"") -> 298.45758
A99: 41 | B99: =IFERROR(INDEX($A$7:$A$54,MATCH(LARGE($F$7:$F$54,41),$F$7:$F$54,0)),"") -> Mall at Partridge Creek | C99: =IFERROR(LARGE($F$7:$F$54,41),"") -> 277.10827
A100: 42 | B100: =IFERROR(INDEX($A$7:$A$54,MATCH(LARGE($F$7:$F$54,42),$F$7:$F$54,0)),"") -> West Towne Mall | C100: =IFERROR(LARGE($F$7:$F$54,42),"") -> 266.93395
A101: 43 | B101: =IFERROR(INDEX($A$7:$A$54,MATCH(LARGE($F$7:$F$54,43),$F$7:$F$54,0)),"") -> Mall at Wellington Green | C101: =IFERROR(LARGE($F$7:$F$54,43),"") -> 261.22758
A102: 44 | B102: =IFERROR(INDEX($A$7:$A$54,MATCH(LARGE($F$7:$F$54,44),$F$7:$F$54,0)),"") -> Mall del Norte | C102: =IFERROR(LARGE($F$7:$F$54,44),"") -> 260.03735
A103: 45 | B103: =IFERROR(INDEX($A$7:$A$54,MATCH(LARGE($F$7:$F$54,45),$F$7:$F$54,0)),"") -> Pearland Town Center | C103: =IFERROR(LARGE($F$7:$F$54,45),"") -> 257.02423
...

Sheet Tenant Data
A1: Property | B1: Tenant | C1: Tenant Type | D1: Category | E1: SQFT | F1: T-12 Sales | G1: Sales PSF | H1: YoY % | I1: Gross Rent PSF | J1: Occ Cost % | K1: _LookupKey
A2: Clackamas Town Center | B2: Aerie | D2: Apparel | E2: 3123 | F2: 1490947 | G2: 477.40858 | H2: -0.062126863 | I2: 56.38 | J2: 0.11809591 | K2: Clackamas Town Center|Aerie
A3: Clackamas Town Center | B3: Aeropostale | D3: Apparel | E3: 3390 | F3: 1411295 | G3: 416.31121 | H3: 0.19593807 | I3: 49.957347 | J3: 0.12 | K3: Clackamas Town Center|Aeropostale
A4: Clackamas Town Center | B4: American Eagle Outfitters | D4: Apparel | E4: 6541 | F4: 2753207 | G4: 420.9153 | H4: 0.024640365 | I4: 59.23 | J4: 0.14071715 | K4: Clackamas Town Center|American Eagle Outfitters
A5: Clackamas Town Center | B5: AT&T | D5: Tech | E5: 6012 | F5: 0 | I5: 95.14 | K5: Clackamas Town Center|AT&T
A6: Clackamas Town Center | B6: Auntie Annes | D6: Food & Beverage | E6: 1575 | F6: 1870256 | G6: 1187.4641 | H6: 0.084080647 | I6: 216.2 | J6: 0.18206866 | K6: Clackamas Town Center|Auntie Annes
A7: Clackamas Town Center | B7: Auntie Annes | D7: Food & Beverage | E7: 1575 | F7: 1870256 | G7: 1187.4641 | H7: -0.066416168 | I7: 216.2 | J7: 0.18206866 | K7: Clackamas Town Center|Auntie Annes
A8: Clackamas Town Center | B8: Banter By Piercing Pagoda | D8: Jewelry | E8: 160 | F8: 627251 | G8: 3920.3187 | H8: -0.043607866 | I8: 392.03177 | J8: 0.099999973 | K8: Clackamas Town Center|Banter By Piercing Pagoda
A9: Clackamas Town Center | B9: Barnes & Noble | D9: Major | E9: 31951 | F9: 8824999 | G9: 276.20416 | H9: 5.2893455e-05 | I9: 22.219782 | J9: 0.08044695 | K9: Clackamas Town Center|Barnes & Noble
A10: Clackamas Town Center | B10: Bath & Body Works | D10: Health & Beauty | E10: 4050 | F10: 3468914 | G10: 856.52198 | H10: -0.0013321069 | I10: 90.47 | J10: 0.10562484 | K10: Clackamas Town Center|Bath & Body Works
A11: Clackamas Town Center | B11: Belle Brows & Beauty | D11: Service | E11: 844 | F11: 261221.84 | G11: 309.50455 | H11: -0.069732028 | I11: 110.78 | J11: 0.35792689 | K11: Clackamas Town Center|Belle Brows & Beauty
A12: Clackamas Town Center | B12: BOBA TEA CREW | D12: Food & Beverage | E12: 609 | F12: 217771 | G12: 357.58785 | H12: -0.13564254 | I12: 109.83 | J12: 0.30714131 | K12: Clackamas Town Center|BOBA TEA CREW
A13: Clackamas Town Center | B13: Bonchon | D13: Restaurant | E13: 1256 | F13: 1025675.9 | G13: 816.62091 | H13: -0.053244759 | I13: 76.09 | J13: 0.093176649 | K13: Clackamas Town Center|Bonchon
A14: Clackamas Town Center | B14: Box Lunch | D14: Apparel | E14: 1592 | F14: 869307 | G14: 546.04711 | H14: -0.16447634 | I14: 109.85 | J14: 0.20117312 | K14: Clackamas Town Center|Box Lunch
A15: Clackamas Town Center | B15: BRAGANZA PEARL TEA | D15: Food & Beverage | E15: 480 | F15: 1015329 | G15: 2115.2688 | H15: -0.047097047 | I15: 312.89 | J15: 0.14791974 | K15: Clackamas Town Center|BRAGANZA PEARL TEA
A16: Clackamas Town Center | B16: Buckle | D16: Apparel | E16: 5386 | F16: 2742082 | G16: 509.11289 | H16: -0.085705552 | I16: 102.25 | J16: 0.20083954 | K16: Clackamas Town Center|Buckle
A17: Clackamas Town Center | B17: Build-A-Bear Workshop | D17: Hobby & Novelty | E17: 3225 | F17: 1403055 | G17: 435.05581 | H17: -0.0080132795 | I17: 69.577815 | J17: 0.15992848 | K17: Clackamas Town Center|Build-A-Bear Workshop
... A24: Clackamas Town Center | B24: Claire's | D24: Jewelry | E24: 937 | F24: 790518 | G24: 843.66916 | H24: -0.074508152 | I24: 250.62 | J24: 0.29705957 | K24: Clackamas Town Center|Claire's
A25: Clackamas Town Center | B25: Claw City | D25: Hobby & Novelty | E25: 2756 | F25: 420748 | G25: 152.66618 | I25: 52.83 | J25: 0.34604913 | K25: Clackamas Town Center|Claw City
A26: Clackamas Town Center | B26: Coach | D26: Apparel | E26: 2035 | F26: 2073580 | G26: 1018.9582 | H26: 0.197353 | I26: 122.27498 | J26: 0.11999999 | K26: Clackamas Town Center|Coach
A27: Clackamas Town Center | B27: CRAZY FRUITS | D27: Food & Beverage | E27: 626 | F27: 338927 | G27: 541.41693 | H27: 0.066182102 | I27: 109.47 | J27: 0.20219168 | K27: Clackamas Town Center|CRAZY FRUITS
A28: Clackamas Town Center | B28: Cricket Wireless | D28: Tech | E28: 882 | F28: 0 | I28: 58.01 | K28: Clackamas Town Center|Cricket Wireless
A29: Clackamas Town Center | B29: CROFFLE CREW CAFÉ | D29: Food & Beverage | E29: 2442 | F29: 2047924 | G29: 838.62572 | I29: 95.163384 | J29: 0.11347539 | K29: Clackamas Town Center|CROFFLE CREW CAFÉ
A30: Clackamas Town Center | B30: Dave & Busters | D30: Major | E30: 36470 | F30: 5768502 | G30: 158.17115 | H30: -0.12708422 | I30: 41.75 | J30: 0.26395458 | K30: Clackamas Town Center|Dave & Busters
A31: Clackamas Town Center | B31: DOSHA SALON SPA | D31: Service | E31: 3360 | F31: 568064 | G31: 169.06667 | H31: 0.093545378 | I31: 35.86 | J31: 0.21210568 | K31: Clackamas Town Center|DOSHA SALON SPA
A32: Clackamas Town Center | B32: DOUGH ZONE | D32: Restaurant | E32: 5800 | F32: 1942214 | G32: 334.86448 | I32: 45.86 | J32: 0.13695092 | K32: Clackamas Town Center|DOUGH ZONE
A33: Clackamas Town Center | B33: DUCK STORE, THE | D33: Hobby & Novelty | E33: 2762 | F33: 1157641.8 | G33: 419.13171 | H33: 0.45105308 | I33: 62.089551 | J33: 0.14813852 | K33: Clackamas Town Center|DUCK STORE, THE
A34: Clackamas Town Center | B34: EUPHORIA BODY PIERCING & TATTOO | D34: Service | E34: 1073 | F34: 588311 | G34: 548.28611 | H34: 0.25343647 | I34: 90.85 | J34: 0.16569816 | K34: Clackamas Town Center|EUPHORIA BODY PIERCING & TATTOO
A35: Clackamas Town Center | B35: Express | D35: Apparel | E35: 4475 | F35: 1296650 | G35: 289.75419 | H35: -0.20682775 | I35: 26.077873 | J35: 0.089999986 | K35: Clackamas Town Center|Express
A36: Clackamas Town Center | B36: Famous Footwear | D36: Shoes | E36: 3937 | F36: 1429111 | G36: 362.99492 | H36: 0.0049828144 | I36: 38.1 | J36: 0.10496015 | K36: Clackamas Town Center|Famous Footwear
A37: Clackamas Town Center | B37: Foot Locker | D37: Shoes | E37: 4512 | F37: 4401173 | G37: 975.43728 | H37: 0.15338281 | I37: 108.16853 | J37: 0.11089234 | K37: Clackamas Town Center|Foot Locker
A38: Clackamas Town Center | B38: Foxy Nails | D38: Service | E38: 1444 | F38: 373398 | G38: 258.58587 | H38: -0.22741768 | I38: 122.33 | J38: 0.47307302 | K38: Clackamas Town Center|Foxy Nails
A39: Clackamas Town Center | B39: Funtastic Playtorium | D39: Hobby & Novelty | E39: 5979 | F39: 327553 | G39: 54.78391 | I39: 20.07 | J39: 0.36634844 | K39: Clackamas Town Center|Funtastic Playtorium
A40: Clackamas Town Center | B40: GameStop | D40: Hobby & Novelty | E40: 2230 | F40: 1165585 | G40: 522.68386 | H40: -0.07065317 | I40: 53 | J40: 0.10139973 | K40: Clackamas Town Center|GameStop
A41: Clackamas Town Center | B41: GNC | D41: Health & Beauty | E41: 1220 | F41: 541991 | G41: 444.25492 | H41: -0.130995 | I41: 88.47 | J41: 0.19914242 | K41: Clackamas Town Center|GNC
A42: Clackamas Town Center | B42: H&M | D42: Apparel | E42: 15726 | F42: 3404314 | G42: 216.47679 | H42: -0.27792223 | I42: 28.81 | J42: 0.13308586 | K42: Clackamas Town Center|H&M
A43: Clackamas Town Center | B43: Hallmark | D43: Hobby & Novelty | E43: 3099 | F43: 821200 | G43: 264.98871 | H43: 0.0045825297 | I43: 36.97 | J43: 0.13951538 | K43: Clackamas Town Center|Hallmark
A44: Clackamas Town Center | B44: HEARTH | D44: Shoes | E44: 2644 | F44: 731170 | G44: 276.53933 | I44: 81.81 | J44: 0.29583495 | K44: Clackamas Town Center|HEARTH
A45: Clackamas Town Center | B45: HIGHLANDER | D45: Apparel | E45: 2329 | F45: 433493 | G45: 186.12838 | H45: -0.04425501 | I45: 52.28 | J45: 0.2808814 | K45: Clackamas Town Center|HIGHLANDER
A46: Clackamas Town Center | B46: Hollister | D46: Service | E46: 7501 | F46: 4628027 | G46: 616.988 | H46: 0.13356173 | I46: 96.837444 | J46: 0.15695191 | K46: Clackamas Town Center|Hollister
A47: Clackamas Town Center | B47: Hot Topic | D47: Apparel | E47: 2063 | F47: 1774318 | G47: 860.06689 | H47: -0.093739619 | I47: 123.21626 | J47: 0.14326358 | K47: Clackamas Town Center|Hot Topic
A48: Clackamas Town Center | B48: Icing By Claires | D48: Jewelry | E48: 1597 | F48: 337571.75 | G48: 211.37868 | H48: -0.10624524 | I48: 17.618 | J48: 0.083348047 | K48: Clackamas Town Center|Icing By Claires
A49: Clackamas Town Center | B49: J. Jill | D49: Apparel | E49: 3432 | F49: 689786 | G49: 200.9866 | H49: 0.053763175 | I49: 27.99 | J49: 0.13926302 | K49: Clackamas Town Center|J. Jill
A50: Clackamas Town Center | B50: Jamba Juice | D50: Food & Beverage | E50: 671 | F50: 1483403 | G50: 2210.7347 | H50: -0.030933498 | I50: 417.92 | J50: 0.18904122 | K50: Clackamas Town Center|Jamba Juice
A51: Clackamas Town Center | B51: JOE KASSAB JEWELERS | D51: Jewelry | E51: 1257 | F51: 2472677 | G51: 1967.1257 | H51: -0.034861045 | I51: 249.72 | J51: 0.12694664 | K51: Clackamas Town Center|JOE KASSAB JEWELERS
A52: Clackamas Town Center | B52: Journeys | D52: Shoes | E52: 3286 | F52: 3533328 | G52: 1075.2672 | H52: 0.094981463 | I52: 170.12 | J52: 0.15821184 | K52: Clackamas Town Center|Journeys
A53: Clackamas Town Center | B53: JUST SPORTS | D53: Apparel | E53: 1476 | F53: 529720 | G53: 358.88889 | H53: -0.15195932 | I53: 51.25 | J53: 0.14280186 | K53: Clackamas Town Center|JUST SPORTS
A54: Clackamas Town Center | B54: Kay Jewelers | D54: Jewelry | E54: 1935 | F54: 3020117 | G54: 1560.784 | H54: -0.07913802 | I54: 196.57 | J54: 0.12594312 | K54: Clackamas Town Center|Kay Jewelers
A55: Clackamas Town Center | B55: Kellys Cajun Grill | D55: Food & Beverage | E55: 598 | F55: 890555 | G55: 1489.2224 | H55: 0.096994052 | I55: 331.88 | J55: 0.22285456 | K55: Clackamas Town Center|Kellys Cajun Grill
A56: Clackamas Town Center | B56: Kellys Cajun Grill | D56: Food & Beverage | E56: 598 | F56: 890555 | G56: 1489.2224 | I56: 331.88 | J56: 0.22285456 | K56: Clackamas Town Center|Kellys Cajun Grill
A57: Clackamas Town Center | B57: Lenscrafters | D57: Service | E57: 3940 | F57: 1761881 | G57: 447.17792 | H57: 0.059744521 | I57: 59.89 | J57: 0.1339288 | K57: Clackamas Town Center|Lenscrafters
A58: Clackamas Town Center | B58: Lids | D58: Apparel | E58: 750 | F58: 774766 | G58: 1033.0213 | H58: 0.049408148 | I58: 118.79566 | J58: 0.11499826 | K58: Clackamas Town Center|Lids
A59: Clackamas Town Center | B59: Loft | D59: Apparel | E59: 5700 | F59: 418866 | G59: 73.485263 | H59: -0.42777621 | I59: 19.71 | J59: 0.26821704 | K59: Clackamas Town Center|Loft
A60: Clackamas Town Center | B60: Lolli And Pops | D60: Food & Beverage | E60: 2274 | F60: 401767 | G60: 176.67854 | H60: -0.20042511 | I60: 26.501805 | J60: 0.15000014 | K60: Clackamas Town Center|Lolli And Pops
A61: Clackamas Town Center | B61: Lovisa | D61: Jewelry | E61: 1325 | F61: 685034 | G61: 517.00679 | H61: 0.027088969 | I61: 78.1542 | J61: 0.15116668 | K61: Clackamas Town Center|Lovisa
A62: Clackamas Town Center | B62: Lululemon | D62: Apparel | E62: 4455 | F62: 4227251 | G62: 948.87789 | H62: -0.11823273 | I62: 61.47 | J62: 0.064781781 | K62: Clackamas Town Center|Lululemon
A63: Clackamas Town Center | B63: Lush Fresh Handmade Cosmetics | D63: Health & Beauty | E63: 1083 | F63: 1308357 | G63: 1208.0859 | H63: -0.060824786 | I63: 162.60177 | J63: 0.13459454 | K63: Clackamas Town Center|Lush Fresh Handmade Cosmetics
A64: Clackamas Town Center | B64: M.A.C Cosmetics | D64: Health & Beauty | E64: 1490 | F64: 451254 | G64: 302.85503 | H64: 0.087691494 | I64: 154.69 | J64: 0.51077243 | K64: Clackamas Town Center|M.A.C Cosmetics
A65: Clackamas Town Center | B65: MADE IN OREGON | D65: Apparel | E65: 2736 | F65: 810987 | G65: 296.41338 | H65: -0.088867745 | I65: 60.3 | J65: 0.20343211 | K65: Clackamas Town Center|MADE IN OREGON
A66: Clackamas Town Center | B66: Mattress World Northwest | D66: Major | E66: 3673 | F66: 0 | I66: 30.85 | K66: Clackamas Town Center|Mattress World Northwest
A67: Clackamas Town Center | B67: Maurices | D67: Apparel | E67: 5212 | F67: 551644 | G67: 105.84114 | H67: -0.050680648 | I67: 18.75 | J67: 0.17715229 | K67: Clackamas Town Center|Maurices
A68: Clackamas Town Center | B68: MEZCALUNA | D68: Restaurant | E68: 4893 | F68: 4752652 | G68: 971.31657 | H68: -0.019772628 | I68: 73.304065 | J68: 0.075468768 | K68: Clackamas Town Center|MEZCALUNA
A69: Clackamas Town Center | B69: MINDTRIX | D69: Service | E69: 2526 | F69: 262653 | G69: 103.97981 | H69: -0.0088027296 | I69: 21.38 | J69: 0.20561684 | K69: Clackamas Town Center|MINDTRIX
A70: Clackamas Town Center | B70: Miniso | D70: Hobby & Novelty | E70: 3435 | F70: 1736059 | G70: 505.40291 | H70: 0.54189522 | I70: 75.810445 | J70: 0.15000002 | K70: Clackamas Town Center|Miniso
A71: Clackamas Town Center | B71: MIRAKUTEI SUSHI & RAMEN | D71: Restaurant | E71: 4580 | F71: 1411543 | G71: 308.19716 | H71: 0.019396542 | I71: 42.74 | J71: 0.13867746 | K71: Clackamas Town Center|MIRAKUTEI SUSHI & RAMEN
A72: Clackamas Town Center | B72: Morgan Jewelers | D72: Jewelry | E72: 847 | F72: 984150 | G72: 1161.9244 | H72: -0.041214123 | I72: 222.82 | J72: 0.19176806 | K72: Clackamas Town Center|Morgan Jewelers
A73: Clackamas Town Center | B73: Noodles & Company | D73: Restaurant | E73: 2900 | F73: 0 | I73: 91.99 | K73: Clackamas Town Center|Noodles & Company
A74: Clackamas Town Center | B74: Nori Japan | D74: Food & Beverage | E74: 676 | F74: 1061558 | G74: 1570.3521 | H74: 0.068128703 | I74: 379.34 | J74: 0.24156366 | K74: Clackamas Town Center|Nori Japan
A75: Clackamas Town Center | B75: O CHI REFLEXOLOGY | D75: Service | E75: 1405 | F75: 213680 | G75: 152.08541 | H75: 0.083062697 | I75: 41.24 | J75: 0.27116342 | K75: Clackamas Town Center|O CHI REFLEXOLOGY
A76: Clackamas Town Center | B76: OIL & VINEGAR | D76: Food & Beverage | E76: 823 | F76: 385640 | G76: 468.57837 | H76: -0.058440943 | I76: 115.19 | J76: 0.24582867 | K76: Clackamas Town Center|OIL & VINEGAR
A77: Clackamas Town Center | B77: OSWEGO GRILL | D77: Restaurant | E77: 6853 | F77: 6123494.8 | G77: 893.54952 | H77: 0.022841505 | I77: 57.004645 | J77: 0.063795731 | K77: Clackamas Town Center|OSWEGO GRILL
A78: Clackamas Town Center | B78: Pacific Sunwear | D78: Apparel | E78: 4626 | F78: 1546130 | G78: 334.22611 | H78: 0.058364274 | I78: 33.99 | J78: 0.10169762 | K78: Clackamas Town Center|Pacific Sunwear
A79: Clackamas Town Center | B79: Panda Express | D79: Restaurant | E79: 780 | F79: 2520327 | G79: 3231.1885 | H79: 0.045261158 | I79: 602.99 | J79: 0.18661555 | K79: Clackamas Town Center|Panda Express
A80: Clackamas Town Center | B80: Pandora | D80: Jewelry | E80: 1300 | F80: 1641704 | G80: 1262.8492 | H80: 0.16895047 | I80: 139.72944 | J80: 0.11064618 | K80: Clackamas Town Center|Pandora
A81: Clackamas Town Center | B81: Panera Bread | D81: Restaurant | E81: 4550 | F81: 2999004 | G81: 659.12176 | H81: -0.080002632 | I81: 67.3 | J81: 0.10210557 | K81: Clackamas Town Center|Panera Bread
A82: Clackamas Town Center | B82: PHAGANS | D82: Major | E82: 13177 | F82: 1837999 | G82: 139.48539 | H82: 0 | I82: 29.34 | J82: 0.21034461 | K82: Clackamas Town Center|PHAGANS
A83: Clackamas Town Center | B83: POKE ZONE | D83: Food & Beverage | E83: 683 | F83: 228134 | G83: 334.01757 | I83: 116.58 | J83: 0.34902356 | K83: Clackamas Town Center|POKE ZONE
A84: Clackamas Town Center | B84: Pop Mart | D84: Hobby & Novelty | E84: 1405 | F84: 4520781 | G84: 3217.6377 | I84: 254.35064 | J84: 0.079048873 | K84: Clackamas Town Center|Pop Mart
A85: Clackamas Town Center | B85: Popeyes Louisiana Kitchen | D85: Restaurant | E85: 1018 | F85: 1323018.9 | G85: 1299.6257 | H85: 0.058638434 | I85: 180.43 | J85: 0.13883228 | K85: Clackamas Town Center|Popeyes Louisiana Kitchen
A86: Clackamas Town Center | B86: PRIM NAILS SPA | D86: Service | E86: 1941 | F86: 449873 | G86: 231.77383 | H86: 0.0019724627 | I86: 61.044346 | J86: 0.26337894 | K86: Clackamas Town Center|PRIM NAILS SPA
A87: Clackamas Town Center | B87: Pro Image Sports | D87: Apparel | E87: 1830 | F87: 644382 | G87: 352.12131 | H87: -0.19963491 | I87: 42.99 | J87: 0.12208861 | K87: Clackamas Town Center|Pro Image Sports
A88: Clackamas Town Center | B88: REI | D88: Major | E88: 28993 | F88: 0 | I88: 36.41 | K88: Clackamas Town Center|REI
A89: Clackamas Town Center | B89: REI | D89: Major | E89: 16113 | F89: 0 | I89: 23.5 | K89: Clackamas Town Center|REI
A90: Clackamas Town Center | B90: Sbarro The Italian Eatery | D90: Food & Beverage | E90: 603 | F90: 1002376 | G90: 1662.3151 | H90: -0.089335181 | I90: 330.92 | J90: 0.19907177 | K90: Clackamas Town Center|Sbarro The Italian Eatery
A91: Clackamas Town Center | B91: Sees Candies | D91: Food & Beverage | E91: 1055 | F91: 1621717 | G91: 1537.1725 | H91: -0.20631292 | I91: 159.05 | J91: 0.10346919 | K91: Clackamas Town Center|Sees Candies
A92: Clackamas Town Center | B92: Sephora | D92: Health & Beauty | E92: 5295 | F92: 8638735 | G92: 1631.4891 | H92: -0.0047327436 | I92: 123.11194 | J92: 0.075459857 | K92: Clackamas Town Center|Sephora
A93: Clackamas Town Center | B93: SHARETEA | D93: Food & Beverage | E93: 1000 | F93: 444569 | G93: 444.569 | H93: -0.16035031 | I93: 70.7 | J93: 0.15903043 | K93: Clackamas Town Center|SHARETEA
A94: Clackamas Town Center | B94: SHOE MILL | D94: Shoes | E94: 1335 | F94: 1098995 | G94: 823.21723 | I94: 83.51 | J94: 0.10144346 | K94: Clackamas Town Center|SHOE MILL
A95: Clackamas Town Center | B95: SIZZLING INDIAN KITCHEN | D95: Food & Beverage | E95: 2574 | F95: 803501 | G95: 312.16045 | I95: 70.31 | J95: 0.22523673 | K95: Clackamas Town Center|SIZZLING INDIAN KITCHEN
A96: Clackamas Town Center | B96: Sleep Number | D96: Major | E96: 3470 | F96: 1774523 | G96: 511.38991 | H96: -0.05575894 | I96: 96.97 | J96: 0.18962048 | K96: Clackamas Town Center|Sleep Number
A97: Clackamas Town Center | B97: Soma Intimates | D97: Apparel | E97: 2500 | F97: 518949 | G97: 207.5796 | H97: 0.001663254 | I97: 41.13 | J97: 0.19814086 | K97: Clackamas Town Center|Soma Intimates
A98: Clackamas Town Center | B98: Spencer Gifts | D98: Hobby & Novelty | E98: 2143 | F98: 1518681 | G98: 708.67056 | H98: -0.11039823 | I98: 130.21 | J98: 0.18373841 | K98: Clackamas Town Center|Spencer Gifts
A99: Clackamas Town Center | B99: Sunglass Hut | D99: Apparel | E99: 1073 | F99: 709287 | G99: 661.03169 | H99: -0.060218796 | I99: 137.97 | J99: 0.20871919 | K99: Clackamas Town Center|Sunglass Hut
A100: Clackamas Town Center | B100: Sushi Burrito | D100: Food & Beverage | E100: 729 | F100: 0 | I100: 176.34 | K100: Clackamas Town Center|Sushi Burrito
A101: Clackamas Town Center | B101: SWEET MOCHI | D101: Food & Beverage | E101: 713 | F101: 559532 | G101: 784.75736 | I101: 161.69 | J101: 0.20603821 | K101: Clackamas Town Center|SWEET MOCHI
A102: Clackamas Town Center | B102: TACO TIME | D102: Food & Beverage | E102: 743 | F102: 586485 | G102: 789.34724 | H102: -0.0001427579 | I102: 159.04 | J102: 0.20148294 | K102: Clackamas Town Center|TACO TIME
A103: Clackamas Town Center | B103: The Cheesecake Factory | D103: Restaurant | E103: 9032 | F103: 8800103 | G103: 974.32496 | H103: 0.025334794 | I103: 63.11 | J103: 0.064773051 | K103: Clackamas Town Center|The Cheesecake Factory
A104: Clackamas Town Center | B104: Tillys | D104: Apparel | E104: 7259 | F104: 1922682 | G104: 264.86871 | H104: -0.057656971 | I104: 49.3 | J104: 0.18612995 | K104: Clackamas Town Center|Tillys
A105: Clackamas Town Center | B105: T-Mobile | D105: Tech | E105: 2025 | F105: 1039091 | G105: 513.13136 | H105: 0.0093627287 | I105: 171.93 | J105: 0.3350604 | K105: Clackamas Town Center|T-Mobile
A106: Clackamas Town Center | B106: Torrid | D106: Apparel | E106: 3812 | F106: 1051462 | G106: 275.82949 | H106: -0.00078366192 | I106: 68.21 | J106: 0.24729046 | K106: Clackamas Town Center|Torrid
...

Sheet Cross Comparison
A1: Tenant Cross-Comparison: Sales PSF
A2: Tenant | B2: Category | C2: # Props | D2: Clackamas Town | E2: Annapolis | F2: Annapolis Town | G2: Arden Fair | H2: Belmar | I2: Brandon Exchange | J2: Briarwood | K2: Bridge Street Tow. | L2: Bridgewater Commo. | M2: Capital City | N2: Coastal Grand | O2: CoolSprings Galle. | P2: Crabtree Valley | Q2: Cross Creek | R2: Crossgates | S2: Destiny USA | T2: Fayette | U2: Galleria at Tyler | V2: Hamilton Place | W2: Hanes | X2: Kansas City | Y2: LaCenterra at Cin. | Z2: Liberty | AA2: Mall at Partridge. | AB2: Mall at Prince Ge. | AC2: Mall at Wellingto. | AD2: Mall del Norte | AE2: Mayfaire Town | AF2: Mesa | AG2: Oak Park | AH2: Oklahoma City | AI2: Paddock | AJ2: Palisades | AK2: Pearland Town | AL2: Providence Place | AM2: Scottsdale Quarter | AN2: SoNo | AO2: SouthPark (OH) | AP2: Southgate | AQ2: Staten Island | AR2: Evergreen Walk | AS2: Towson Town | AT2: Tysons Corner | AU2: Walden Galleria | AV2: West County | AW2: West Towne | AX2: Westfarms | AY2: Willow Grove Park | AZ2: Set Avg | BA2: Delta | BB2: Rank | BC2: Of
A3: Include → | D3: ='Property Summary'!B2 -> Y | E3: ='Property Summary'!B3 -> Y | F3: ='Property Summary'!B4 -> Y | G3: ='Property Summary'!B5 -> Y | H3: ='Property Summary'!B6 -> Y | I3: ='Property Summary'!B7 -> Y | J3: ='Property Summary'!B8 -> Y | K3: ='Property Summary'!B9 -> Y | L3: ='Property Summary'!B10 -> Y | M3: ='Property Summary'!B11 -> Y | N3: ='Property Summary'!B12 -> Y | O3: ='Property Summary'!B13 -> Y | P3: ='Property Summary'!B14 -> Y | Q3: ='Property Summary'!B15 -> Y | R3: ='Property Summary'!B16 -> Y | S3: ='Property Summary'!B17 -> Y | T3: ='Property Summary'!B18 -> Y | U3: ='Property Summary'!B19 -> Y | V3: ='Property Summary'!B20 -> Y | W3: ='Property Summary'!B21 -> Y | X3: ='Property Summary'!B22 -> Y | Y3: ='Property Summary'!B23 -> Y | Z3: ='Property Summary'!B24 -> Y | AA3: ='Property Summary'!B25 -> Y | AB3: ='Property Summary'!B26 -> Y | AC3: ='Property Summary'!B27 -> Y | AD3: ='Property Summary'!B28 -> Y | AE3: ='Property Summary'!B29 -> Y | AF3: ='Property Summary'!B30 -> Y | AG3: ='Property Summary'!B31 -> Y | AH3: ='Property Summary'!B32 -> Y | AI3: ='Property Summary'!B33 -> Y | AJ3: ='Property Summary'!B34 -> Y | AK3: ='Property Summary'!B35 -> Y | AL3: ='Property Summary'!B36 -> Y | AM3: ='Property Summary'!B37 -> Y | AN3: ='Property Summary'!B38 -> Y | AO3: ='Property Summary'!B39 -> Y | AP3: ='Property Summary'!B40 -> Y | AQ3: ='Property Summary'!B41 -> Y | AR3: ='Property Summary'!B42 -> Y | AS3: ='Property Summary'!B43 -> Y | AT3: ='Property Summary'!B44 -> Y | AU3: ='Property Summary'!B45 -> Y | AV3: ='Property Summary'!B46 -> Y | AW3: ='Property Summary'!B47 -> Y | AX3: ='Property Summary'!B48 -> Y | AY3: ='Property Summary'!B49 -> Y
A4: Bath & Body Works | B4: Health & Beauty | C4: 44 | D4: 856.52198 | E4: 1000.6235 | G4: 877.42436 | H4: 319.70937 | I4: 1422.121 | J4: 59.77435 | K4: 1122.9743 | L4: 1014.7793 | M4: 782.30853 | N4: 932.8354 | O4: 812.46673 | P4: 912.57249 | Q4: 1253.073 | R4: 743.93088 | S4: 657.87952 | T4: 808.93449 | U4: 741.46712 | V4: 1007.0956 | W4: 634.9319 | X4: 638.86043 | Z4: 518.87132 | AA4: 665.90714 | AB4: 932.165 | AC4: 1055.9232 | AD4: 998.02265 | AE4: 797.26366 | AF4: 1043.6031 | AG4: 697.27756 | AI4: 1149.6938 | AJ4: 584.15453 | AK4: 781.83727 | AL4: 809.64706 | AM4: 492.22522 | AN4: 602.0177 | AO4: 839.40791 | AP4: 652.01533 | AQ4: 793.65396 | AS4: 900.67122 | AT4: 1118.9578 | AU4: 491.5012 | AV4: 1057.5691 | AW4: 578.84848 | AX4: 1112.3191 | AY4: 753.55272 | AZ4: =IFERROR(AVERAGEIFS(D4:AY4,$D$3:$AY$3,"Y",D4:AY4,"<>"),"") -> 818.80433 | BA4: =IFERROR(D4-AZ4,"") -> 37.717649 | BB4: =IFERROR(COUNTIFS(D4:AY4,">"&D4,$D$3:$AY$3,"Y",D4:AY4,"<>")+1,"") -> 19 | BC4: =COUNTIFS($D$3:$AY$3,"Y",D4:AY4,"<>") -> 44
A5: Claire's | B5: Jewelry | C5: 42 | D5: 843.66916 | E5: 660.49612 | G5: 816.63636 | H5: 267.67188 | I5: 950.3913 | J5: 46.681416 | K5: 616.24223 | L5: 737.63667 | M5: 456.01614 | N5: 425.41458 | O5: 685.03626 | P5: 649.53265 | Q5: 791.86802 | R5: 489.94863 | S5: 592.94305 | T5: 687.73484 | U5: 565.46276 | V5: 573.11313 | W5: 343.49944 | X5: 223.65323 | Y5: 546.4728 | Z5: 288.18498 | AA5: 543.31722 | AB5: 470.58272 | AC5: 479.77177 | AD5: 353.7354 | AE5: 245.20159 | AF5: 360.53706 | AG5: 803.05396 | AI5: 494.24267 | AJ5: 281.1046 | AK5: 444.24173 | AO5: 414.63783 | AP5: 404.79879 | AQ5: 559.66118 | AS5: 421.85513 | AT5: 656.82972 | AU5: 541.02119 | AV5: 596.12063 | AW5: 211.37874 | AX5: 723.32056 | AY5: 288.60852 | AZ5: =IFERROR(AVERAGEIFS(D5:AY5,$D$3:$AY$3,"Y",D5:AY5,"<>"),"") -> 513.15063 | BA5: =IFERROR(D5-AZ5,"") -> 330.51852 | BB5: =IFERROR(COUNTIFS(D5:AY5,">"&D5,$D$3:$AY$3,"Y",D5:AY5,"<>")+1,"") -> 2 | BC5: =COUNTIFS($D$3:$AY$3,"Y",D5:AY5,"<>") -> 42
A6: Sunglass Hut | B6: Apparel | C6: 39 | D6: 661.03169 | E6: 761.30343 | G6: 1918.4647 | I6: 1038.8517 | J6: 90.082645 | K6: 936.09944 | L6: 2514.5009 | M6: 1110.594 | N6: 3135.8883 | O6: 1386.808 | P6: 1019.0953 | Q6: 1032.2676 | R6: 559.86278 | S6: 1089.1056 | T6: 1189.6371 | U6: 516.85175 | V6: 1453.6172 | W6: 559.73651 | X6: 331.05008 | Z6: 478.56601 | AA6: 838.01713 | AC6: 1463.2068 | AD6: 1705.1853 | AE6: 1355.478 | AF6: 1839.0334 | AG6: 749.66909 | AI6: 1012.0971 | AK6: 600.27891 | AM6: 1363.044 | AN6: 953.26353 | AO6: 678.46566 | AQ6: 648.09184 | AR6: 506.72375 | AS6: 1181.5642 | AT6: 2411.8733 | AU6: 846.2881 | AV6: 1409.3869 | AW6: 599.45155 | AX6: 832.62967 | AZ6: =IFERROR(AVERAGEIFS(D6:AY6,$D$3:$AY$3,"Y",D6:AY6,"<>"),"") -> 1096.8503 | BA6: =IFERROR(D6-AZ6,"") -> -435.81864 | BB6: =IFERROR(COUNTIFS(D6:AY6,">"&D6,$D$3:$AY$3,"Y",D6:AY6,"<>")+1,"") -> 29 | BC6: =COUNTIFS($D$3:$AY$3,"Y",D6:AY6,"<>") -> 39
A7: Lids | B7: Apparel | C7: 38 | D7: 1033.0213 | E7: 627.00382 | G7: 919.71661 | I7: 2092.0609 | J7: 88.888889 | L7: 790.86812 | M7: 967.62857 | N7: 431.01488 | O7: 504.46063 | P7: 1321.5864 | Q7: 939.07559 | R7: 984.14673 | S7: 1206.2505 | T7: 982.71019 | U7: 1174.27 | V7: 868.84287 | W7: 722.53389 | Z7: 384.48636 | AA7: 359.62237 | AB7: 589.30993 | AC7: 632.8092 | AD7: 1040.1593 | AF7: 1019.4794 | AG7: 1825.3767 | AI7: 875.02266 | AJ7: 929.79284 | AK7: 923.57179 | AL7: 1210.2232 | AN7: 305.56918 | AO7: 420.96459 | AP7: 413.41614 | AQ7: 527.84721 | AS7: 869.8614 | AT7: 701.52062 | AU7: 1019.0433 | AV7: 901.87235 | AW7: 668.09015 | AY7: 772.25348 | AZ7: =IFERROR(AVERAGEIFS(D7:AY7,$D$3:$AY$3,"Y",D7:AY7,"<>"),"") -> 843.27295 | BA7: =IFERROR(D7-AZ7,"") -> 189.74838 | BB7: =IFERROR(COUNTIFS(D7:AY7,">"&D7,$D$3:$AY$3,"Y",D7:AY7,"<>")+1,"") -> 8 | BC7: =COUNTIFS($D$3:$AY$3,"Y",D7:AY7,"<>") -> 38
A8: Pandora | B8: Jewelry | C8: 38 | D8: 1262.8492 | E8: 2548.2648 | G8: 2195.9755 | I8: 2025.3227 | J8: 126.85285 | K8: 1038.8553 | L8: 2298.087 | M8: 1978.9305 | N8: 2585.3054 | O8: 1879.0738 | P8: 4177.38 | Q8: 1161.5877 | S8: 1723.4765 | T8: 1448.094 | U8: 3563.078 | V8: 1387.9992 | W8: 1980.5913 | Y8: 1034.3451 | Z8: 1231.5738 | AA8: 899.45375 | AC8: 3259.2867 | AD8: 1826.3573 | AG8: 1469.5726 | AI8: 1699.7613 | AJ8: 1974.8587 | AK8: 1633.3359 | AL8: 976.527 | AN8: 2141.892 | AO8: 1541.1733 | AP8: 342.50317 | AQ8: 1840.7971 | AS8: 2020.0819 | AT8: 2397.597 | AU8: 1973.7359 | AV8: 1957.391 | AW8: 1189.2049 | AX8: 3635.6062 | AY8: 2087.3893 | AZ8: =IFERROR(AVERAGEIFS(D8:AY8,$D$3:$AY$3,"Y",D8:AY8,"<>"),"") -> 1855.636 | BA8: =IFERROR(D8-AZ8,"") -> -592.78676 | BB8: =IFERROR(COUNTIFS(D8:AY8,">"&D8,$D$3:$AY$3,"Y",D8:AY8,"<>")+1,"") -> 29 | BC8: =COUNTIFS($D$3:$AY$3,"Y",D8:AY8,"<>") -> 38
A9: Journeys | B9: Shoes | C9: 37 | D9: 1075.2672 | E9: 437.25231 | G9: 1227.4669 | I9: 1009.5313 | J9: 43.450479 | L9: 415.12736 | M9: 607.37485 | N9: 946.51523 | O9: 702.48235 | P9: 781.745 | Q9: 334.6449 | R9: 426.36653 | S9: 498.46943 | T9: 484.02438 | U9: 1024.7919 | V9: 858.16612 | W9: 381.06768 | Z9: 563.542 | AA9: 345.24317 | AC9: 1187.3069 | AD9: 581.69592 | AF9: 635.13865 | AG9: 813.07253 | AI9: 780.3493 | AJ9: 471.98739 | AK9: 590.59284 | AL9: 503.41703 | AN9: 474.85801 | AO9: 533.10427 | AP9: 409.97797 | AQ9: 488.99629 | AS9: 506.76406 | AT9: 616.56778 | AV9: 774.28173 | AW9: 434.81636 | AX9: 857.15344 | AY9: 391.66478 | AZ9: =IFERROR(AVERAGEIFS(D9:AY9,$D$3:$AY$3,"Y",D9:AY9,"<>"),"") -> 627.41282 | BA9: =IFERROR(D9-AZ9,"") -> 447.85438 | BB9: =IFERROR(COUNTIFS(D9:AY9,">"&D9,$D$3:$AY$3,"Y",D9:AY9,"<>")+1,"") -> 3 | BC9: =COUNTIFS($D$3:$AY$3,"Y",D9:AY9,"<>") -> 37
A10: Auntie Annes | B10: Food & Beverage | C10: 36 | D10: 1187.4641 | E10: 1632.5357 | G10: 2415.367 | I10: 3844.1354 | J10: 163.91982 | L10: 9386.82 | M10: 6192.1736 | N10: 1236.4141 | O10: 3478.0593 | P10: 2780.8881 | Q10: 3293.09 | R10: 2377.391 | S10: 1035.099 | T10: 4694.0811 | U10: 1278.5881 | V10: 4790.6943 | W10: 4954.3532 | Z10: 1026.1036 | AA10: 756.87862 | AB10: 1904.595 | AC10: 1046.7078 | AD10: 3441.5778 | AF10: 960.74409 | AG10: 4009.725 | AI10: 4850.4592 | AJ10: 2564.825 | AL10: 12087.12 | AO10: 4183.6278 | AP10: 356.67881 | AQ10: 3430.4196 | AS10: 1087.5896 | AT10: 3550.1908 | AU10: 1176.16 | AV10: 3041.3363 | AW10: 1481.9543 | AX10: 623.83131 | AZ10: =IFERROR(AVERAGEIFS(D10:AY10,$D$3:$AY$3,"Y",D10:AY10,"<>"),"") -> 2953.3777 | BA10: =IFERROR(D10-AZ10,"") -> -1765.9136 | BB10: =IFERROR(COUNTIFS(D10:AY10,">"&D10,$D$3:$AY$3,"Y",D10:AY10,"<>")+1,"") -> 26 | BC10: =COUNTIFS($D$3:$AY$3,"Y",D10:AY10,"<>") -> 36
A11: Zumiez | B11: Apparel | C11: 36 | D11: 592.33269 | E11: 270.75068 | G11: 853.85563 | I11: 508.76124 | J11: 19.711004 | L11: 396.91982 | M11: 243.74052 | N11: 259.17603 | O11: 298.58343 | P11: 685.27112 | Q11: 433.63317 | R11: 395.70288 | S11: 350.99786 | T11: 338.88737 | U11: 697.91867 | V11: 318.70534 | W11: 322.85595 | Z11: 271.27877 | AA11: 161.89272 | AC11: 481.31717 | AF11: 360.01212 | AG11: 557.61536 | AI11: 341.32082 | AJ11: 199.14637 | AK11: 277.52635 | AL11: 374.64731 | AN11: 190.97711 | AO11: 243.34747 | AP11: 346.67935 | AQ11: 257.85828 | AS11: 237.51448 | AT11: 445.42655 | AU11: 359.27118 | AV11: 443.97491 | AW11: 170.62646 | AY11: 208.66409 | AZ11: =IFERROR(AVERAGEIFS(D11:AY11,$D$3:$AY$3,"Y",D11:AY11,"<>"),"") -> 358.80278 | BA11: =IFERROR(D11-AZ11,"") -> 233.5299 | BB11: =IFERROR(COUNTIFS(D11:AY11,">"&D11,$D$3:$AY$3,"Y",D11:AY11,"<>")+1,"") -> 4 | BC11: =COUNTIFS($D$3:$AY$3,"Y",D11:AY11,"<>") -> 36
A12: Windsor | B12: Apparel | C12: 35 | D12: 292.87555 | E12: 359.64092 | G12: 553.67549 | I12: 672.87356 | J12: 20.890635 | L12: 320.54887 | M12: 187.07101 | N12: 385.22329 | O12: 352.27827 | P12: 569.56615 | Q12: 345.11337 | R12: 424.99669 | S12: 260.3233 | T12: 339.9768 | U12: 281.04841 | V12: 424.01983 | W12: 356.22797 | Z12: 136.51761 | AA12: 312.03729 | AC12: 397.7917 | AD12: 353.03592 | AF12: 207.05763 | AG12: 357.00794 | AI12: 328.66733 | AJ12: 401.91047 | AK12: 231.54503 | AL12: 343.01397 | AO12: 411.43148 | AQ12: 199.34508 | AS12: 260.85193 | AT12: 404.71068 | AU12: 348.98357 | AV12: 369.67425 | AW12: 223.88564 | AY12: 322.82909 | AZ12: =IFERROR(AVERAGEIFS(D12:AY12,$D$3:$AY$3,"Y",D12:AY12,"<>"),"") -> 335.90419 | BA12: =IFERROR(D12-AZ12,"") -> -43.028641 | BB12: =IFERROR(COUNTIFS(D12:AY12,">"&D12,$D$3:$AY$3,"Y",D12:AY12,"<>")+1,"") -> 25 | BC12: =COUNTIFS($D$3:$AY$3,"Y",D12:AY12,"<>") -> 35
A13: American Eagle Outfitters | B13: Apparel | C13: 34 | D13: 420.9153 | G13: 502.2122 | I13: 710.9816 | L13: 617.60018 | M13: 530.19264 | N13: 507.91398 | O13: 546.91799 | P13: 794.2921 | Q13: 409.53707 | R13: 845.03282 | T13: 661.75673 | U13: 395.6165 | V13: 663.94169 | W13: 677.58516 | X13: 276.73278 | Z13: 548.23015 | AA13: 512.86554 | AC13: 308.22775 | AF13: 431.7292 | AG13: 583.80341 | AI13: 317.09377 | AJ13: 394.32794 | AL13: 354.59679 | AN13: 292.64167 | AO13: 432.60841 | AP13: 250.97015 | AQ13: 571.08438 | AS13: 382.31102 | AT13: 1024.8108 | AU13: 455.69126 | AV13: 866.47957 | AW13: 333.47473 | AX13: 581.76894 | AY13: 669.71435 | AZ13: =IFERROR(AVERAGEIFS(D13:AY13,$D$3:$AY$3,"Y",D13:AY13,"<>"),"") -> 525.69584 | BA13: =IFERROR(D13-AZ13,"") -> -104.78054 | BB13: =IFERROR(COUNTIFS(D13:AY13,">"&D13,$D$3:$AY$3,"Y",D13:AY13,"<>")+1,"") -> 23 | BC13: =COUNTIFS($D$3:$AY$3,"Y",D13:AY13,"<>") -> 34
A14: Hot Topic | B14: Apparel | C14: 34 | D14: 860.06689 | E14: 382.21667 | G14: 866.38536 | I14: 1211.6507 | J14: 34.654788 | L14: 605.04684 | M14: 579.61183 | N14: 503.74297 | O14: 545.00086 | Q14: 839.20404 | R14: 776.44529 | S14: 933.54642 | T14: 952.95583 | U14: 480.94168 | V14: 867.90188 | W14: 742.2418 | Z14: 562.38579 | AA14: 449.05682 | AC14: 731.98571 | AD14: 560.20791 | AF14: 298.91412 | AG14: 1038.8554 | AJ14: 548.04448 | AK14: 284.89823 | AL14: 725.2663 | AN14: 143.85275 | AO14: 742.26082 | AQ14: 444.82488 | AS14: 638.94805 | AU14: 699.38253 | AV14: 816.48037 | AW14: 481.69544 | AX14: 770.77316 | AY14: 456.13098 | AZ14: =IFERROR(AVERAGEIFS(D14:AY14,$D$3:$AY$3,"Y",D14:AY14,"<>"),"") -> 634.57581 | BA14: =IFERROR(D14-AZ14,"") -> 225.49108 | BB14: =IFERROR(COUNTIFS(D14:AY14,">"&D14,$D$3:$AY$3,"Y",D14:AY14,"<>")+1,"") -> 7 | BC14: =COUNTIFS($D$3:$AY$3,"Y",D14:AY14,"<>") -> 34
A15: Kay Jewelers | B15: Jewelry | C15: 34 | D15: 1560.784 | E15: 1381.5589 | G15: 2076.1011 | I15: 1960.585 | J15: 111.24424 | L15: 1369.7266 | M15: 1713.0586 | N15: 2171.5731 | O15: 1129.9844 | P15: 2706.2061 | Q15: 2061.3783 | R15: 1256.9782 | S15: 710.16096 | T15: 2282.0901 | U15: 1172.8857 | V15: 1432.5707 | W15: 1129.1832 | AA15: 1018.3767 | AB15: 392.88428 | AC15: 3058.9295 | AD15: 1270.4266 | AF15: 1818.8816 | AG15: 1537.4103 | AI15: 2214.681 | AK15: 807.288 | AN15: 477.66053 | AO15: 1748.1851 | AQ15: 806.51819 | AT15: 1142.8462 | AU15: 2027.3796 | AV15: 833.67587 | AW15: 570.37691 | AX15: 2029.7707 | AY15: 1228.4854 | AZ15: =IFERROR(AVERAGEIFS(D15:AY15,$D$3:$AY$3,"Y",D15:AY15,"<>"),"") -> 1447.3484 | BA15: =IFERROR(D15-AZ15,"") -> 113.43558 | BB15: =IFERROR(COUNTIFS(D15:AY15,">"&D15,$D$3:$AY$3,"Y",D15:AY15,"<>")+1,"") -> 14 | BC15: =COUNTIFS($D$3:$AY$3,"Y",D15:AY15,"<>") -> 34
A16: Lenscrafters | B16: Service | C16: 34 | D16: 447.17792 | E16: 751.65586 | G16: 660.61259 | H16: 518.87861 | I16: 785.81863 | J16: 43.028127 | L16: 1392.0772 | N16: 804.50227 | O16: 592.25883 | P16: 713.36612 | Q16: 950.94217 | R16: 822.69436 | S16: 686.54292 | U16: 1006.825 | V16: 563.51063 | W16: 1371.183 | Y16: 644.90656 | Z16: 840.0758 | AA16: 459.32036 | AC16: 450.64303 | AG16: 793.90813 | AJ16: 900.00192 | AK16: 694.78964 | AL16: 484.52044 | AM16: 558.0683 | AN16: 388.75481 | AP16: 248.531 | AQ16: 458.44975 | AR16: 717.08314 | AS16: 570.3311 | AT16: 681.79393 | AU16: 359.65911 | AV16: 635.33517 | AX16: 562.34846 | AZ16: =IFERROR(AVERAGEIFS(D16:AY16,$D$3:$AY$3,"Y",D16:AY16,"<>"),"") -> 663.5175 | BA16: =IFERROR(D16-AZ16,"") -> -216.33958 | BB16: =IFERROR(COUNTIFS(D16:AY16,">"&D16,$D$3:$AY$3,"Y",D16:AY16,"<>")+1,"") -> 30 | BC16: =COUNTIFS($D$3:$AY$3,"Y",D16:AY16,"<>") -> 34
A17: Spencer Gifts | B17: Hobby & Novelty | C17: 34 | D17: 708.67056 | E17: 545.79166 | G17: 794.1556 | I17: 810.60091 | J17: 46.532091 | L17: 490.08293 | M17: 500.44111 | N17: 605.5509 | O17: 514.22524 | P17: 998.13493 | Q17: 605.82503 | R17: 972.83599 | S17: 858.23836 | T17: 661.04573 | U17: 649.22455 | V17: 747.94189 | W17: 538.40525 | Z17: 416.71524 | AA17: 249.80546 | AC17: 472.59067 | AD17: 376.88951 | AF17: 720.18396 | AG17: 901.18255 | AI17: 575.60967 | AJ17: 409.49262 | AK17: 233.94171 | AL17: 812.16 | AO17: 522.34006 | AP17: 386.66484 | AQ17: 396.84544 | AS17: 546.31809 | AT17: 735.31063 | AU17: 930.4214 | AV17: 750.42767 | AZ17: =IFERROR(AVERAGEIFS(D17:AY17,$D$3:$AY$3,"Y",D17:AY17,"<>"),"") -> 602.4883 | BA17: =IFERROR(D17-AZ17,"") -> 106.18225 | BB17: =IFERROR(COUNTIFS(D17:AY17,">"&D17,$D$3:$AY$3,"Y",D17:AY17,"<>")+1,"") -> 13 | BC17: =COUNTIFS($D$3:$AY$3,"Y",D17:AY17,"<>") -> 34
A18: Champs Sports | B18: Shoes | C18: 33 | D18: 924.2662 | E18: 326.18938 | G18: 873.62238 | I18: 675.75398 | J18: 32.31441 | L18: 708.58672 | N18: 309.56649 | O18: 193.21862 | P18: 910.41118 | Q18: 423.04866 | R18: 479.90599 | S18: 388.90546 | T18: 269.55066 | U18: 484.24555 | V18: 264.62372 | W18: 307.77606 | Z18: 280.54876 | AB18: 424.50797 | AC18: 516.58206 | AD18: 648.40682 | AG18: 521.56991 | AJ18: 381.57426 | AK18: 300.24 | AL18: 457.53395 | AN18: 285.26464 | AO18: 285.84526 | AS18: 362.04079 | AT18: 469.29368 | AU18: 419.08848 | AV18: 571.06542 | AW18: 300.28831 | AX18: 811.45307 | AY18: 272.5329 | AZ18: =IFERROR(AVERAGEIFS(D18:AY18,$D$3:$AY$3,"Y",D18:AY18,"<>"),"") -> 450.90369 | BA18: =IFERROR(D18-AZ18,"") -> 473.36251 | BB18: =IFERROR(COUNTIFS(D18:AY18,">"&D18,$D$3:$AY$3,"Y",D18:AY18,"<>")+1,"") -> 1 | BC18: =COUNTIFS($D$3:$AY$3,"Y",D18:AY18,"<>") -> 33
A19: Hollister | B19: Service | C19: 33 | D19: 616.988 | E19: 232.88719 | G19: 546.60079 | I19: 409.16483 | L19: 523.85746 | M19: 463.84464 | N19: 399.08564 | O19: 763.57917 | P19: 769.16516 | R19: 545.59362 | S19: 404.83058 | T19: 552.68464 | U19: 436.42346 | V19: 492.2723 | W19: 554.64917 | Z19: 538.29535 | AA19: 472.12992 | AC19: 468.87036 | AD19: 372.68421 | AG19: 598.65034 | AI19: 371.98339 | AJ19: 611.69888 | AK19: 229.96462 | AL19: 457.84564 | AN19: 527.1928 | AO19: 564.67378 | AP19: 334.85091 | AQ19: 489.04711 | AT19: 1252.9359 | AU19: 620.64863 | AV19: 756.17707 | AX19: 517.21133 | AY19: 495.852 | AZ19: =IFERROR(AVERAGEIFS(D19:AY19,$D$3:$AY$3,"Y",D19:AY19,"<>"),"") -> 527.04057 | BA19: =IFERROR(D19-AZ19,"") -> 89.947429 | BB19: =IFERROR(COUNTIFS(D19:AY19,">"&D19,$D$3:$AY$3,"Y",D19:AY19,"<>")+1,"") -> 6 | BC19: =COUNTIFS($D$3:$AY$3,"Y",D19:AY19,"<>") -> 33
A20: Sephora | B20: Health & Beauty | C20: 32 | D20: 1631.4891 | E20: 963.45812 | F20: 703.79791 | G20: 2177.5794 | H20: 214.10924 | I20: 1105.2425 | J20: 89.867078 | K20: 1463.4489 | L20: 1241.7277 | O20: 2129.4774 | P20: 2120.2381 | T20: 1202.3742 | U20: 1392.3504 | V20: 1480.6142 | W20: 843.20349 | X20: 2034.0464 | Y20: 2674.5417 | AA20: 1256.1875 | AG20: 1565.8696 | AJ20: 1419.862 | AL20: 1627.6035 | AM20: 2377.5168 | AN20: 1899.9876 | AQ20: 1431.3277 | AR20: 1345.1787 | AS20: 1468.9651 | AT20: 3103.2737 | AU20: 1565.7621 | AV20: 2265.6208 | AW20: 1268.7698 | AX20: 1503.8408 | AY20: 1287.2552 | AZ20: =IFERROR(AVERAGEIFS(D20:AY20,$D$3:$AY$3,"Y",D20:AY20,"<>"),"") -> 1526.7058 | BA20: =IFERROR(D20-AZ20,"") -> 104.7833 | BB20: =IFERROR(COUNTIFS(D20:AY20,">"&D20,$D$3:$AY$3,"Y",D20:AY20,"<>")+1,"") -> 10 | BC20: =COUNTIFS($D$3:$AY$3,"Y",D20:AY20,"<>") -> 32
A21: Zales Jewelers | B21: Jewelry | C21: 31 | D21: 813.40745 | E21: 621.69669 | G21: 1720.9388 | I21: 1722.0037 | J21: 34.022682 | L21: 1281.3585 | M21: 1355.9554 | N21: 1323.8973 | O21: 948.04487 | P21: 1057.7435 | Q21: 803.01154 | S21: 691.06489 | T21: 863.35567 | U21: 1070.9907 | V21: 2049.4378 | W21: 1027.9221 | Z21: 1028.5908 | AA21: 1113.3744 | AC21: 844.72875 | AD21: 2242.9176 | AF21: 1086.2155 | AG21: 1597.9002 | AI21: 1340.5414 | AJ21: 1347.6915 | AK21: 727.90136 | AL21: 710.81824 | AO21: 766.11323 | AQ21: 390.66528 | AS21: 903.48935 | AX21: 1475.3069 | AY21: 821.39591 | AZ21: =IFERROR(AVERAGEIFS(D21:AY21,$D$3:$AY$3,"Y",D21:AY21,"<>"),"") -> 1089.7581 | BA21: =IFERROR(D21-AZ21,"") -> -276.35068 | BB21: =IFERROR(COUNTIFS(D21:AY21,">"&D21,$D$3:$AY$3,"Y",D21:AY21,"<>")+1,"") -> 23 | BC21: =COUNTIFS($D$3:$AY$3,"Y",D21:AY21,"<>") -> 31
A22: Buckle | B22: Apparel | C22: 30 | D22: 509.11289 | E22: 495.82209 | G22: 719.61268 | I22: 535.27595 | J22: 25.333056 | K22: 350.92913 | M22: 344.20816 | N22: 385.78702 | O22: 529.03234 | P22: 475.77812 | Q22: 381.64079 | R22: 318.02575 | S22: 472.11599 | T22: 496.95242 | V22: 536.04538 | W22: 474.84859 | X22: 274.51524 | Z22: 333.2348 | AA22: 251.93801 | AD22: 426.30206 | AE22: 336.04306 | AF22: 628.87648 | AG22: 657.94051 | AI22: 606.78533 | AK22: 358.52409 | AO22: 338.56769 | AP22: 449.47021 | AU22: 335.09053 | AV22: 508.11585 | AW22: 399.30396 | AZ22: =IFERROR(AVERAGEIFS(D22:AY22,$D$3:$AY$3,"Y",D22:AY22,"<>"),"") -> 431.84094 | BA22: =IFERROR(D22-AZ22,"") -> 77.271946 | BB22: =IFERROR(COUNTIFS(D22:AY22,">"&D22,$D$3:$AY$3,"Y",D22:AY22,"<>")+1,"") -> 8 | BC22: =COUNTIFS($D$3:$AY$3,"Y",D22:AY22,"<>") -> 30
A23: Charley's Philly Steaks | B23: Restaurant | C23: 29 | D23: 1587.9748 | E23: 2530.4626 | G23: 1414.4028 | I23: 2236.6667 | L23: 1512.5737 | M23: 522.22829 | N23: 1934.56 | O23: 1493.6425 | R23: 1326.5068 | S23: 1845.5946 | T23: 1139.9823 | U23: 1764.6332 | V23: 2386.6737 | W23: 1313.0708 | Z23: 398.32639 | AB23: 3683.9153 | AC23: 1420.3326 | AD23: 1573.58 | AF23: 601.40152 | AG23: 960.80406 | AI23: 2377.8035 | AJ23: 1682.5403 | AL23: 2206.5153 | AO23: 2050.6469 | AQ23: 1640.432 | AS23: 1856.6972 | AT23: 3882.7868 | AU23: 1395.0954 | AV23: 3863.5455 | AZ23: =IFERROR(AVERAGEIFS(D23:AY23,$D$3:$AY$3,"Y",D23:AY23,"<>"),"") -> 1813.9102 | BA23: =IFERROR(D23-AZ23,"") -> -225.93541 | BB23: =IFERROR(COUNTIFS(D23:AY23,">"&D23,$D$3:$AY$3,"Y",D23:AY23,"<>")+1,"") -> 16 | BC23: =COUNTIFS($D$3:$AY$3,"Y",D23:AY23,"<>") -> 29
A24: Aeropostale | B24: Apparel | C24: 28 | D24: 416.31121 | G24: 535.76107 | I24: 670.68095 | J24: 21.912442 | L24: 535.35591 | M24: 429.28989 | O24: 313.93725 | P24: 613.66601 | Q24: 386.26183 | R24: 383.02842 | S24: 339.00879 | T24: 428.6825 | U24: 320.78636 | V24: 422.31833 | W24: 413.53292 | AC24: 605.6157 | AD24: 393.40021 | AG24: 651.10446 | AI24: 474.8168 | AJ24: 429.12347 | AK24: 325.03309 | AL24: 458.53981 | AO24: 455.67118 | AQ24: 385.56002 | AS24: 211.77869 | AU24: 437.75219 | AX24: 579.6975 | AY24: 369.75903 | AZ24: =IFERROR(AVERAGEIFS(D24:AY24,$D$3:$AY$3,"Y",D24:AY24,"<>"),"") -> 428.87093 | BA24: =IFERROR(D24-AZ24,"") -> -12.55972 | BB24: =IFERROR(COUNTIFS(D24:AY24,">"&D24,$D$3:$AY$3,"Y",D24:AY24,"<>")+1,"") -> 16 | BC24: =COUNTIFS($D$3:$AY$3,"Y",D24:AY24,"<>") -> 28
A25: Lovisa | B25: Jewelry | C25: 28 | D25: 517.00679 | E25: 317.84263 | J25: 21.284185 | L25: 830.40074 | M25: 598.30355 | N25: 249.83082 | O25: 781.51414 | P25: 648.22177 | Q25: 447.50862 | R25: 463.83976 | S25: 371.5112 | T25: 914.33705 | U25: 934.94586 | V25: 788.2124 | AA25: 341.08081 | AC25: 419.35182 | AG25: 842.28191 | AJ25: 467.76156 | AL25: 519.6 | AN25: 465.7367 | AO25: 606.39334 | AQ25: 507.52088 | AS25: 523.69713 | AT25: 437.98482 | AU25: 358.06068 | AV25: 477.68451 | AW25: 781.69972 | AY25: 731.10976 | AZ25: =IFERROR(AVERAGEIFS(D25:AY25,$D$3:$AY$3,"Y",D25:AY25,"<>"),"") -> 548.74011 | BA25: =IFERROR(D25-AZ25,"") -> -31.73332 | BB25: =IFERROR(COUNTIFS(D25:AY25,">"&D25,$D$3:$AY$3,"Y",D25:AY25,"<>")+1,"") -> 14 | BC25: =COUNTIFS($D$3:$AY$3,"Y",D25:AY25,"<>") -> 28
A26: Pacific Sunwear | B26: Apparel | C26: 28 | D26: 334.22611 | G26: 422.43116 | I26: 457.03876 | J26: 27.582477 | L26: 732.50672 | N26: 563.07117 | O26: 654.5421 | P26: 744.432 | Q26: 318.27403 | R26: 659.87615 | S26: 450.44175 | T26: 478.96004 | U26: 342.93511 | W26: 306.10309 | Z26: 279.49201 | AC26: 407.82375 | AF26: 416.37514 | AG26: 756.42365 | AJ26: 516.37968 | AL26: 577.64997 | AN26: 337.09775 | AO26: 420.6398 | AS26: 351.37592 | AT26: 910.93677 | AU26: 724.4821 | AV26: 766.37942 | AX26: 815.65482 | AY26: 390.19444 | AZ26: =IFERROR(AVERAGEIFS(D26:AY26,$D$3:$AY$3,"Y",D26:AY26,"<>"),"") -> 505.83307 | BA26: =IFERROR(D26-AZ26,"") -> -171.60696 | BB26: =IFERROR(COUNTIFS(D26:AY26,">"&D26,$D$3:$AY$3,"Y",D26:AY26,"<>")+1,"") -> 24 | BC26: =COUNTIFS($D$3:$AY$3,"Y",D26:AY26,"<>") -> 28
A27: Torrid | B27: Apparel | C27: 28 | D27: 275.82949 | E27: 218.51859 | G27: 382.80213 | I27: 550.47764 | J27: 12.52459 | L27: 241.59272 | M27: 169.35643 | O27: 159.60402 | Q27: 249.53805 | S27: 236.08379 | T27: 144.25413 | U27: 397.54649 | W27: 179.84775 | Z27: 292.4356 | AC27: 107.97958 | AE27: 126.10927 | AF27: 129.74988 | AG27: 294.16495 | AI27: 160.18555 | AK27: 154.22389 | AO27: 273.61005 | AP27: 181.96011 | AQ27: 233.55848 | AS27: 154.8718 | AU27: 328.41122 | AV27: 260.33885 | AW27: 121.57993 | AY27: 190.82075 | AZ27: =IFERROR(AVERAGEIFS(D27:AY27,$D$3:$AY$3,"Y",D27:AY27,"<>"),"") -> 222.4277 | BA27: =IFERROR(D27-AZ27,"") -> 53.401781 | BB27: =IFERROR(COUNTIFS(D27:AY27,">"&D27,$D$3:$AY$3,"Y",D27:AY27,"<>")+1,"") -> 7 | BC27: =COUNTIFS($D$3:$AY$3,"Y",D27:AY27,"<>") -> 28
A28: Vans | B28: Shoes | C28: 27 | D28: 453.30767 | E28: 487.95569 | G28: 767.4132 | I28: 794.39549 | J28: 30.533333 | L28: 524.26269 | P28: 593.74053 | Q28: 316.59572 | R28: 366.07024 | S28: 309.73386 | T28: 219.7788 | U28: 1075.9121 | V28: 246.02759 | W28: 267.98583 | AC28: 190.67158 | AD28: 252.86109 | AG28: 324.42841 | AK28: 202.78324 | AM28: 393.96218 | AO28: 178.30171 | AQ28: 310.75803 | AS28: 299.73864 | AT28: 456.9818 | AU28: 239.41446 | AV28: 307.56946 | AW28: 165.17605 | AX28: 646.00429 | AZ28: =IFERROR(AVERAGEIFS(D28:AY28,$D$3:$AY$3,"Y",D28:AY28,"<>"),"") -> 386.01347 | BA28: =IFERROR(D28-AZ28,"") -> 67.294199 | BB28: =IFERROR(COUNTIFS(D28:AY28,">"&D28,$D$3:$AY$3,"Y",D28:AY28,"<>")+1,"") -> 9 | BC28: =COUNTIFS($D$3:$AY$3,"Y",D28:AY28,"<>") -> 27
A29: Banter By Piercing Pagoda | B29: Jewelry | C29: 26 | D29: 3920.3187 | E29: 2712.451 | G29: 1873.6813 | I29: 10703.663 | J29: 167.85714 | M29: 4350.8152 | N29: 4114.4295 | O29: 1848.2697 | P29: 5931.2 | Q29: 2851.6871 | R29: 5768.0946 | S29: 4690.4546 | V29: 2023.104 | W29: 5231.7055 | AC29: 5686.0737 | AD29: 3291.5725 | AF29: 1686.5044 | AG29: 3977.5333 | AI29: 9945.5398 | AJ29: 4660.5029 | AL29: 8558.325 | AO29: 4242.5869 | AQ29: 5196.8123 | AT29: 2949.411 | AU29: 5416.2972 | AX29: 949.92575 | AZ29: =IFERROR(AVERAGEIFS(D29:AY29,$D$3:$AY$3,"Y",D29:AY29,"<>"),"") -> 4336.4929 | BA29: =IFERROR(D29-AZ29,"") -> -416.17417 | BB29: =IFERROR(COUNTIFS(D29:AY29,">"&D29,$D$3:$AY$3,"Y",D29:AY29,"<>")+1,"") -> 16 | BC29: =COUNTIFS($D$3:$AY$3,"Y",D29:AY29,"<>") -> 26
A30: Build-A-Bear Workshop | B30: Hobby & Novelty | C30: 26 | D30: 435.05581 | E30: 381.81596 | I30: 533.91247 | L30: 317.07878 | M30: 447.78556 | O30: 516.06703 | P30: 615.15155 | Q30: 406.94768 | R30: 519.48921 | S30: 669.40219 | T30: 588.83112 | U30: 404.27661 | V30: 582.15841 | W30: 325.40514 | AD30: 244.37637 | AG30: 619.00214 | AJ30: 329.42644 | AL30: 653.34579 | AO30: 512.21896 | AQ30: 284.38676 | AS30: 283.94352 | AU30: 629.87123 | AV30: 671.69729 | AW30: 2165.3434 | AX30: 523.0616 | AY30: 387.36347 | AZ30: =IFERROR(AVERAGEIFS(D30:AY30,$D$3:$AY$3,"Y",D30:AY30,"<>"),"") -> 540.28517 | BA30: =IFERROR(D30-AZ30,"") -> -105.22936 | BB30: =IFERROR(COUNTIFS(D30:AY30,">"&D30,$D$3:$AY$3,"Y",D30:AY30,"<>")+1,"") -> 16 | BC30: =COUNTIFS($D$3:$AY$3,"Y",D30:AY30,"<>") -> 26
A31: GameStop | B31: Hobby & Novelty | C31: 26 | D31: 522.68386 | E31: 870.33356 | G31: 1400.5427 | I31: 623.9 | M31: 701.69894 | N31: 794.37981 | O31: 671.96528 | P31: 1280.8054 | R31: 1033.0661 | S31: 981.6227 | V31: 766.38463 | W31: 612.55686 | AB31: 890.02955 | AC31: 816.35486 | AD31: 619.90218 | AE31: 451.59731 | AI31: 758.31437 | AJ31: 889.44278 | AK31: 484.67756 | AL31: 443.73544 | AN31: 277.79826 | AP31: 598.97934 | AQ31: 925.98274 | AT31: 1197.7939 | AU31: 832.51578 | AY31: 407.71987 | AZ31: =IFERROR(AVERAGEIFS(D31:AY31,$D$3:$AY$3,"Y",D31:AY31,"<>"),"") -> 763.64553 | BA31: =IFERROR(D31-AZ31,"") -> -240.96168 | BB31: =IFERROR(COUNTIFS(D31:AY31,">"&D31,$D$3:$AY$3,"Y",D31:AY31,"<>")+1,"") -> 21 | BC31: =COUNTIFS($D$3:$AY$3,"Y",D31:AY31,"<>") -> 26
A32: Miniso | B32: Hobby & Novelty | C32: 26 | D32: 505.40291 | G32: 381.89699 | M32: 222.19019 | N32: 172.05011 | O32: 346.0836 | P32: 27.706582 | T32: 243.04219 | U32: 532.02444 | V32: 391.65741 | W32: 338.15291 | AC32: 265.30254 | AD32: 260.50383 | AF32: 160.01396 | AG32: 490.16617 | AI32: 186.30105 | AJ32: 115.57438 | AK32: 234.16914 | AL32: 314.28112 | AN32: 165.79519 | AO32: 290.61357 | AP32: 155.95755 | AS32: 197.51816 | AT32: 525.39549 | AV32: 437.04881 | AW32: 210.76566 | AY32: 293.41247 | AZ32: =IFERROR(AVERAGEIFS(D32:AY32,$D$3:$AY$3,"Y",D32:AY32,"<>"),"") -> 287.03948 | BA32: =IFERROR(D32-AZ32,"") -> 218.36343 | BB32: =IFERROR(COUNTIFS(D32:AY32,">"&D32,$D$3:$AY$3,"Y",D32:AY32,"<>")+1,"") -> 3 | BC32: =COUNTIFS($D$3:$AY$3,"Y",D32:AY32,"<>") -> 26
A33: Box Lunch | B33: Apparel | C33: 25 | D33: 546.04711 | E33: 500.36375 | G33: 606.27403 | I33: 982.59109 | M33: 261.19508 | N33: 224.13959 | O33: 406.04578 | Q33: 464.41065 | S33: 382.47719 | T33: 445.20533 | U33: 741.03116 | V33: 412.38373 | W33: 378.20382 | Z33: 251.1867 | AA33: 247.27146 | AC33: 288.61195 | AD33: 309.81634 | AF33: 232.8138 | AG33: 644.98771 | AJ33: 272.45588 | AO33: 333.86469 | AQ33: 372.05613 | AU33: 434.87971 | AW33: 252.02295 | AY33: 181.84711 | AZ33: =IFERROR(AVERAGEIFS(D33:AY33,$D$3:$AY$3,"Y",D33:AY33,"<>"),"") -> 406.88731 | BA33: =IFERROR(D33-AZ33,"") -> 139.1598 | BB33: =IFERROR(COUNTIFS(D33:AY33,">"&D33,$D$3:$AY$3,"Y",D33:AY33,"<>")+1,"") -> 5 | BC33: =COUNTIFS($D$3:$AY$3,"Y",D33:AY33,"<>") -> 25
A34: Cinnabon | B34: Food & Beverage | C34: 25 | D34: 1808.6732 | E34: 1652.6714 | G34: 1920.2276 | I34: 2162.8533 | J34: 57.335329 | M34: 1387.6348 | N34: 1660.1558 | P34: 6243.4975 | Q34: 584.29644 | R34: 773.31705 | S34: 629.12578 | T34: 365.54539 | U34: 1435.6158 | W34: 738.75386 | Z34: 353.3576 | AB34: 1292.7429 | AC34: 1190.4978 | AF34: 368.36852 | AJ34: 1203.3433 | AO34: 1757.5367 | AQ34: 1975.9616 | AS34: 395.68525 | AT34: 2455.5469 | AU34: 565.91932 | AX34: 1124.0982 | AZ34: =IFERROR(AVERAGEIFS(D34:AY34,$D$3:$AY$3,"Y",D34:AY34,"<>"),"") -> 1364.1105 | BA34: =IFERROR(D34-AZ34,"") -> 444.56276 | BB34: =IFERROR(COUNTIFS(D34:AY34,">"&D34,$D$3:$AY$3,"Y",D34:AY34,"<>")+1,"") -> 6 | BC34: =COUNTIFS($D$3:$AY$3,"Y",D34:AY34,"<>") -> 25
A35: Foot Locker | B35: Shoes | C35: 23 | D35: 975.43728 | E35: 614.585 | G35: 776.14646 | H35: 621.26078 | I35: 1088.145 | J35: 57.460036 | M35: 587.33894 | N35: 371.59983 | O35: 368.71013 | Q35: 873.93966 | R35: 950.94571 | S35: 851.37063 | V35: 402.41809 | Z35: 359.17354 | AB35: 674.16325 | AC35: 610.04396 | AF35: 409.85706 | AG35: 688.99471 | AI35: 531.55584 | AJ35: 924.29029 | AQ35: 791.2158 | AV35: 819.98344 | AY35: 919.78795 | AZ35: =IFERROR(AVERAGEIFS(D35:AY35,$D$3:$AY$3,"Y",D35:AY35,"<>"),"") -> 663.8445 | BA35: =IFERROR(D35-AZ35,"") -> 311.59278 | BB35: =IFERROR(COUNTIFS(D35:AY35,">"&D35,$D$3:$AY$3,"Y",D35:AY35,"<>")+1,"") -> 2 | BC35: =COUNTIFS($D$3:$AY$3,"Y",D35:AY35,"<>") -> 23
A36: Lush Fresh Handmade Cosmetics | B36: Health & Beauty | C36: 23 | D36: 1208.0859 | E36: 1471.9674 | G36: 980.13333 | I36: 1570.9688 | J36: 129.80392 | K36: 722.83919 | L36: 699.72257 | P36: 1728.64 | R36: 799.43256 | S36: 567.64581 | Z36: 1040.9467 | AA36: 1185.8899 | AC36: 614.64447 | AG36: 839.50351 | AL36: 444.18462 | AN36: 381.17947 | AQ36: 462.85737 | AS36: 962.30876 | AT36: 807.52137 | AU36: 561.81566 | AV36: 1261.2516 | AX36: 1416.1631 | AY36: 373.84113 | AZ36: =IFERROR(AVERAGEIFS(D36:AY36,$D$3:$AY$3,"Y",D36:AY36,"<>"),"") -> 879.62379 | BA36: =IFERROR(D36-AZ36,"") -> 328.46209 | BB36: =IFERROR(COUNTIFS(D36:AY36,">"&D36,$D$3:$AY$3,"Y",D36:AY36,"<>")+1,"") -> 6 | BC36: =COUNTIFS($D$3:$AY$3,"Y",D36:AY36,"<>") -> 23
A37: Express | B37: Apparel | C37: 21 | D37: 289.75419 | E37: 263.70502 | I37: 333.29059 | J37: 1.5414526 | M37: 149.49642 | N37: 210.66698 | Q37: 163.39588 | R37: 163.14376 | U37: 174.63671 | V37: 121.94586 | Z37: 103.17019 | AA37: 204.59586 | AC37: 175.0093 | AD37: 175.68386 | AJ37: 202.58558 | AK37: 198.92849 | AL37: 248.68331 | AO37: 166.22812 | AU37: 175.0381 | AW37: 109.5073 | AX37: 441.21837 | AZ37: =IFERROR(AVERAGEIFS(D37:AY37,$D$3:$AY$3,"Y",D37:AY37,"<>"),"") -> 193.91549 | BA37: =IFERROR(D37-AZ37,"") -> 95.838698 | BB37: =IFERROR(COUNTIFS(D37:AY37,">"&D37,$D$3:$AY$3,"Y",D37:AY37,"<>")+1,"") -> 3 | BC37: =COUNTIFS($D$3:$AY$3,"Y",D37:AY37,"<>") -> 21
A38: Sbarro The Italian Eatery | B38: Food & Beverage | C38: 21 | D38: 1662.3151 | E38: 453.80668 | G38: 1031.9207 | L38: 764.46429 | M38: 709.90476 | N38: 874.47377 | O38: 1317.5313 | R38: 1125.9758 | S38: 1185.3534 | T38: 913.86103 | U38: 1621.5515 | V38: 965.50793 | W38: 791.24066 | Z38: 529.49485 | AB38: 1135.7236 | AC38: 1208.8797 | AD38: 991.44116 | AO38: 701.58158 | AU38: 1631.4897 | AW38: 842.39968 | AX38: 492.46376 | AZ38: =IFERROR(AVERAGEIFS(D38:AY38,$D$3:$AY$3,"Y",D38:AY38,"<>"),"") -> 997.68481 | BA38: =IFERROR(D38-AZ38,"") -> 664.63028 | BB38: =IFERROR(COUNTIFS(D38:AY38,">"&D38,$D$3:$AY$3,"Y",D38:AY38,"<>")+1,"") -> 1 | BC38: =COUNTIFS($D$3:$AY$3,"Y",D38:AY38,"<>") -> 21
A39: Victorias Secret | B39: Apparel | C39: 21 | D39: 667.60615 | G39: 693.43659 | K39: 455.64266 | L39: 437.53073 | M39: 376.22635 | N39: 505.51665 | Q39: 333.34839 | R39: 353.66043 | V39: 554.72287 | W39: 433.95691 | AB39: 638.38056 | AE39: 421.8362 | AF39: 497.43278 | AI39: 459.13986 | AK39: 374.56896 | AL39: 569.97335 | AN39: 439.41047 | AP39: 423.89322 | AW39: 503.00466 | AX39: 668.71105 | AY39: 422.28356 | AZ39: =IFERROR(AVERAGEIFS(D39:AY39,$D$3:$AY$3,"Y",D39:AY39,"<>"),"") -> 487.1563 | BA39: =IFERROR(D39-AZ39,"") -> 180.44985 | BB39: =IFERROR(COUNTIFS(D39:AY39,">"&D39,$D$3:$AY$3,"Y",D39:AY39,"<>")+1,"") -> 3 | BC39: =COUNTIFS($D$3:$AY$3,"Y",D39:AY39,"<>") -> 21
A40: Lululemon | B40: Apparel | C40: 20 | D40: 948.87789 | E40: 3404.1463 | G40: 2058.0073 | K40: 1284.0774 | L40: 1695.3814 | P40: 1858.3114 | R40: 1915.1373 | S40: 1939.0161 | X40: 1986.4159 | Y40: 1761.2925 | AA40: 1352.8939 | AE40: 1278.0316 | AH40: 1805.3673 | AM40: 1625.2327 | AP40: 800.60265 | AS40: 2065.0505 | AT40: 2233.2054 | AU40: 1751.0588 | AV40: 1945.6052 | AX40: 2489.8206 | AZ40: =IFERROR(AVERAGEIFS(D40:AY40,$D$3:$AY$3,"Y",D40:AY40,"<>"),"") -> 1809.8766 | BA40: =IFERROR(D40-AZ40,"") -> -860.99873 | BB40: =IFERROR(COUNTIFS(D40:AY40,">"&D40,$D$3:$AY$3,"Y",D40:AY40,"<>")+1,"") -> 19 | BC40: =COUNTIFS($D$3:$AY$3,"Y",D40:AY40,"<>") -> 20
A41: GNC | B41: Health & Beauty | C41: 19 | D41: 444.25492 | M41: 781.38607 | N41: 318.95189 | R41: 222.37854 | S41: 380.21043 | T41: 270.5862 | U41: 299.2247 | V41: 373.62446 | AB41: 453.82131 | AD41: 438.36038 | AF41: 348.14971 | AI41: 325.7484 | AJ41: 230.00172 | AK41: 373.27067 | AO41: 296.66341 | AT41: 776.72625 | AU41: 279.5788 | AW41: 372.3362 | AX41: 388.53265 | AZ41: =IFERROR(AVERAGEIFS(D41:AY41,$D$3:$AY$3,"Y",D41:AY41,"<>"),"") -> 388.09509 | BA41: =IFERROR(D41-AZ41,"") -> 56.159829 | BB41: =IFERROR(COUNTIFS(D41:AY41,">"&D41,$D$3:$AY$3,"Y",D41:AY41,"<>")+1,"") -> 4 | BC41: =COUNTIFS($D$3:$AY$3,"Y",D41:AY41,"<>") -> 19
A42: J. Jill | B42: Apparel | C42: 18 | D42: 200.9866 | F42: 489.3638 | K42: 422.05081 | O42: 425.38644 | P42: 478.47594 | R42: 259.64419 | T42: 407.54073 | W42: 260.85949 | X42: 616.63849 | Y42: 381.04848 | AE42: 500.27538 | AN42: 179.84143 | AO42: 324.80059 | AR42: 263.07664 | AT42: 497.98358 | AU42: 266.06507 | AV42: 426.72157 | AX42: 291.64644 | AZ42: =IFERROR(AVERAGEIFS(D42:AY42,$D$3:$AY$3,"Y",D42:AY42,"<>"),"") -> 371.80032 | BA42: =IFERROR(D42-AZ42,"") -> -170.81372 | BB42: =IFERROR(COUNTIFS(D42:AY42,">"&D42,$D$3:$AY$3,"Y",D42:AY42,"<>")+1,"") -> 17 | BC42: =COUNTIFS($D$3:$AY$3,"Y",D42:AY42,"<>") -> 18
A43: Soma Intimates | B43: Apparel | C43: 18 | D43: 207.5796 | K43: 364.2762 | L43: 275.72875 | O43: 511.31827 | P43: 413.79162 | S43: 202.26657 | T43: 386.23415 | X43: 497.84425 | Y43: 441.79711 | Z43: 252.93886 | AA43: 287.36319 | AE43: 370.81762 | AN43: 283.7453 | AR43: 362.51349 | AT43: 451.72679 | AU43: 201.84813 | AV43: 481.21066 | AW43: 241.26385 | AZ43: =IFERROR(AVERAGEIFS(D43:AY43,$D$3:$AY$3,"Y",D43:AY43,"<>"),"") -> 346.34802 | BA43: =IFERROR(D43-AZ43,"") -> -138.76842 | BB43: =IFERROR(COUNTIFS(D43:AY43,">"&D43,$D$3:$AY$3,"Y",D43:AY43,"<>")+1,"") -> 16 | BC43: =COUNTIFS($D$3:$AY$3,"Y",D43:AY43,"<>") -> 18
A44: Aerie | B44: Apparel | C44: 17 | D44: 477.40858 | G44: 346.96336 | I44: 530.65231 | L44: 721.28483 | M44: 559.70767 | O44: 842.87236 | P44: 848.4124 | S44: 607.80285 | T44: 1102.0165 | V44: 735.14293 | AE44: 827.86562 | AG44: 859.89448 | AJ44: 323.90996 | AL44: 609.66 | AN44: 534.74981 | AO44: 475.27399 | AW44: 515.76786 | AZ44: =IFERROR(AVERAGEIFS(D44:AY44,$D$3:$AY$3,"Y",D44:AY44,"<>"),"") -> 642.3168 | BA44: =IFERROR(D44-AZ44,"") -> -164.90821 | BB44: =IFERROR(COUNTIFS(D44:AY44,">"&D44,$D$3:$AY$3,"Y",D44:AY44,"<>")+1,"") -> 14 | BC44: =COUNTIFS($D$3:$AY$3,"Y",D44:AY44,"<>") -> 17
A45: Aldo | B45: Shoes | C45: 15 | D45: 133.08686 | E45: 463.56912 | G45: 490.28011 | I45: 468.74686 | P45: 867.89068 | Q45: 321.41866 | U45: 451.36669 | AC45: 457.34494 | AG45: 350.29154 | AJ45: 377.60628 | AL45: 385.69333 | AQ45: 384.39772 | AS45: 380.32685 | AT45: 708.78612 | AX45: 394.72794 | AZ45: =IFERROR(AVERAGEIFS(D45:AY45,$D$3:$AY$3,"Y",D45:AY45,"<>"),"") -> 442.36891 | BA45: =IFERROR(D45-AZ45,"") -> -309.28205 | BB45: =IFERROR(COUNTIFS(D45:AY45,">"&D45,$D$3:$AY$3,"Y",D45:AY45,"<>")+1,"") -> 15 | BC45: =COUNTIFS($D$3:$AY$3,"Y",D45:AY45,"<>") -> 15
A46: Loft | B46: Apparel | C46: 15 | D46: 73.485263 | H46: 100.95635 | J46: 12.705931 | K46: 273.73733 | N46: 115.05074 | S46: 159.52622 | X46: 304.98213 | Y46: 285.99161 | AA46: 187.56073 | AE46: 332.01924 | AG46: 107.71825 | AR46: 279.06818 | AU46: 204.45893 | AV46: 392.32773 | AY46: 192.86681 | AZ46: =IFERROR(AVERAGEIFS(D46:AY46,$D$3:$AY$3,"Y",D46:AY46,"<>"),"") -> 201.49703 | BA46: =IFERROR(D46-AZ46,"") -> -128.01177 | BB46: =IFERROR(COUNTIFS(D46:AY46,">"&D46,$D$3:$AY$3,"Y",D46:AY46,"<>")+1,"") -> 14 | BC46: =COUNTIFS($D$3:$AY$3,"Y",D46:AY46,"<>") -> 15
A47: Sleep Number | B47: Major | C47: 15 | D47: 511.38991 | E47: 838.63461 | I47: 1033.0873 | L47: 1111.9359 | N47: 1074.7353 | P47: 780.92683 | Q47: 660.02169 | T47: 851.34112 | V47: 950.69578 | AE47: 804.71708 | AH47: 432.88265 | AQ47: 425.15215 | AR47: 650.45759 | AT47: 1470.9472 | AU47: 692.00209 | AZ47: =IFERROR(AVERAGEIFS(D47:AY47,$D$3:$AY$3,"Y",D47:AY47,"<>"),"") -> 819.26181 | BA47: =IFERROR(D47-AZ47,"") -> -307.8719 | BB47: =IFERROR(COUNTIFS(D47:AY47,">"&D47,$D$3:$AY$3,"Y",D47:AY47,"<>")+1,"") -> 13 | BC47: =COUNTIFS($D$3:$AY$3,"Y",D47:AY47,"<>") -> 15
A48: FYE Music & Movies | B48: Hobby & Novelty | C48: 14 | D48: 150.28929 | I48: 332.61541 | M48: 193.38314 | R48: 231.60216 | S48: 156.39988 | T48: 170.4039 | U48: 194.23129 | W48: 115.44449 | AC48: 122.87108 | AG48: 194.01225 | AI48: 141.07792 | AJ48: 83.691575 | AO48: 127.00838 | AU48: 250.14663 | AZ48: =IFERROR(AVERAGEIFS(D48:AY48,$D$3:$AY$3,"Y",D48:AY48,"<>"),"") -> 175.94124 | BA48: =IFERROR(D48-AZ48,"") -> -25.651956 | BB48: =IFERROR(COUNTIFS(D48:AY48,">"&D48,$D$3:$AY$3,"Y",D48:AY48,"<>")+1,"") -> 9 | BC48: =COUNTIFS($D$3:$AY$3,"Y",D48:AY48,"<>") -> 14
A49: T-Mobile | B49: Tech | C49: 14 | D49: 513.13136 | E49: 1803.7782 | G49: 242.09244 | I49: 3013.4876 | J49: 39.390476 | L49: 1214.3881 | P49: 1356.8557 | Q49: 994.56142 | R49: 388.33927 | U49: 1023.4897 | AL49: 3974.2605 | AP49: 248.64194 | AQ49: 1484.2805 | AS49: 1614.942 | AZ49: =IFERROR(AVERAGEIFS(D49:AY49,$D$3:$AY$3,"Y",D49:AY49,"<>"),"") -> 1279.4028 | BA49: =IFERROR(D49-AZ49,"") -> -766.27144 | BB49: =IFERROR(COUNTIFS(D49:AY49,">"&D49,$D$3:$AY$3,"Y",D49:AY49,"<>")+1,"") -> 10 | BC49: =COUNTIFS($D$3:$AY$3,"Y",D49:AY49,"<>") -> 14
A50: Eddie Bauer | B50: Apparel | C50: 13 | D50: 193.4022 | E50: 214.77464 | J50: 23.126873 | L50: 364.92829 | S50: 325.33949 | T50: 161.09295 | W50: 194.58496 | AA50: 163.64801 | AG50: 191.26628 | AR50: 136.3198 | AT50: 322.99796 | AU50: 188.27782 | AW50: 226.68557 | AZ50: =IFERROR(AVERAGEIFS(D50:AY50,$D$3:$AY$3,"Y",D50:AY50,"<>"),"") -> 208.18806 | BA50: =IFERROR(D50-AZ50,"") -> -14.785868 | BB50: =IFERROR(COUNTIFS(D50:AY50,">"&D50,$D$3:$AY$3,"Y",D50:AY50,"<>")+1,"") -> 7 | BC50: =COUNTIFS($D$3:$AY$3,"Y",D50:AY50,"<>") -> 13
A51: Popeyes Louisiana Kitchen | B51: Restaurant | C51: 13 | D51: 1299.6257 | E51: 1409.9229 | Q51: 1028.7526 | R51: 2127.1111 | T51: 1197.059 | AB51: 2363.7116 | AC51: 1579.895 | AI51: 719.56101 | AJ51: 1144.4549 | AO51: 1814.4497 | AQ51: 1649.9812 | AS51: 1289.4395 | AV51: 726.03374 | AZ51: =IFERROR(AVERAGEIFS(D51:AY51,$D$3:$AY$3,"Y",D51:AY51,"<>"),"") -> 1411.5383 | BA51: =IFERROR(D51-AZ51,"") -> -111.91263 | BB51: =IFERROR(COUNTIFS(D51:AY51,">"&D51,$D$3:$AY$3,"Y",D51:AY51,"<>")+1,"") -> 7 | BC51: =COUNTIFS($D$3:$AY$3,"Y",D51:AY51,"<>") -> 13
A52: Coach | B52: Apparel | C52: 11 | D52: 1018.9582 | G52: 543.14796 | J52: 54.649891 | S52: 560.2697 | T52: 852.56985 | AA52: 618.27413 | AG52: 1057.0125 | AS52: 583.78687 | AT52: 987.82635 | AU52: 749.9831 | AX52: 867.32222 | AZ52: =IFERROR(AVERAGEIFS(D52:AY52,$D$3:$AY$3,"Y",D52:AY52,"<>"),"") -> 717.61825 | BA52: =IFERROR(D52-AZ52,"") -> 301.33998 | BB52: =IFERROR(COUNTIFS(D52:AY52,">"&D52,$D$3:$AY$3,"Y",D52:AY52,"<>")+1,"") -> 2 | BC52: =COUNTIFS($D$3:$AY$3,"Y",D52:AY52,"<>") -> 11
A53: Chipotle Mexican Grill | B53: Restaurant | C53: 10 | D53: 1268.3081 | E53: 2169.1724 | I53: 2996.326 | L53: 1211.3062 | T53: 1256.8959 | AG53: 2394.0377 | AJ53: 1403.9057 | AQ53: 1832.0075 | AT53: 1141.8513 | AV53: 1025.9701 | AZ53: =IFERROR(AVERAGEIFS(D53:AY53,$D$3:$AY$3,"Y",D53:AY53,"<>"),"") -> 1669.9781 | BA53: =IFERROR(D53-AZ53,"") -> -401.66995 | BB53: =IFERROR(COUNTIFS(D53:AY53,">"&D53,$D$3:$AY$3,"Y",D53:AY53,"<>")+1,"") -> 6 | BC53: =COUNTIFS($D$3:$AY$3,"Y",D53:AY53,"<>") -> 10
A54: J.Crew | B54: Apparel | C54: 10 | D54: 199.24316 | J54: 26.857668 | L54: 411.99718 | T54: 252.79128 | AE54: 318.44329 | AL54: 267.3088 | AP54: 188.16503 | AS54: 439.2651 | AU54: 317.59445 | AX54: 413.93437 | AZ54: =IFERROR(AVERAGEIFS(D54:AY54,$D$3:$AY$3,"Y",D54:AY54,"<>"),"") -> 283.56003 | BA54: =IFERROR(D54-AZ54,"") -> -84.316873 | BB54: =IFERROR(COUNTIFS(D54:AY54,">"&D54,$D$3:$AY$3,"Y",D54:AY54,"<>")+1,"") -> 8 | BC54: =COUNTIFS($D$3:$AY$3,"Y",D54:AY54,"<>") -> 10
A55: The Cheesecake Factory | B55: Restaurant | C55: 10 | D55: 974.32496 | E55: 1448.2385 | K55: 1385.6261 | L55: 1105.4119 | O55: 941.26253 | T55: 1053.4656 | V55: 850.1583 | Z55: 958.05796 | AL55: 1285.1797 | AW55: 756.13516 | AZ55: =IFERROR(AVERAGEIFS(D55:AY55,$D$3:$AY$3,"Y",D55:AY55,"<>"),"") -> 1075.7861 | BA55: =IFERROR(D55-AZ55,"") -> -101.46112 | BB55: =IFERROR(COUNTIFS(D55:AY55,">"&D55,$D$3:$AY$3,"Y",D55:AY55,"<>")+1,"") -> 6 | BC55: =COUNTIFS($D$3:$AY$3,"Y",D55:AY55,"<>") -> 10
A56: Carters | B56: Apparel | C56: 9 | D56: 670.84788 | I56: 359.37796 | S56: 247.03101 | AC56: 219.32852 | AJ56: 253.88138 | AN56: 212.66565 | AO56: 276.68754 | AQ56: 242.7036 | AR56: 287.67516 | AZ56: =IFERROR(AVERAGEIFS(D56:AY56,$D$3:$AY$3,"Y",D56:AY56,"<>"),"") -> 307.79986 | BA56: =IFERROR(D56-AZ56,"") -> 363.04802 | BB56: =IFERROR(COUNTIFS(D56:AY56,">"&D56,$D$3:$AY$3,"Y",D56:AY56,"<>")+1,"") -> 1 | BC56: =COUNTIFS($D$3:$AY$3,"Y",D56:AY56,"<>") -> 9
A57: Hallmark | B57: Hobby & Novelty | C57: 9 | D57: 264.98871 | E57: 228.95594 | O57: 340.4642 | AC57: 258.9164 | AG57: 208.17453 | AK57: 152.009 | AV57: 231.17455 | AW57: 216.77184 | AX57: 324.74387 | AZ57: =IFERROR(AVERAGEIFS(D57:AY57,$D$3:$AY$3,"Y",D57:AY57,"<>"),"") -> 247.35545 | BA57: =IFERROR(D57-AZ57,"") -> 17.633257 | BB57: =IFERROR(COUNTIFS(D57:AY57,">"&D57,$D$3:$AY$3,"Y",D57:AY57,"<>")+1,"") -> 3 | BC57: =COUNTIFS($D$3:$AY$3,"Y",D57:AY57,"<>") -> 9
A58: Maurices | B58: Apparel | C58: 9 | D58: 105.84114 | V58: 139.53434 | W58: 102.81906 | AF58: 176.39712 | AG58: 117.93329 | AI58: 168.89371 | AP58: 178.91281 | AV58: 137.07963 | AW58: 198.23956 | AZ58: =IFERROR(AVERAGEIFS(D58:AY58,$D$3:$AY$3,"Y",D58:AY58,"<>"),"") -> 147.29452 | BA58: =IFERROR(D58-AZ58,"") -> -41.453383 | BB58: =IFERROR(COUNTIFS(D58:AY58,">"&D58,$D$3:$AY$3,"Y",D58:AY58,"<>")+1,"") -> 8 | BC58: =COUNTIFS($D$3:$AY$3,"Y",D58:AY58,"<>") -> 9
A59: Tillys | B59: Apparel | C59: 9 | D59: 264.86871 | E59: 242.13071 | G59: 373.65362 | I59: 321.49657 | O59: 200.25396 | Q59: 242.15112 | U59: 450.07231 | AL59: 190.42779 | AO59: 203.0727 | AZ59: =IFERROR(AVERAGEIFS(D59:AY59,$D$3:$AY$3,"Y",D59:AY59,"<>"),"") -> 276.45861 | BA59: =IFERROR(D59-AZ59,"") -> -11.589896 | BB59: =IFERROR(COUNTIFS(D59:AY59,">"&D59,$D$3:$AY$3,"Y",D59:AY59,"<>")+1,"") -> 4 | BC59: =COUNTIFS($D$3:$AY$3,"Y",D59:AY59,"<>") -> 9
A60: Visionworks | B60: Service | C60: 9 | D60: 571.44 | I60: 594.20101 | N60: 272.27093 | O60: 219.05975 | V60: 420.58715 | AD60: 285.41796 | AF60: 531.81643 | AG60: 211.25358 | AS60: 326.39932 | AZ60: =IFERROR(AVERAGEIFS(D60:AY60,$D$3:$AY$3,"Y",D60:AY60,"<>"),"") -> 381.3829 | BA60: =IFERROR(D60-AZ60,"") -> 190.0571 | BB60: =IFERROR(COUNTIFS(D60:AY60,">"&D60,$D$3:$AY$3,"Y",D60:AY60,"<>")+1,"") -> 2 | BC60: =COUNTIFS($D$3:$AY$3,"Y",D60:AY60,"<>") -> 9
A61: Panera Bread | B61: Restaurant | C61: 8 | D61: 659.12176 | I61: 519.87662 | K61: 740.84012 | S61: 742.36885 | X61: 513.05918 | AL61: 574.24977 | AQ61: 445.79737 | AR61: 741.0148 | AZ61: =IFERROR(AVERAGEIFS(D61:AY61,$D$3:$AY$3,"Y",D61:AY61,"<>"),"") -> 617.04106 | BA61: =IFERROR(D61-AZ61,"") -> 42.080699 | BB61: =IFERROR(COUNTIFS(D61:AY61,">"&D61,$D$3:$AY$3,"Y",D61:AY61,"<>")+1,"") -> 4 | BC61: =COUNTIFS($D$3:$AY$3,"Y",D61:AY61,"<>") -> 8
A62: Famous Footwear | B62: Shoes | C62: 7 | D62: 362.99492 | R62: 246.25749 | S62: 310.54132 | AF62: 208.1813 | AJ62: 287.90467 | AP62: 249.72598 | AU62: 397.94451 | AZ62: =IFERROR(AVERAGEIFS(D62:AY62,$D$3:$AY$3,"Y",D62:AY62,"<>"),"") -> 294.79289 | BA62: =IFERROR(D62-AZ62,"") -> 68.202035 | BB62: =IFERROR(COUNTIFS(D62:AY62,">"&D62,$D$3:$AY$3,"Y",D62:AY62,"<>")+1,"") -> 2 | BC62: =COUNTIFS($D$3:$AY$3,"Y",D62:AY62,"<>") -> 7
A63: Lolli And Pops | B63: Food & Beverage | C63: 7 | D63: 176.67854 | E63: 383.1032 | G63: 342.84189 | L63: 345.27571 | AG63: 389.53577 | AT63: 579.06765 | AV63: 441.49928 | AZ63: =IFERROR(AVERAGEIFS(D63:AY63,$D$3:$AY$3,"Y",D63:AY63,"<>"),"") -> 379.71458 | BA63: =IFERROR(D63-AZ63,"") -> -203.03604 | BB63: =IFERROR(COUNTIFS(D63:AY63,">"&D63,$D$3:$AY$3,"Y",D63:AY63,"<>")+1,"") -> 7 | BC63: =COUNTIFS($D$3:$AY$3,"Y",D63:AY63,"<>") -> 7
A64: M.A.C Cosmetics | B64: Health & Beauty | C64: 7 | D64: 302.85503 | E64: 680.04917 | G64: 936.16545 | I64: 532.0625 | U64: 1289.9035 | AS64: 401.60438 | AX64: 583.83939 | AZ64: =IFERROR(AVERAGEIFS(D64:AY64,$D$3:$AY$3,"Y",D64:AY64,"<>"),"") -> 675.21134 | BA64: =IFERROR(D64-AZ64,"") -> -372.35631 | BB64: =IFERROR(COUNTIFS(D64:AY64,">"&D64,$D$3:$AY$3,"Y",D64:AY64,"<>")+1,"") -> 7 | BC64: =COUNTIFS($D$3:$AY$3,"Y",D64:AY64,"<>") -> 7
A65: Panda Express | B65: Restaurant | C65: 7 | D65: 3231.1885 | G65: 1632.592 | J65: 106.64264 | U65: 1982.6496 | AG65: 1872.8629 | AT65: 1216.1455 | AV65: 1773.2575 | AZ65: =IFERROR(AVERAGEIFS(D65:AY65,$D$3:$AY$3,"Y",D65:AY65,"<>"),"") -> 1687.9055 | BA65: =IFERROR(D65-AZ65,"") -> 1543.283 | BB65: =IFERROR(COUNTIFS(D65:AY65,">"&D65,$D$3:$AY$3,"Y",D65:AY65,"<>")+1,"") -> 1 | BC65: =COUNTIFS($D$3:$AY$3,"Y",D65:AY65,"<>") -> 7
A66: Icing By Claires | B66: Jewelry | C66: 6 | D66: 211.37868 | G66: 227.94288 | I66: 530.44817 | J66: 22.076923 | U66: 273.10739 | AX66: 467.68867 | AZ66: =IFERROR(AVERAGEIFS(D66:AY66,$D$3:$AY$3,"Y",D66:AY66,"<>"),"") -> 288.77379 | BA66: =IFERROR(D66-AZ66,"") -> -77.395107 | BB66: =IFERROR(COUNTIFS(D66:AY66,">"&D66,$D$3:$AY$3,"Y",D66:AY66,"<>")+1,"") -> 5 | BC66: =COUNTIFS($D$3:$AY$3,"Y",D66:AY66,"<>") -> 6
A67: Jamba Juice | B67: Food & Beverage | C67: 6 | D67: 2210.7347 | G67: 623.81429 | H67: 314.90904 | Y67: 252.06629 | AT67: 3092.895 | AV67: 526.89756 | AZ67: =IFERROR(AVERAGEIFS(D67:AY67,$D$3:$AY$3,"Y",D67:AY67,"<>"),"") -> 1170.2195 | BA67: =IFERROR(D67-AZ67,"") -> 1040.5152 | BB67: =IFERROR(COUNTIFS(D67:AY67,">"&D67,$D$3:$AY$3,"Y",D67:AY67,"<>")+1,"") -> 2 | BC67: =COUNTIFS($D$3:$AY$3,"Y",D67:AY67,"<>") -> 6
A68: Pro Image Sports | B68: Apparel | C68: 6 | D68: 352.12131 | G68: 510.32714 | L68: 173.00495 | R68: 424.72917 | V68: 480.45302 | AP68: 215.48856 | AZ68: =IFERROR(AVERAGEIFS(D68:AY68,$D$3:$AY$3,"Y",D68:AY68,"<>"),"") -> 359.35402 | BA68: =IFERROR(D68-AZ68,"") -> -7.2327133 | BB68: =IFERROR(COUNTIFS(D68:AY68,">"&D68,$D$3:$AY$3,"Y",D68:AY68,"<>")+1,"") -> 4 | BC68: =COUNTIFS($D$3:$AY$3,"Y",D68:AY68,"<>") -> 6
A69: Bonchon | B69: Restaurant | C69: 3 | D69: 816.62091 | M69: 1114.2143 | AK69: 427.11894 | AZ69: =IFERROR(AVERAGEIFS(D69:AY69,$D$3:$AY$3,"Y",D69:AY69,"<>"),"") -> 785.98473 | BA69: =IFERROR(D69-AZ69,"") -> 30.636176 | BB69: =IFERROR(COUNTIFS(D69:AY69,">"&D69,$D$3:$AY$3,"Y",D69:AY69,"<>")+1,"") -> 2 | BC69: =COUNTIFS($D$3:$AY$3,"Y",D69:AY69,"<>") -> 3
A70: Kellys Cajun Grill | B70: Food & Beverage | C70: 3 | D70: 1489.2224 | AB70: 1528.5219 | AC70: 954.79151 | AZ70: =IFERROR(AVERAGEIFS(D70:AY70,$D$3:$AY$3,"Y",D70:AY70,"<>"),"") -> 1324.1786 | BA70: =IFERROR(D70-AZ70,"") -> 165.04382 | BB70: =IFERROR(COUNTIFS(D70:AY70,">"&D70,$D$3:$AY$3,"Y",D70:AY70,"<>")+1,"") -> 2 | BC70: =COUNTIFS($D$3:$AY$3,"Y",D70:AY70,"<>") -> 3
A71: Pop Mart | B71: Hobby & Novelty | C71: 3 | D71: 3217.6377 | AL71: 64.017778 | AN71: 1776.5145 | AZ71: =IFERROR(AVERAGEIFS(D71:AY71,$D$3:$AY$3,"Y",D71:AY71,"<>"),"") -> 1686.0567 | BA71: =IFERROR(D71-AZ71,"") -> 1531.5811 | BB71: =IFERROR(COUNTIFS(D71:AY71,">"&D71,$D$3:$AY$3,"Y",D71:AY71,"<>")+1,"") -> 1 | BC71: =COUNTIFS($D$3:$AY$3,"Y",D71:AY71,"<>") -> 3
A72: Sees Candies | B72: Food & Beverage | C72: 3 | D72: 1537.1725 | G72: 708.45043 | U72: 1452.628 | AZ72: =IFERROR(AVERAGEIFS(D72:AY72,$D$3:$AY$3,"Y",D72:AY72,"<>"),"") -> 1232.7503 | BA72: =IFERROR(D72-AZ72,"") -> 304.42219 | BB72: =IFERROR(COUNTIFS(D72:AY72,">"&D72,$D$3:$AY$3,"Y",D72:AY72,"<>")+1,"") -> 1 | BC72: =COUNTIFS($D$3:$AY$3,"Y",D72:AY72,"<>") -> 3
A73: Belle Brows & Beauty | B73: Service | C73: 2 | D73: 309.50455 | AD73: 96.420228 | AZ73: =IFERROR(AVERAGEIFS(D73:AY73,$D$3:$AY$3,"Y",D73:AY73,"<>"),"") -> 202.96239 | BA73: =IFERROR(D73-AZ73,"") -> 106.54216 | BB73: =IFERROR(COUNTIFS(D73:AY73,">"&D73,$D$3:$AY$3,"Y",D73:AY73,"<>")+1,"") -> 1 | BC73: =COUNTIFS($D$3:$AY$3,"Y",D73:AY73,"<>") -> 2
A74: Morgan Jewelers | B74: Jewelry | C74: 2 | D74: 1161.9244 | AP74: 863.30017 | AZ74: =IFERROR(AVERAGEIFS(D74:AY74,$D$3:$AY$3,"Y",D74:AY74,"<>"),"") -> 1012.6123 | BA74: =IFERROR(D74-AZ74,"") -> 149.31213 | BB74: =IFERROR(COUNTIFS(D74:AY74,">"&D74,$D$3:$AY$3,"Y",D74:AY74,"<>")+1,"") -> 1 | BC74: =COUNTIFS($D$3:$AY$3,"Y",D74:AY74,"<>") -> 2
A75: Nori Japan | B75: Food & Beverage | C75: 2 | D75: 1570.3521 | O75: 1356.8321 | AZ75: =IFERROR(AVERAGEIFS(D75:AY75,$D$3:$AY$3,"Y",D75:AY75,"<>"),"") -> 1463.5921 | BA75: =IFERROR(D75-AZ75,"") -> 106.75998 | BB75: =IFERROR(COUNTIFS(D75:AY75,">"&D75,$D$3:$AY$3,"Y",D75:AY75,"<>")+1,"") -> 1 | BC75: =COUNTIFS($D$3:$AY$3,"Y",D75:AY75,"<>") -> 2

Sheet Category Matrix
A1: Category Comparison: Weighted Sales PSF
A2: Category | B2: # Props | C2: Clackamas Town | D2: Annapolis | E2: Annapolis Town | F2: Arden Fair | G2: Belmar | H2: Brandon Exchange | I2: Briarwood | J2: Bridge Street Tow. | K2: Bridgewater Commo. | L2: Capital City | M2: Coastal Grand | N2: CoolSprings Galle. | O2: Crabtree Valley | P2: Cross Creek | Q2: Crossgates | R2: Destiny USA | S2: Fayette | T2: Galleria at Tyler | U2: Hamilton Place | V2: Hanes | W2: Kansas City | X2: LaCenterra at Cin. | Y2: Liberty | Z2: Mall at Partridge. | AA2: Mall at Prince Ge. | AB2: Mall at Wellingto. | AC2: Mall del Norte | AD2: Mayfaire Town | AE2: Mesa | AF2: Oak Park | AG2: Oklahoma City | AH2: Paddock | AI2: Palisades | AJ2: Pearland Town | AK2: Providence Place | AL2: Scottsdale Quarter | AM2: SoNo | AN2: SouthPark (OH) | AO2: Southgate | AP2: Staten Island | AQ2: The Shops At Ever. | AR2: Towson Town | AS2: Tysons Corner | AT2: Walden Galleria | AU2: West County | AV2: West Towne | AW2: Westfarms | AX2: Willow Grove Park | AY2: Set Avg
A3: Include → | C3: ='Property Summary'!B2 -> Y | D3: ='Property Summary'!B3 -> Y | E3: ='Property Summary'!B4 -> Y | F3: ='Property Summary'!B5 -> Y | G3: ='Property Summary'!B6 -> Y | H3: ='Property Summary'!B7 -> Y | I3: ='Property Summary'!B8 -> Y | J3: ='Property Summary'!B9 -> Y | K3: ='Property Summary'!B10 -> Y | L3: ='Property Summary'!B11 -> Y | M3: ='Property Summary'!B12 -> Y | N3: ='Property Summary'!B13 -> Y | O3: ='Property Summary'!B14 -> Y | P3: ='Property Summary'!B15 -> Y | Q3: ='Property Summary'!B16 -> Y | R3: ='Property Summary'!B17 -> Y | S3: ='Property Summary'!B18 -> Y | T3: ='Property Summary'!B19 -> Y | U3: ='Property Summary'!B20 -> Y | V3: ='Property Summary'!B21 -> Y | W3: ='Property Summary'!B22 -> Y | X3: ='Property Summary'!B23 -> Y | Y3: ='Property Summary'!B24 -> Y | Z3: ='Property Summary'!B25 -> Y | AA3: ='Property Summary'!B26 -> Y | AB3: ='Property Summary'!B27 -> Y | AC3: ='Property Summary'!B28 -> Y | AD3: ='Property Summary'!B29 -> Y | AE3: ='Property Summary'!B30 -> Y | AF3: ='Property Summary'!B31 -> Y | AG3: ='Property Summary'!B32 -> Y | AH3: ='Property Summary'!B33 -> Y | AI3: ='Property Summary'!B34 -> Y | AJ3: ='Property Summary'!B35 -> Y | AK3: ='Property Summary'!B36 -> Y | AL3: ='Property Summary'!B37 -> Y | AM3: ='Property Summary'!B38 -> Y | AN3: ='Property Summary'!B39 -> Y | AO3: ='Property Summary'!B40 -> Y | AP3: ='Property Summary'!B41 -> Y | AQ3: ='Property Summary'!B42 -> Y | AR3: ='Property Summary'!B43 -> Y | AS3: ='Property Summary'!B44 -> Y | AT3: ='Property Summary'!B45 -> Y | AU3: ='Property Summary'!B46 -> Y | AV3: ='Property Summary'!B47 -> Y | AW3: ='Property Summary'!B48 -> Y | AX3: ='Property Summary'!B49 -> Y
A4: Apparel | B4: 48 | C4: 394.35609 | D4: 326.7467 | E4: 425.44732 | F4: 521.38038 | G4: 179.49132 | H4: 409.25977 | I4: 24.938699 | J4: 424.38398 | K4: 455.56222 | L4: 347.92987 | M4: 301.59058 | N4: 385.39606 | O4: 533.76429 | P4: 327.14023 | Q4: 414.91147 | R4: 334.38365 | S4: 405.16728 | T4: 318.89235 | U4: 362.99373 | V4: 301.8448 | W4: 513.80396 | X4: 535.17379 | Y4: 235.43554 | Z4: 277.10827 | AA4: 298.45758 | AB4: 261.22758 | AC4: 260.03735 | AD4: 384.60052 | AE4: 344.03692 | AF4: 407.65463 | AG4: 841.37709 | AH4: 366.47859 | AI4: 338.20689 | AJ4: 257.02423 | AK4: 343.8473 | AL4: 846.39327 | AM4: 305.74396 | AN4: 320.6442 | AO4: 358.77209 | AP4: 314.4637 | AQ4: 299.18778 | AR4: 377.55433 | AS4: 669.58306 | AT4: 388.281 | AU4: 548.0924 | AV4: 266.93395 | AW4: 635.24549 | AX4: 408.852 | AY4: =IFERROR(AVERAGEIFS(C4:AX4,$C$3:$AX$3,"Y",C4:AX4,"<>"),"") -> 387.4958
A5: Shoes | B5: 46 | C5: 636.78008 | D5: 344.35097 | F5: 867.25245 | G5: 621.26078 | H5: 784.52577 | I5: 36.379234 | K5: 544.04885 | L5: 498.63427 | M5: 367.36205 | N5: 502.42189 | O5: 757.84936 | P5: 404.71747 | Q5: 522.31914 | R5: 539.56417 | S5: 425.47346 | T5: 639.25003 | U5: 406.90473 | V5: 360.1991 | W5: 351.16128 | X5: 1081.4461 | Y5: 364.05134 | Z5: 400.07242 | AA5: 514.19833 | AB5: 525.90824 | AC5: 639.15979 | AD5: 413.91994 | AE5: 398.82628 | AF5: 503.56823 | AG5: 785.95299 | AH5: 512.61578 | AI5: 548.65865 | AJ5: 413.83101 | AK5: 545.32237 | AL5: 468.91284 | AM5: 417.08039 | AN5: 289.13273 | AO5: 329.74303 | AP5: 521.58206 | AQ5: 597.0474 | AR5: 557.88118 | AS5: 661.0945 | AT5: 523.79283 | AU5: 633.13903 | AV5: 453.66724 | AW5: 690.71591 | AX5: 568.62816 | AY5: =IFERROR(AVERAGEIFS(C5:AX5,$C$3:$AX$3,"Y",C5:AX5,"<>"),"") -> 521.09574
A6: Jewelry | B6: 48 | C6: 1075.6566 | D6: 895.49858 | E6: 610.81733 | F6: 1284.5848 | G6: 343.92182 | H6: 1252.7328 | I6: 58.861142 | J6: 1016.9753 | K6: 933.18869 | L6: 1209.6678 | M6: 1131.6186 | N6: 1075.8662 | O6: 1866.8519 | P6: 1111.0988 | Q6: 1023.2159 | R6: 666.75627 | S6: 1314.8703 | T6: 867.2569 | U6: 1270.6793 | V6: 929.6764 | W6: 824.17594 | X6: 1073.739 | Y6: 694.99153 | Z6: 812.50482 | AA6: 820.1517 | AB6: 1253.8803 | AC6: 1042.6309 | AD6: 1269.2207 | AE6: 975.53769 | AF6: 1600.4487 | AG6: 1072.7688 | AH6: 1354.3483 | AI6: 796.44594 | AJ6: 1003.6058 | AK6: 1057.5246 | AL6: 1941.5609 | AM6: 840.76762 | AN6: 949.32731 | AO6: 853.88396 | AP6: 1354.7605 | AQ6: 572.038 | AR6: 782.5486 | AS6: 1853.8019 | AT6: 833.77725 | AU6: 1076.5048 | AV6: 710.75554 | AW6: 1358.0259 | AX6: 1009.8115 | AY6: =IFERROR(AVERAGEIFS(C6:AX6,$C$3:$AX$3,"Y",C6:AX6,"<>"),"") -> 1036.0278
A7: Health & Beauty | B7: 48 | C7: 1096.7614 | D7: 929.82844 | E7: 703.79791 | F7: 1469.3953 | G7: 244.19095 | H7: 1201.9429 | I7: 80.143703 | J7: 1187.2915 | K7: 968.10826 | L7: 551.79058 | M7: 640.14042 | N7: 989.13544 | O7: 1437.887 | P7: 944.75792 | Q7: 619.46859 | R7: 593.34508 | S7: 681.47386 | T7: 829.67551 | U7: 1022.9278 | V7: 577.02487 | W7: 1011.3275 | X7: 1572.1064 | Y7: 600.08305 | Z7: 817.82933 | AA7: 535.15236 | AB7: 762.46645 | AC7: 544.98671 | AD7: 566.83629 | AE7: 456.40853 | AF7: 697.28893 | AG7: 481.26817 | AH7: 588.77652 | AI7: 645.45709 | AJ7: 353.13903 | AK7: 1113.9027 | AL7: 1601.9845 | AM7: 1182.9898 | AN7: 492.17782 | AO7: 651.54901 | AP7: 988.06522 | AQ7: 530.07338 | AR7: 1115.1951 | AS7: 1748.3704 | AT7: 777.9853 | AU7: 1146.4686 | AV7: 827.02367 | AW7: 1090.6009 | AX7: 917.95286 | AY7: =IFERROR(AVERAGEIFS(C7:AX7,$C$3:$AX$3,"Y",C7:AX7,"<>"),"") -> 845.55319
A8: Food & Beverage | B8: 47 | C8: 893.99749 | D8: 743.65791 | E8: 265.58241 | F8: 829.74931 | G8: 403.0655 | H8: 1070.7666 | I8: 64.995958 | J8: 582.6215 | K8: 1135.5649 | L8: 738.3412 | M8: 709.70259 | N8: 944.93004 | O8: 1581.6585 | P8: 1223.0661 | Q8: 672.7897 | R8: 741.98633 | S8: 991.46584 | T8: 1022.4917 | U8: 1616.3821 | V8: 1144.7081 | W8: 543.49381 | X8: 813.20452 | Y8: 489.27761 | Z8: 573.43421 | AA8: 1138.9329 | AB8: 769.52737 | AC8: 1222.933 | AD8: 878.58874 | AE8: 420.32776 | AF8: 1081.6042 | AG8: 659.98502 | AH8: 840.49721 | AI8: 734.32544 | AJ8: 406.22749 | AK8: 1863.6 | AL8: 534.03856 | AN8: 1172.9587 | AO8: 367.39134 | AP8: 1089.4971 | AQ8: 693.10147 | AR8: 942.24902 | AS8: 1398.552 | AT8: 687.24864 | AU8: 1476.8346 | AV8: 1074.4089 | AW8: 767.33229 | AX8: 2913.5495 | AY8: =IFERROR(AVERAGEIFS(C8:AX8,$C$3:$AX$3,"Y",C8:AX8,"<>"),"") -> 913.41798
A9: Restaurant | B9: 47 | C9: 844.24471 | D9: 979.22908 | E9: 527.84421 | F9: 574.81877 | G9: 462.40485 | H9: 891.73771 | I9: 52.053193 | J9: 719.96825 | K9: 778.49917 | L9: 322.75701 | M9: 607.76946 | N9: 806.28499 | O9: 989.60739 | P9: 721.61329 | Q9: 1684.5247 | R9: 369.18704 | S9: 747.62879 | T9: 745.26249 | U9: 763.08125 | V9: 418.41546 | W9: 857.40173 | X9: 763.0691 | Y9: 667.72367 | Z9: 430.5909 | AA9: 1200.628 | AB9: 1318.5199 | AC9: 702.11102 | AD9: 451.12137 | AE9: 692.02499 | AF9: 705.29094 | AG9: 708.65564 | AH9: 1632.0785 | AI9: 517.59843 | AJ9: 508.4834 | AK9: 862.58846 | AL9: 1343.179 | AN9: 574.94265 | AO9: 409.3548 | AP9: 929.83518 | AQ9: 680.58823 | AR9: 2235.7441 | AS9: 871.09821 | AT9: 484.01909 | AU9: 1034.9057 | AV9: 661.42892 | AW9: 455.25633 | AX9: 775.2753 | AY9: =IFERROR(AVERAGEIFS(C9:AX9,$C$3:$AX$3,"Y",C9:AX9,"<>"),"") -> 776.17969
A10: Hobby & Novelty | B10: 48 | C10: 417.91599 | D10: 537.20183 | E10: 652.41709 | F10: 635.17336 | G10: 156.96853 | H10: 586.80462 | I10: 41.02194 | J10: 119.72811 | K10: 421.86481 | L10: 371.31256 | M10: 312.04255 | N10: 624.74697 | O10: 884.40368 | P10: 423.45536 | Q10: 576.7004 | R10: 469.83522 | S10: 309.04281 | T10: 387.8587 | U10: 313.40428 | V10: 243.75157 | W10: 480.2954 | X10: 764.61322 | Y10: 272.32872 | Z10: 249.80546 | AA10: 355.84182 | AB10: 256.75003 | AC10: 343.20958 | AD10: 414.30366 | AE10: 205.46046 | AF10: 526.17282 | AG10: 523.74957 | AH10: 278.11651 | AI10: 338.45281 | AJ10: 278.18718 | AK10: 635.54777 | AL10: 882.43734 | AM10: 454.95162 | AN10: 285.83916 | AO10: 237.21339 | AP10: 454.23808 | AQ10: 445.60574 | AR10: 310.58272 | AS10: 1191.8197 | AT10: 665.0719 | AU10: 550.38357 | AV10: 263.29756 | AW10: 701.45468 | AX10: 286.23039 | AY10: =IFERROR(AVERAGEIFS(C10:AX10,$C$3:$AX$3,"Y",C10:AX10,"<>"),"") -> 440.3669
A11: Service | B11: 47 | C11: 398.207 | D11: 306.60001 | E11: 434.75699 | F11: 590.28915 | G11: 332.63556 | H11: 571.24956 | I11: 36.661537 | J11: 257.09965 | K11: 693.60948 | L11: 350.62834 | M11: 485.39815 | N11: 557.44046 | O11: 717.42263 | P11: 714.04881 | Q11: 631.92923 | R11: 468.41711 | S11: 552.68464 | T11: 471.48142 | U11: 425.28861 | V11: 782.49979 | W11: 401.84299 | X11: 491.15069 | Y11: 460.81777 | Z11: 450.19516 | AA11: 152.34575 | AB11: 287.92866 | AC11: 251.36408 | AD11: 634.50981 | AE11: 544.7116 | AF11: 522.98448 | AG11: 466.58099 | AH11: 371.98339 | AI11: 408.03323 | AJ11: 288.24383 | AK11: 357.7442 | AL11: 865.3756 | AM11: 388.75481 | AN11: 589.79494 | AO11: 179.56996 | AP11: 481.66336 | AQ11: 672.38706 | AR11: 480.33846 | AS11: 805.28219 | AT11: 429.88877 | AU11: 696.6665 | AV11: 158.86124 | AW11: 487.1663 | AY11: =IFERROR(AVERAGEIFS(C11:AX11,$C$3:$AX$3,"Y",C11:AX11,"<>"),"") -> 470.30923
A12: Tech | B12: 33 | C12: 513.13136 | D12: 1115.1035 | F12: 242.09244 | G12: 1079.399 | H12: 723.48437 | I12: 41.436266 | K12: 729.84211 | L12: 467.14026 | M12: 630.31481 | N12: 909.21714 | O12: 1081.0302 | P12: 1023.0463 | Q12: 388.33927 | R12: 1136.7799 | T12: 458.89214 | U12: 520.37552 | W12: 158.01204 | Y12: 225.58183 | Z12: 65.084306 | AA12: 435.20793 | AB12: 347.40798 | AE12: 204.33169 | AH12: 1189.8272 | AI12: 808.76364 | AK12: 2981.0889 | AO12: 248.64194 | AP12: 1077.6457 | AR12: 899.89779 | AS12: 2350.1286 | AT12: 898.72309 | AU12: 226.03721 | AV12: 181.87042 | AW12: 1791.3082 | AY12: =IFERROR(AVERAGEIFS(C12:AX12,$C$3:$AX$3,"Y",C12:AX12,"<>"),"") -> 762.09645
A13: Major | B13: 28 | C13: 511.38991 | D13: 775.98715 | H13: 1033.0873 | K13: 793.08267 | M13: 1074.7353 | N13: 377.59646 | O13: 1715.1211 | P13: 660.02169 | Q13: 455.72836 | R13: 311.45295 | S13: 851.34112 | U13: 576.36456 | W13: 455.5832 | X13: 930.56045 | Z13: 864.34226 | AA13: 360.1278 | AD13: 804.71708 | AG13: 937.27422 | AI13: 337.69193 | AM13: 328.78378 | AN13: 126.53041 | AP13: 425.15215 | AQ13: 353.77329 | AR13: 1216.216 | AS13: 963.9631 | AT13: 390.0663 | AU13: 1090.6274 | AW13: 2478.55 | AY13: =IFERROR(AVERAGEIFS(C13:AX13,$C$3:$AX$3,"Y",C13:AX13,"<>"),"") -> 757.13814
A14: Anchor | B14: 0 | AY14: =IFERROR(AVERAGEIFS(C14:AX14,$C$3:$AX$3,"Y",C14:AX14,"<>"),"")
A15: Apple | B15: 18 | D15: 4368.0798 | F15: 5847.1034 | H15: 9861.4082 | I15: 455.51601 | J15: 7507.4928 | K15: 5323.5169 | N15: 5650.662 | O15: 5586.537 | R15: 4716.7093 | W15: 6589.9047 | AB15: 6816.3242 | AL15: 5393.7781 | AM15: 4437.0458 | AP15: 8307.9841 | AR15: 6126.0738 | AT15: 4751.1559 | AU15: 5688.83 | AX15: 5040.6558 | AY15: =IFERROR(AVERAGEIFS(C15:AX15,$C$3:$AX$3,"Y",C15:AX15,"<>"),"") -> 5692.7099

Sheet Clackamas Ranking
A1: Clackamas Town Center - Sales PSF Ranking Analysis
A2: Where Clackamas ranks vs. the full comparison set
A4: Total Tenants Ranked | B4: 72
A5: Ranked #1 (Highest Sales PSF) | B5: 9 (12.5%)
A6: Ranked Top 3 | B6: 22 (30.6%)
A7: Ranked Top Half | B7: 38 (52.8%)
A8: Ranked Last | B8: 3 (4.2%)
A11: Tenant | B11: Category | C11: Clackamas PSF | D11: Rank | E11: Of | F11: Best Property | G11: Best PSF | H11: Delta vs Best
A12: Champs Sports | B12: Shoes | C12: 924.2662 | D12: 1 | E12: 33 | F12: Clackamas Town Center | G12: 924.2662 | H12: 0
A13: Sbarro The Italian Eatery | B13: Food & Beverage | C13: 1662.3151 | D13: 1 | E13: 21 | F13: Clackamas Town Center | G13: 1662.3151 | H13: 0
A14: Carters | B14: Apparel | C14: 670.84788 | D14: 1 | E14: 9 | F14: Clackamas Town Center | G14: 670.84788 | H14: 0
A15: Panda Express | B15: Restaurant | C15: 3231.1885 | D15: 1 | E15: 7 | F15: Clackamas Town Center | G15: 3231.1885 | H15: 0
A16: Pop Mart | B16: Hobby & Novelty | C16: 3217.6377 | D16: 1 | E16: 3 | F16: Clackamas Town Center | G16: 3217.6377 | H16: 0
A17: Sees Candies | B17: Food & Beverage | C17: 1537.1725 | D17: 1 | E17: 3 | F17: Clackamas Town Center | G17: 1537.1725 | H17: 0
A18: Belle Brows & Beauty | B18: Service | C18: 309.50455 | D18: 1 | E18: 2 | F18: Clackamas Town Center | G18: 309.50455 | H18: 0
A19: Morgan Jewelers | B19: Jewelry | C19: 1161.9244 | D19: 1 | E19: 2 | F19: Clackamas Town Center | G19: 1161.9244 | H19: 0
A20: Nori Japan | B20: Food & Beverage | C20: 1570.3521 | D20: 1 | E20: 2 | F20: Clackamas Town Center | G20: 1570.3521 | H20: 0
A21: Claire's | B21: Jewelry | C21: 843.66916 | D21: 2 | E21: 42 | F21: Brandon Exchange | G21: 950.3913 | H21: -106.72215
A22: Foot Locker | B22: Shoes | C22: 975.43728 | D22: 2 | E22: 23 | F22: Brandon Exchange | G22: 1088.145 | H22: -112.70773
A23: Coach | B23: Apparel | C23: 1018.9582 | D23: 2 | E23: 11 | F23: Oak Park Mall | G23: 1057.0125 | H23: -38.054261
... A83: Lenscrafters | B83: Service | C83: 447.17792 | D83: 30 | E83: 34 | F83: Bridgewater Commons | G83: 1392.0772 | H83: -944.89927

Sheet _TenantList
A1: Aerie
A2: Aeropostale
A3: Aldo
A4: American Eagle Outfitters
A5: Auntie Annes
A6: BOBA TEA CREW
A7: BRAGANZA PEARL TEA
A8: Banter By Piercing Pagoda
A9: Bath & Body Works
A10: Belle Brows & Beauty
A11: Bonchon
A12: Box Lunch
... A106: Zumiez

Sheet _CatList
A1: Apparel
A2: Food & Beverage
A3: Health & Beauty
A4: Hobby & Novelty
A5: Jewelry
A6: Major
A7: Restaurant
A8: Service
A9: Shoes
A10: Tech

Sheet _CategoryCalc
A1: Property | B1: Apparel_PSF | C1: Shoes_PSF | D1: Jewelry_PSF | E1: Health & Beauty_PSF | F1: Food & Beverage_PSF | G1: Restaurant_PSF | H1: Hobby & Novelty_PSF | I1: Service_PSF | J1: Tech_PSF | K1: Major_PSF | L1: Anchor_PSF | M1: Apple_PSF | N1: Apparel_OCC | O1: Shoes_OCC | P1: Jewelry_OCC | Q1: Health & Beauty_OCC | R1: Food & Beverage_OCC | S1: Restaurant_OCC | T1: Hobby & Novelty_OCC | U1: Service_OCC | V1: Tech_OCC | W1: Major_OCC | X1: Anchor_OCC | Y1: Apple_OCC | Z1: Apparel_SALES | AA1: Shoes_SALES | AB1: Jewelry_SALES | AC1: Health & Beauty_SALES | AD1: Food & Beverage_SALES | AE1: Restaurant_SALES | AF1: Hobby & Novelty_SALES | AG1: Service_SALES | AH1: Tech_SALES | AI1: Major_SALES | AJ1: Anchor_SALES | AK1: Apple_SALES | AL1: Apparel_SQFT | AM1: Shoes_SQFT | AN1: Jewelry_SQFT | AO1: Health & Beauty_SQFT | AP1: Food & Beverage_SQFT | AQ1: Restaurant_SQFT | AR1: Hobby & Novelty_SQFT | AS1: Service_SQFT | AT1: Tech_SQFT | AU1: Major_SQFT | AV1: Anchor_SQFT | AW1: Apple_SQFT | AX1: Enclosed | AY1: Include | AZ1: Total_SQFT
